Workbook

Sheet Dashboard
B1: Airline Flight Analytics - Complete Dashboard
B4: 1. FLIGHT PERFORMANCE
B5: TOTAL FLIGHTS | C5: OPERATED FLIGHTS | D5: ON-TIME FLIGHTS | E5: ON-TIME % (of operated) | F5: AVG DURATION (min) | G5: AVG DISTANCE (KM)
B6: ='Flight Performance'!B6 -> 10000 | C6: ='Flight Performance'!C6 -> 9384 | D6: ='Flight Performance'!D6 -> 1808 | E6: ='Flight Performance'!E6 -> 0.19266837 | F6: ='Flight Performance'!F6 -> 191.20759 | G6: ='Flight Performance'!G6 -> 1371.7468
B25: 2. DELAY ANALYSIS
B26: DELAYED FLIGHTS | C26: DELAY RATE (of operated) | D26: AVG DEP DELAY (min) | E26: AVG ARR DELAY (min) | F26: MAX ARR DELAY (min) | G26: DELAYS OVER 30 MIN
B27: ='Delay Analysis'!B6 -> 7576 | C27: ='Delay Analysis'!C6 -> 0.80733163 | D27: ='Delay Analysis'!D6 -> 16.822677 | E27: ='Delay Analysis'!E6 -> 20.262788 | F27: ='Delay Analysis'!F6 -> 130 | G27: ='Delay Analysis'!G6 -> 2777
B46: 3. CANCELLATION ANALYSIS
B47: CANCELLED FLIGHTS | C47: CANCELLATION RATE | D47: TOP REASON | E47: SEATS AFFECTED | F47: AVG CANCELLED / MONTH | G47: HIGHEST CANCEL-RATE AIRLINE
B48: ='Cancellation Analysis'!B6 -> 616 | C48: ='Cancellation Analysis'!C6 -> 0.0616 | D48: ='Cancellation Analysis'!D6 -> Technical Issue | E48: ='Cancellation Analysis'!E6 -> 113268 | F48: ='Cancellation Analysis'!F6 -> 51.333333 | G48: ='Cancellation Analysis'!G6 -> IndiGo
B67: 4. PASSENGER ANALYTICS
B68: TOTAL PASSENGERS | C68: TOTAL SEATS (operated) | D68: OVERALL LOAD FACTOR | E68: AVG PAX PER FLIGHT | F68: AVG TICKET PRICE (₹) | G68: EMPTY SEATS
B69: ='Passenger Analytics'!B6 -> 1346015 | C69: ='Passenger Analytics'!C6 -> 1730361 | D69: ='Passenger Analytics'!D6 -> 0.77788103 | E69: ='Passenger Analytics'!E6 -> 143.43723 | F69: ='Passenger Analytics'!F6 -> 6895.9763 | G69: ='Passenger Analytics'!G6 -> 384346
B88: 5. ROUTE ANALYTICS
B89: TOP ROUTE (by pax) | C89: TOP ROUTE PASSENGERS | D89: AVG DISTANCE (KM) | E89: LONGEST ROUTE (KM) | F89: SHORTEST ROUTE (KM) | G89: TOP-10 SHARE OF PAX
B90: ='Route Analytics'!B6 -> Ahmedabad - Goa | C90: ='Route Analytics'!C6 -> 19700 | D90: ='Route Analytics'!D6 -> 1371.7468 | E90: ='Route Analytics'!E6 -> 2399 | F90: ='Route Analytics'!F6 -> 350 | G90: ='Route Analytics'!G6 -> 0.13082246
B109: 6. AIRPORT PERFORMANCE
B110: AIRPORTS | C110: TOTAL DEPARTURES | D110: BUSIEST AIRPORT | E110: HIGHEST DELAY RATE | F110: HIGHEST CANCEL RATE | G110: BEST ON-TIME AIRPORT
B111: ='Airport Performance'!B6 -> 10 | C111: ='Airport Performance'!C6 -> 10000 | D111: ='Airport Performance'!D6 -> Pune (PNQ) | E111: ='Airport Performance'!E6 -> Kolkata (CCU) | F111: ='Airport Performance'!F6 -> Delhi (DEL) | G111: ='Airport Performance'!G6 -> Pune (PNQ)
B130: 7. AIRLINE PERFORMANCE
B131: AIRLINES | C131: MOST FLIGHTS | D131: TOP REVENUE | E131: TOP PROFIT | F131: BEST ON-TIME (lowest delay rate) | G131: HIGHEST LOAD FACTOR
B132: ='Airline Performance'!B6 -> 6 | C132: ='Airline Performance'!C6 -> IndiGo | D132: ='Airline Performance'!D6 -> IndiGo | E132: ='Airline Performance'!E6 -> IndiGo | F132: ='Airline Performance'!F6 -> Vistara | G132: ='Airline Performance'!G6 -> Air India
B151: 8. REVENUE DASHBOARD
B152: TOTAL REVENUE | C152: TICKET REVENUE | D152: BAGGAGE REVENUE | E152: ANCILLARY REVENUE | F152: OPERATING COST | G152: NET PROFIT | H152: PROFIT MARGIN
B153: ='Revenue Dashboard'!B6 -> 1036.5107 | C153: ='Revenue Dashboard'!C6 -> 928.80041 | D153: ='Revenue Dashboard'!D6 -> 46.964298 | E153: ='Revenue Dashboard'!E6 -> 60.745986 | F153: ='Revenue Dashboard'!F6 -> 756.63315 | G153: ='Revenue Dashboard'!G6 -> 279.87755 | H153: ='Revenue Dashboard'!H6 -> 0.27001897

Sheet Flight Performance
B1: Flight Performance
B5: TOTAL FLIGHTS | C5: OPERATED FLIGHTS | D5: ON-TIME FLIGHTS | E5: ON-TIME % (of operated) | F5: AVG DURATION (min) | G5: AVG DISTANCE (KM)
B6: =COUNTA(Flight_Data!$A$2:$A$10001) -> 10000 | C6: =COUNTIF(Flight_Data!$R$2:$R$10001,"No") -> 9384 | D6: =COUNTIF(Flight_Data!$Q$2:$Q$10001,"On Time") -> 1808 | E6: =IFERROR(D6/C6,0) -> 0.19266837 | F6: =AVERAGEIFS(Flight_Data!$N$2:$N$10001,Flight_Data!$R$2:$R$10001,"No") -> 191.20759 | G6: =AVERAGE(Flight_Data!$I$2:$I$10001) -> 1371.7468
B41: Flight Status Summary | F41: Monthly Flights | K41: Flights by Origin Region
B42: Flight Status | C42: Flights | D42: % of Total | F42: Month | G42: Total Flights | H42: Operated | I42: Cancelled | K42: Region | L42: Flights | M42: Avg Distance (KM)
B43: On Time | C43: =COUNTIF(Flight_Data!$Q$2:$Q$10001,B43) -> 1808 | D43: =IFERROR(C43/COUNTA(Flight_Data!$A$2:$A$10001),0) -> 0.1808 | F43: Jan | G43: =COUNTIF(Flight_Data!$AJ$2:$AJ$10001,F43) -> 851 | H43: =COUNTIFS(Flight_Data!$AJ$2:$AJ$10001,F43,Flight_Data!$R$2:$R$10001,"No") -> 803 | I43: =G43-H43 -> 48 | K43: East | L43: =COUNTIF(Flight_Data!$AE$2:$AE$10001,K43) -> 938 | M43: =AVERAGEIF(Flight_Data!$AE$2:$AE$10001,K43,Flight_Data!$I$2:$I$10001) -> 1363.8902
B44: Delayed <30 min | C44: =COUNTIF(Flight_Data!$Q$2:$Q$10001,B44) -> 4799 | D44: =IFERROR(C44/COUNTA(Flight_Data!$A$2:$A$10001),0) -> 0.4799 | F44: Feb | G44: =COUNTIF(Flight_Data!$AJ$2:$AJ$10001,F44) -> 753 | H44: =COUNTIFS(Flight_Data!$AJ$2:$AJ$10001,F44,Flight_Data!$R$2:$R$10001,"No") -> 708 | I44: =G44-H44 -> 45 | K44: North | L44: =COUNTIF(Flight_Data!$AE$2:$AE$10001,K44) -> 2024 | M44: =AVERAGEIF(Flight_Data!$AE$2:$AE$10001,K44,Flight_Data!$I$2:$I$10001) -> 1388.504
B45: Delayed 30-120 min | C45: =COUNTIF(Flight_Data!$Q$2:$Q$10001,B45) -> 2774 | D45: =IFERROR(C45/COUNTA(Flight_Data!$A$2:$A$10001),0) -> 0.2774 | F45: Mar | G45: =COUNTIF(Flight_Data!$AJ$2:$AJ$10001,F45) -> 838 | H45: =COUNTIFS(Flight_Data!$AJ$2:$AJ$10001,F45,Flight_Data!$R$2:$R$10001,"No") -> 789 | I45: =G45-H45 -> 49 | K45: South | L45: =COUNTIF(Flight_Data!$AE$2:$AE$10001,K45) -> 2955 | M45: =AVERAGEIF(Flight_Data!$AE$2:$AE$10001,K45,Flight_Data!$I$2:$I$10001) -> 1361.957
B46: Delayed >120 min | C46: =COUNTIF(Flight_Data!$Q$2:$Q$10001,B46) -> 3 | D46: =IFERROR(C46/COUNTA(Flight_Data!$A$2:$A$10001),0) -> 0.0003 | F46: Apr | G46: =COUNTIF(Flight_Data!$AJ$2:$AJ$10001,F46) -> 812 | H46: =COUNTIFS(Flight_Data!$AJ$2:$AJ$10001,F46,Flight_Data!$R$2:$R$10001,"No") -> 753 | I46: =G46-H46 -> 59 | K46: West | L46: =COUNTIF(Flight_Data!$AE$2:$AE$10001,K46) -> 4083 | M46: =AVERAGEIF(Flight_Data!$AE$2:$AE$10001,K46,Flight_Data!$I$2:$I$10001) -> 1372.3301
B47: Cancelled | C47: =COUNTIF(Flight_Data!$Q$2:$Q$10001,B47) -> 616 | D47: =IFERROR(C47/COUNTA(Flight_Data!$A$2:$A$10001),0) -> 0.0616 | F47: May | G47: =COUNTIF(Flight_Data!$AJ$2:$AJ$10001,F47) -> 846 | H47: =COUNTIFS(Flight_Data!$AJ$2:$AJ$10001,F47,Flight_Data!$R$2:$R$10001,"No") -> 798 | I47: =G47-H47 -> 48 | K47: Total | L47: =SUM(L43:L46) -> 10000 | M47: =AVERAGE(Flight_Data!$I$2:$I$10001) -> 1371.7468
B48: Total | C48: =SUM(C43:C47) -> 10000 | D48: =SUM(D43:D47) -> 1 | F48: Jun | G48: =COUNTIF(Flight_Data!$AJ$2:$AJ$10001,F48) -> 829 | H48: =COUNTIFS(Flight_Data!$AJ$2:$AJ$10001,F48,Flight_Data!$R$2:$R$10001,"No") -> 775 | I48: =G48-H48 -> 54
F49: Jul | G49: =COUNTIF(Flight_Data!$AJ$2:$AJ$10001,F49) -> 885 | H49: =COUNTIFS(Flight_Data!$AJ$2:$AJ$10001,F49,Flight_Data!$R$2:$R$10001,"No") -> 837 | I49: =G49-H49 -> 48
F50: Aug | G50: =COUNTIF(Flight_Data!$AJ$2:$AJ$10001,F50) -> 822 | H50: =COUNTIFS(Flight_Data!$AJ$2:$AJ$10001,F50,Flight_Data!$R$2:$R$10001,"No") -> 760 | I50: =G50-H50 -> 62
F51: Sep | G51: =COUNTIF(Flight_Data!$AJ$2:$AJ$10001,F51) -> 808 | H51: =COUNTIFS(Flight_Data!$AJ$2:$AJ$10001,F51,Flight_Data!$R$2:$R$10001,"No") -> 766 | I51: =G51-H51 -> 42
B52: Flights by Airline | F52: Oct | G52: =COUNTIF(Flight_Data!$AJ$2:$AJ$10001,F52) -> 831 | H52: =COUNTIFS(Flight_Data!$AJ$2:$AJ$10001,F52,Flight_Data!$R$2:$R$10001,"No") -> 789 | I52: =G52-H52 -> 42
B53: Airline | C53: Flights | D53: Avg Duration (min) | E53: Avg Distance (KM) | F53: Nov | G53: =COUNTIF(Flight_Data!$AJ$2:$AJ$10001,F53) -> 818 | H53: =COUNTIFS(Flight_Data!$AJ$2:$AJ$10001,F53,Flight_Data!$R$2:$R$10001,"No") -> 762 | I53: =G53-H53 -> 56
B54: IndiGo | C54: =COUNTIF(Flight_Data!$C$2:$C$10001,B54) -> 3206 | D54: =AVERAGEIFS(Flight_Data!$N$2:$N$10001,Flight_Data!$C$2:$C$10001,B54,Flight_Data!$R$2:$R$10001,"No") -> 192.13489 | E54: =AVERAGEIF(Flight_Data!$C$2:$C$10001,B54,Flight_Data!$I$2:$I$10001) -> 1378.0989 | F54: Dec | G54: =COUNTIF(Flight_Data!$AJ$2:$AJ$10001,F54) -> 907 | H54: =COUNTIFS(Flight_Data!$AJ$2:$AJ$10001,F54,Flight_Data!$R$2:$R$10001,"No") -> 844 | I54: =G54-H54 -> 63
B55: Air India | C55: =COUNTIF(Flight_Data!$C$2:$C$10001,B55) -> 1812 | D55: =AVERAGEIFS(Flight_Data!$N$2:$N$10001,Flight_Data!$C$2:$C$10001,B55,Flight_Data!$R$2:$R$10001,"No") -> 188.73135 | E55: =AVERAGEIF(Flight_Data!$C$2:$C$10001,B55,Flight_Data!$I$2:$I$10001) -> 1355.9503 | F55: Total | G55: =SUM(G43:G54) -> 10000 | H55: =SUM(H43:H54) -> 9384 | I55: =SUM(I43:I54) -> 616
B56: Vistara | C56: =COUNTIF(Flight_Data!$C$2:$C$10001,B56) -> 1460 | D56: =AVERAGEIFS(Flight_Data!$N$2:$N$10001,Flight_Data!$C$2:$C$10001,B56,Flight_Data!$R$2:$R$10001,"No") -> 190.91142 | E56: =AVERAGEIF(Flight_Data!$C$2:$C$10001,B56,Flight_Data!$I$2:$I$10001) -> 1362.5486
B57: SpiceJet | C57: =COUNTIF(Flight_Data!$C$2:$C$10001,B57) -> 1321 | D57: =AVERAGEIFS(Flight_Data!$N$2:$N$10001,Flight_Data!$C$2:$C$10001,B57,Flight_Data!$R$2:$R$10001,"No") -> 191.13162 | E57: =AVERAGEIF(Flight_Data!$C$2:$C$10001,B57,Flight_Data!$I$2:$I$10001) -> 1366.2695
B58: Akasa Air | C58: =COUNTIF(Flight_Data!$C$2:$C$10001,B58) -> 1222 | D58: =AVERAGEIFS(Flight_Data!$N$2:$N$10001,Flight_Data!$C$2:$C$10001,B58,Flight_Data!$R$2:$R$10001,"No") -> 190.27408 | E58: =AVERAGEIF(Flight_Data!$C$2:$C$10001,B58,Flight_Data!$I$2:$I$10001) -> 1366.3486
B59: Air India Express | C59: =COUNTIF(Flight_Data!$C$2:$C$10001,B59) -> 979 | D59: =AVERAGEIFS(Flight_Data!$N$2:$N$10001,Flight_Data!$C$2:$C$10001,B59,Flight_Data!$R$2:$R$10001,"No") -> 194.51251 | E59: =AVERAGEIF(Flight_Data!$C$2:$C$10001,B59,Flight_Data!$I$2:$I$10001) -> 1408.0286
B60: Total | C60: =SUM(C54:C59) -> 10000 | D60: =AVERAGEIFS(Flight_Data!$N$2:$N$10001,Flight_Data!$R$2:$R$10001,"No") -> 191.20759 | E60: =AVERAGE(Flight_Data!$I$2:$I$10001) -> 1371.7468

Sheet Delay Analysis
B1: Delay Analysis
B5: DELAYED FLIGHTS | C5: DELAY RATE (of operated) | D5: AVG DEP DELAY (min) | E5: AVG ARR DELAY (min) | F5: MAX ARR DELAY (min) | G5: DELAYS OVER 30 MIN
B6: =COUNTIF(Flight_Data!$Q$2:$Q$10001,"Delayed*") -> 7576 | C6: =IFERROR(B6/COUNTIF(Flight_Data!$R$2:$R$10001,"No"),0) -> 0.80733163 | D6: =AVERAGEIFS(Flight_Data!$O$2:$O$10001,Flight_Data!$R$2:$R$10001,"No") -> 16.822677 | E6: =AVERAGEIFS(Flight_Data!$P$2:$P$10001,Flight_Data!$R$2:$R$10001,"No") -> 20.262788 | F6: =MAX(Flight_Data!$P$2:$P$10001) -> 130 | G6: =COUNTIF(Flight_Data!$Q$2:$Q$10001,"Delayed 30-120 min")+COUNTIF(Flight_Data!$Q$2:$Q$10001,"Delayed >120 min") -> 2777
B41: Delay Category | F41: Monthly Delay Trend
B42: Category | C42: Flights | D42: % of Operated | F42: Month | G42: Avg Dep Delay (min) | H42: Avg Arr Delay (min) | I42: Delayed Flights | J42: Delay Rate
B43: On Time | C43: =COUNTIF(Flight_Data!$Q$2:$Q$10001,B43) -> 1808 | D43: =IFERROR(C43/COUNTIF(Flight_Data!$R$2:$R$10001,"No"),0) -> 0.19266837 | F43: Jan | G43: =IFERROR(AVERAGEIFS(Flight_Data!$O$2:$O$10001,Flight_Data!$AJ$2:$AJ$10001,F43,Flight_Data!$R$2:$R$10001,"No"),0) -> 16.645081 | H43: =IFERROR(AVERAGEIFS(Flight_Data!$P$2:$P$10001,Flight_Data!$AJ$2:$AJ$10001,F43,Flight_Data!$R$2:$R$10001,"No"),0) -> 19.478207 | I43: =COUNTIFS(Flight_Data!$AJ$2:$AJ$10001,F43,Flight_Data!$Q$2:$Q$10001,"Delayed*") -> 648 | J43: =IFERROR(I43/COUNTIFS(Flight_Data!$AJ$2:$AJ$10001,F43,Flight_Data!$R$2:$R$10001,"No"),0) -> 0.80697385
B44: Delayed <30 min | C44: =COUNTIF(Flight_Data!$Q$2:$Q$10001,B44) -> 4799 | D44: =IFERROR(C44/COUNTIF(Flight_Data!$R$2:$R$10001,"No"),0) -> 0.51140239 | F44: Feb | G44: =IFERROR(AVERAGEIFS(Flight_Data!$O$2:$O$10001,Flight_Data!$AJ$2:$AJ$10001,F44,Flight_Data!$R$2:$R$10001,"No"),0) -> 17.628531 | H44: =IFERROR(AVERAGEIFS(Flight_Data!$P$2:$P$10001,Flight_Data!$AJ$2:$AJ$10001,F44,Flight_Data!$R$2:$R$10001,"No"),0) -> 21.686441 | I44: =COUNTIFS(Flight_Data!$AJ$2:$AJ$10001,F44,Flight_Data!$Q$2:$Q$10001,"Delayed*") -> 567 | J44: =IFERROR(I44/COUNTIFS(Flight_Data!$AJ$2:$AJ$10001,F44,Flight_Data!$R$2:$R$10001,"No"),0) -> 0.80084746
B45: Delayed 30-120 min | C45: =COUNTIF(Flight_Data!$Q$2:$Q$10001,B45) -> 2774 | D45: =IFERROR(C45/COUNTIF(Flight_Data!$R$2:$R$10001,"No"),0) -> 0.29560955 | F45: Mar | G45: =IFERROR(AVERAGEIFS(Flight_Data!$O$2:$O$10001,Flight_Data!$AJ$2:$AJ$10001,F45,Flight_Data!$R$2:$R$10001,"No"),0) -> 16.726236 | H45: =IFERROR(AVERAGEIFS(Flight_Data!$P$2:$P$10001,Flight_Data!$AJ$2:$AJ$10001,F45,Flight_Data!$R$2:$R$10001,"No"),0) -> 20.485425 | I45: =COUNTIFS(Flight_Data!$AJ$2:$AJ$10001,F45,Flight_Data!$Q$2:$Q$10001,"Delayed*") -> 650 | J45: =IFERROR(I45/COUNTIFS(Flight_Data!$AJ$2:$AJ$10001,F45,Flight_Data!$R$2:$R$10001,"No"),0) -> 0.82382763
B46: Delayed >120 min | C46: =COUNTIF(Flight_Data!$Q$2:$Q$10001,B46) -> 3 | D46: =IFERROR(C46/COUNTIF(Flight_Data!$R$2:$R$10001,"No"),0) -> 0.00031969309 | F46: Apr | G46: =IFERROR(AVERAGEIFS(Flight_Data!$O$2:$O$10001,Flight_Data!$AJ$2:$AJ$10001,F46,Flight_Data!$R$2:$R$10001,"No"),0) -> 16.108898 | H46: =IFERROR(AVERAGEIFS(Flight_Data!$P$2:$P$10001,Flight_Data!$AJ$2:$AJ$10001,F46,Flight_Data!$R$2:$R$10001,"No"),0) -> 20.069057 | I46: =COUNTIFS(Flight_Data!$AJ$2:$AJ$10001,F46,Flight_Data!$Q$2:$Q$10001,"Delayed*") -> 598 | J46: =IFERROR(I46/COUNTIFS(Flight_Data!$AJ$2:$AJ$10001,F46,Flight_Data!$R$2:$R$10001,"No"),0) -> 0.79415671
B47: Total | C47: =SUM(C43:C46) -> 9384 | D47: =SUM(D43:D46) -> 1 | F47: May | G47: =IFERROR(AVERAGEIFS(Flight_Data!$O$2:$O$10001,Flight_Data!$AJ$2:$AJ$10001,F47,Flight_Data!$R$2:$R$10001,"No"),0) -> 17.307018 | H47: =IFERROR(AVERAGEIFS(Flight_Data!$P$2:$P$10001,Flight_Data!$AJ$2:$AJ$10001,F47,Flight_Data!$R$2:$R$10001,"No"),0) -> 20.194236 | I47: =COUNTIFS(Flight_Data!$AJ$2:$AJ$10001,F47,Flight_Data!$Q$2:$Q$10001,"Delayed*") -> 637 | J47: =IFERROR(I47/COUNTIFS(Flight_Data!$AJ$2:$AJ$10001,F47,Flight_Data!$R$2:$R$10001,"No"),0) -> 0.79824561
F48: Jun | G48: =IFERROR(AVERAGEIFS(Flight_Data!$O$2:$O$10001,Flight_Data!$AJ$2:$AJ$10001,F48,Flight_Data!$R$2:$R$10001,"No"),0) -> 17.189677 | H48: =IFERROR(AVERAGEIFS(Flight_Data!$P$2:$P$10001,Flight_Data!$AJ$2:$AJ$10001,F48,Flight_Data!$R$2:$R$10001,"No"),0) -> 19.277419 | I48: =COUNTIFS(Flight_Data!$AJ$2:$AJ$10001,F48,Flight_Data!$Q$2:$Q$10001,"Delayed*") -> 629 | J48: =IFERROR(I48/COUNTIFS(Flight_Data!$AJ$2:$AJ$10001,F48,Flight_Data!$R$2:$R$10001,"No"),0) -> 0.8116129
F49: Jul | G49: =IFERROR(AVERAGEIFS(Flight_Data!$O$2:$O$10001,Flight_Data!$AJ$2:$AJ$10001,F49,Flight_Data!$R$2:$R$10001,"No"),0) -> 16.046595 | H49: =IFERROR(AVERAGEIFS(Flight_Data!$P$2:$P$10001,Flight_Data!$AJ$2:$AJ$10001,F49,Flight_Data!$R$2:$R$10001,"No"),0) -> 20.017921 | I49: =COUNTIFS(Flight_Data!$AJ$2:$AJ$10001,F49,Flight_Data!$Q$2:$Q$10001,"Delayed*") -> 675 | J49: =IFERROR(I49/COUNTIFS(Flight_Data!$AJ$2:$AJ$10001,F49,Flight_Data!$R$2:$R$10001,"No"),0) -> 0.80645161
F50: Aug | G50: =IFERROR(AVERAGEIFS(Flight_Data!$O$2:$O$10001,Flight_Data!$AJ$2:$AJ$10001,F50,Flight_Data!$R$2:$R$10001,"No"),0) -> 17.807895 | H50: =IFERROR(AVERAGEIFS(Flight_Data!$P$2:$P$10001,Flight_Data!$AJ$2:$AJ$10001,F50,Flight_Data!$R$2:$R$10001,"No"),0) -> 21.834211 | I50: =COUNTIFS(Flight_Data!$AJ$2:$AJ$10001,F50,Flight_Data!$Q$2:$Q$10001,"Delayed*") -> 634 | J50: =IFERROR(I50/COUNTIFS(Flight_Data!$AJ$2:$AJ$10001,F50,Flight_Data!$R$2:$R$10001,"No"),0) -> 0.83421053
F51: Sep | G51: =IFERROR(AVERAGEIFS(Flight_Data!$O$2:$O$10001,Flight_Data!$AJ$2:$AJ$10001,F51,Flight_Data!$R$2:$R$10001,"No"),0) -> 17.018277 | H51: =IFERROR(AVERAGEIFS(Flight_Data!$P$2:$P$10001,Flight_Data!$AJ$2:$AJ$10001,F51,Flight_Data!$R$2:$R$10001,"No"),0) -> 21.032637 | I51: =COUNTIFS(Flight_Data!$AJ$2:$AJ$10001,F51,Flight_Data!$Q$2:$Q$10001,"Delayed*") -> 627 | J51: =IFERROR(I51/COUNTIFS(Flight_Data!$AJ$2:$AJ$10001,F51,Flight_Data!$R$2:$R$10001,"No"),0) -> 0.81853786
F52: Oct | G52: =IFERROR(AVERAGEIFS(Flight_Data!$O$2:$O$10001,Flight_Data!$AJ$2:$AJ$10001,F52,Flight_Data!$R$2:$R$10001,"No"),0) -> 16.6109 | H52: =IFERROR(AVERAGEIFS(Flight_Data!$P$2:$P$10001,Flight_Data!$AJ$2:$AJ$10001,F52,Flight_Data!$R$2:$R$10001,"No"),0) -> 19.579214 | I52: =COUNTIFS(Flight_Data!$AJ$2:$AJ$10001,F52,Flight_Data!$Q$2:$Q$10001,"Delayed*") -> 632 | J52: =IFERROR(I52/COUNTIFS(Flight_Data!$AJ$2:$AJ$10001,F52,Flight_Data!$R$2:$R$10001,"No"),0) -> 0.80101394
F53: Nov | G53: =IFERROR(AVERAGEIFS(Flight_Data!$O$2:$O$10001,Flight_Data!$AJ$2:$AJ$10001,F53,Flight_Data!$R$2:$R$10001,"No"),0) -> 16.918635 | H53: =IFERROR(AVERAGEIFS(Flight_Data!$P$2:$P$10001,Flight_Data!$AJ$2:$AJ$10001,F53,Flight_Data!$R$2:$R$10001,"No"),0) -> 20.135171 | I53: =COUNTIFS(Flight_Data!$AJ$2:$AJ$10001,F53,Flight_Data!$Q$2:$Q$10001,"Delayed*") -> 611 | J53: =IFERROR(I53/COUNTIFS(Flight_Data!$AJ$2:$AJ$10001,F53,Flight_Data!$R$2:$R$10001,"No"),0) -> 0.80183727
F54: Dec | G54: =IFERROR(AVERAGEIFS(Flight_Data!$O$2:$O$10001,Flight_Data!$AJ$2:$AJ$10001,F54,Flight_Data!$R$2:$R$10001,"No"),0) -> 16.063981 | H54: =IFERROR(AVERAGEIFS(Flight_Data!$P$2:$P$10001,Flight_Data!$AJ$2:$AJ$10001,F54,Flight_Data!$R$2:$R$10001,"No"),0) -> 19.632701 | I54: =COUNTIFS(Flight_Data!$AJ$2:$AJ$10001,F54,Flight_Data!$Q$2:$Q$10001,"Delayed*") -> 668 | J54: =IFERROR(I54/COUNTIFS(Flight_Data!$AJ$2:$AJ$10001,F54,Flight_Data!$R$2:$R$10001,"No"),0) -> 0.79146919
F55: Total / Avg | G55: =AVERAGEIFS(Flight_Data!$O$2:$O$10001,Flight_Data!$R$2:$R$10001,"No") -> 16.822677 | H55: =AVERAGEIFS(Flight_Data!$P$2:$P$10001,Flight_Data!$R$2:$R$10001,"No") -> 20.262788 | I55: =SUM(I43:I54) -> 7576 | J55: =IFERROR(I55/COUNTIF(Flight_Data!$R$2:$R$10001,"No"),0) -> 0.80733163
B57: Delay by Airline
B58: Airline | C58: Operated | D58: Delayed | E58: Delay Rate | F58: Avg Dep Delay (min) | G58: Avg Arr Delay (min)
B59: IndiGo | C59: =COUNTIFS(Flight_Data!$C$2:$C$10001,B59,Flight_Data!$R$2:$R$10001,"No") -> 2995 | D59: =COUNTIFS(Flight_Data!$C$2:$C$10001,B59,Flight_Data!$Q$2:$Q$10001,"Delayed*") -> 2451 | E59: =IFERROR(D59/C59,0) -> 0.81836394 | F59: =AVERAGEIFS(Flight_Data!$O$2:$O$10001,Flight_Data!$C$2:$C$10001,B59,Flight_Data!$R$2:$R$10001,"No") -> 16.869449 | G59: =AVERAGEIFS(Flight_Data!$P$2:$P$10001,Flight_Data!$C$2:$C$10001,B59,Flight_Data!$R$2:$R$10001,"No") -> 20.483472
B60: Air India | C60: =COUNTIFS(Flight_Data!$C$2:$C$10001,B60,Flight_Data!$R$2:$R$10001,"No") -> 1716 | D60: =COUNTIFS(Flight_Data!$C$2:$C$10001,B60,Flight_Data!$Q$2:$Q$10001,"Delayed*") -> 1374 | E60: =IFERROR(D60/C60,0) -> 0.8006993 | F60: =AVERAGEIFS(Flight_Data!$O$2:$O$10001,Flight_Data!$C$2:$C$10001,B60,Flight_Data!$R$2:$R$10001,"No") -> 16.69289 | G60: =AVERAGEIFS(Flight_Data!$P$2:$P$10001,Flight_Data!$C$2:$C$10001,B60,Flight_Data!$R$2:$R$10001,"No") -> 19.937063
B61: Vistara | C61: =COUNTIFS(Flight_Data!$C$2:$C$10001,B61,Flight_Data!$R$2:$R$10001,"No") -> 1366 | D61: =COUNTIFS(Flight_Data!$C$2:$C$10001,B61,Flight_Data!$Q$2:$Q$10001,"Delayed*") -> 1085 | E61: =IFERROR(D61/C61,0) -> 0.7942899 | F61: =AVERAGEIFS(Flight_Data!$O$2:$O$10001,Flight_Data!$C$2:$C$10001,B61,Flight_Data!$R$2:$R$10001,"No") -> 17.207906 | G61: =AVERAGEIFS(Flight_Data!$P$2:$P$10001,Flight_Data!$C$2:$C$10001,B61,Flight_Data!$R$2:$R$10001,"No") -> 20.464861
B62: SpiceJet | C62: =COUNTIFS(Flight_Data!$C$2:$C$10001,B62,Flight_Data!$R$2:$R$10001,"No") -> 1246 | D62: =COUNTIFS(Flight_Data!$C$2:$C$10001,B62,Flight_Data!$Q$2:$Q$10001,"Delayed*") -> 990 | E62: =IFERROR(D62/C62,0) -> 0.79454254 | F62: =AVERAGEIFS(Flight_Data!$O$2:$O$10001,Flight_Data!$C$2:$C$10001,B62,Flight_Data!$R$2:$R$10001,"No") -> 16.626806 | G62: =AVERAGEIFS(Flight_Data!$P$2:$P$10001,Flight_Data!$C$2:$C$10001,B62,Flight_Data!$R$2:$R$10001,"No") -> 20.055377
B63: Akasa Air | C63: =COUNTIFS(Flight_Data!$C$2:$C$10001,B63,Flight_Data!$R$2:$R$10001,"No") -> 1142 | D63: =COUNTIFS(Flight_Data!$C$2:$C$10001,B63,Flight_Data!$Q$2:$Q$10001,"Delayed*") -> 940 | E63: =IFERROR(D63/C63,0) -> 0.82311734 | F63: =AVERAGEIFS(Flight_Data!$O$2:$O$10001,Flight_Data!$C$2:$C$10001,B63,Flight_Data!$R$2:$R$10001,"No") -> 16.915061 | G63: =AVERAGEIFS(Flight_Data!$P$2:$P$10001,Flight_Data!$C$2:$C$10001,B63,Flight_Data!$R$2:$R$10001,"No") -> 20.221541
B64: Air India Express | C64: =COUNTIFS(Flight_Data!$C$2:$C$10001,B64,Flight_Data!$R$2:$R$10001,"No") -> 919 | D64: =COUNTIFS(Flight_Data!$C$2:$C$10001,B64,Flight_Data!$Q$2:$Q$10001,"Delayed*") -> 736 | E64: =IFERROR(D64/C64,0) -> 0.80087051 | F64: =AVERAGEIFS(Flight_Data!$O$2:$O$10001,Flight_Data!$C$2:$C$10001,B64,Flight_Data!$R$2:$R$10001,"No") -> 16.490751 | G64: =AVERAGEIFS(Flight_Data!$P$2:$P$10001,Flight_Data!$C$2:$C$10001,B64,Flight_Data!$R$2:$R$10001,"No") -> 20.183896
B65: Total | C65: =SUM(C59:C64) -> 9384 | D65: =SUM(D59:D64) -> 7576 | E65: =IFERROR(D65/C65,0) -> 0.80733163 | F65: =AVERAGEIFS(Flight_Data!$O$2:$O$10001,Flight_Data!$R$2:$R$10001,"No") -> 16.822677 | G65: =AVERAGEIFS(Flight_Data!$P$2:$P$10001,Flight_Data!$R$2:$R$10001,"No") -> 20.262788

Sheet Cancellation Analysis
B1: Cancellation Analysis
B5: CANCELLED FLIGHTS | C5: CANCELLATION RATE | D5: TOP REASON | E5: SEATS AFFECTED | F5: AVG CANCELLED / MONTH | G5: HIGHEST CANCEL-RATE AIRLINE
B6: =COUNTIF(Flight_Data!$R$2:$R$10001,"Yes") -> 616 | C6: =IFERROR(B6/COUNTA(Flight_Data!$A$2:$A$10001),0) -> 0.0616 | D6: =INDEX(B43:B47,MATCH(MAX(C43:C47),C43:C47,0)) -> Technical Issue | E6: =SUMIF(Flight_Data!$R$2:$R$10001,"Yes",Flight_Data!$T$2:$T$10001) -> 113268 | F6: =B6/12 -> 51.333333 | G6: =INDEX(J43:J48,MATCH(MAX(M43:M48),M43:M48,0)) -> IndiGo
B41: Cancellation Reasons | F41: Monthly Cancellations | J41: Cancellation by Airline
B42: Reason | C42: Cancelled Flights | D42: % of Cancellations | F42: Month | G42: Cancelled | H42: Cancel Rate | J42: Airline | K42: Total Flights | L42: Cancelled | M42: Cancel Rate
B43: Technical Issue | C43: =COUNTIF(Flight_Data!$S$2:$S$10001,B43) -> 191 | D43: =IFERROR(C43/COUNTIF(Flight_Data!$R$2:$R$10001,"Yes"),0) -> 0.31006494 | F43: Jan | G43: =COUNTIFS(Flight_Data!$AJ$2:$AJ$10001,F43,Flight_Data!$R$2:$R$10001,"Yes") -> 48 | H43: =IFERROR(G43/COUNTIF(Flight_Data!$AJ$2:$AJ$10001,F43),0) -> 0.05640423 | J43: IndiGo | K43: =COUNTIF(Flight_Data!$C$2:$C$10001,J43) -> 3206 | L43: =COUNTIFS(Flight_Data!$C$2:$C$10001,J43,Flight_Data!$R$2:$R$10001,"Yes") -> 211 | M43: =IFERROR(L43/K43,0) -> 0.065814099
B44: Weather | C44: =COUNTIF(Flight_Data!$S$2:$S$10001,B44) -> 159 | D44: =IFERROR(C44/COUNTIF(Flight_Data!$R$2:$R$10001,"Yes"),0) -> 0.25811688 | F44: Feb | G44: =COUNTIFS(Flight_Data!$AJ$2:$AJ$10001,F44,Flight_Data!$R$2:$R$10001,"Yes") -> 45 | H44: =IFERROR(G44/COUNTIF(Flight_Data!$AJ$2:$AJ$10001,F44),0) -> 0.059760956 | J44: Air India | K44: =COUNTIF(Flight_Data!$C$2:$C$10001,J44) -> 1812 | L44: =COUNTIFS(Flight_Data!$C$2:$C$10001,J44,Flight_Data!$R$2:$R$10001,"Yes") -> 96 | M44: =IFERROR(L44/K44,0) -> 0.052980132
B45: Operational Issue | C45: =COUNTIF(Flight_Data!$S$2:$S$10001,B45) -> 122 | D45: =IFERROR(C45/COUNTIF(Flight_Data!$R$2:$R$10001,"Yes"),0) -> 0.19805195 | F45: Mar | G45: =COUNTIFS(Flight_Data!$AJ$2:$AJ$10001,F45,Flight_Data!$R$2:$R$10001,"Yes") -> 49 | H45: =IFERROR(G45/COUNTIF(Flight_Data!$AJ$2:$AJ$10001,F45),0) -> 0.058472554 | J45: Vistara | K45: =COUNTIF(Flight_Data!$C$2:$C$10001,J45) -> 1460 | L45: =COUNTIFS(Flight_Data!$C$2:$C$10001,J45,Flight_Data!$R$2:$R$10001,"Yes") -> 94 | M45: =IFERROR(L45/K45,0) -> 0.064383562
B46: Crew Shortage | C46: =COUNTIF(Flight_Data!$S$2:$S$10001,B46) -> 84 | D46: =IFERROR(C46/COUNTIF(Flight_Data!$R$2:$R$10001,"Yes"),0) -> 0.13636364 | F46: Apr | G46: =COUNTIFS(Flight_Data!$AJ$2:$AJ$10001,F46,Flight_Data!$R$2:$R$10001,"Yes") -> 59 | H46: =IFERROR(G46/COUNTIF(Flight_Data!$AJ$2:$AJ$10001,F46),0) -> 0.072660099 | J46: SpiceJet | K46: =COUNTIF(Flight_Data!$C$2:$C$10001,J46) -> 1321 | L46: =COUNTIFS(Flight_Data!$C$2:$C$10001,J46,Flight_Data!$R$2:$R$10001,"Yes") -> 75 | M46: =IFERROR(L46/K46,0) -> 0.05677517
B47: Airport Closure | C47: =COUNTIF(Flight_Data!$S$2:$S$10001,B47) -> 60 | D47: =IFERROR(C47/COUNTIF(Flight_Data!$R$2:$R$10001,"Yes"),0) -> 0.097402597 | F47: May | G47: =COUNTIFS(Flight_Data!$AJ$2:$AJ$10001,F47,Flight_Data!$R$2:$R$10001,"Yes") -> 48 | H47: =IFERROR(G47/COUNTIF(Flight_Data!$AJ$2:$AJ$10001,F47),0) -> 0.056737589 | J47: Akasa Air | K47: =COUNTIF(Flight_Data!$C$2:$C$10001,J47) -> 1222 | L47: =COUNTIFS(Flight_Data!$C$2:$C$10001,J47,Flight_Data!$R$2:$R$10001,"Yes") -> 80 | M47: =IFERROR(L47/K47,0) -> 0.065466448
B48: Total | C48: =SUM(C43:C47) -> 616 | D48: =SUM(D43:D47) -> 1 | F48: Jun | G48: =COUNTIFS(Flight_Data!$AJ$2:$AJ$10001,F48,Flight_Data!$R$2:$R$10001,"Yes") -> 54 | H48: =IFERROR(G48/COUNTIF(Flight_Data!$AJ$2:$AJ$10001,F48),0) -> 0.065138721 | J48: Air India Express | K48: =COUNTIF(Flight_Data!$C$2:$C$10001,J48) -> 979 | L48: =COUNTIFS(Flight_Data!$C$2:$C$10001,J48,Flight_Data!$R$2:$R$10001,"Yes") -> 60 | M48: =IFERROR(L48/K48,0) -> 0.061287028
F49: Jul | G49: =COUNTIFS(Flight_Data!$AJ$2:$AJ$10001,F49,Flight_Data!$R$2:$R$10001,"Yes") -> 48 | H49: =IFERROR(G49/COUNTIF(Flight_Data!$AJ$2:$AJ$10001,F49),0) -> 0.054237288 | J49: Total | K49: =SUM(K43:K48) -> 10000 | L49: =SUM(L43:L48) -> 616 | M49: =IFERROR(L49/K49,0) -> 0.0616
F50: Aug | G50: =COUNTIFS(Flight_Data!$AJ$2:$AJ$10001,F50,Flight_Data!$R$2:$R$10001,"Yes") -> 62 | H50: =IFERROR(G50/COUNTIF(Flight_Data!$AJ$2:$AJ$10001,F50),0) -> 0.075425791
F51: Sep | G51: =COUNTIFS(Flight_Data!$AJ$2:$AJ$10001,F51,Flight_Data!$R$2:$R$10001,"Yes") -> 42 | H51: =IFERROR(G51/COUNTIF(Flight_Data!$AJ$2:$AJ$10001,F51),0) -> 0.051980198
B52: Cancellation by Origin Region | F52: Oct | G52: =COUNTIFS(Flight_Data!$AJ$2:$AJ$10001,F52,Flight_Data!$R$2:$R$10001,"Yes") -> 42 | H52: =IFERROR(G52/COUNTIF(Flight_Data!$AJ$2:$AJ$10001,F52),0) -> 0.050541516
B53: Region | C53: Total Flights | D53: Cancelled | E53: Cancel Rate | F53: Nov | G53: =COUNTIFS(Flight_Data!$AJ$2:$AJ$10001,F53,Flight_Data!$R$2:$R$10001,"Yes") -> 56 | H53: =IFERROR(G53/COUNTIF(Flight_Data!$AJ$2:$AJ$10001,F53),0) -> 0.068459658
B54: East | C54: =COUNTIF(Flight_Data!$AE$2:$AE$10001,B54) -> 938 | D54: =COUNTIFS(Flight_Data!$AE$2:$AE$10001,B54,Flight_Data!$R$2:$R$10001,"Yes") -> 56 | E54: =IFERROR(D54/C54,0) -> 0.059701493 | F54: Dec | G54: =COUNTIFS(Flight_Data!$AJ$2:$AJ$10001,F54,Flight_Data!$R$2:$R$10001,"Yes") -> 63 | H54: =IFERROR(G54/COUNTIF(Flight_Data!$AJ$2:$AJ$10001,F54),0) -> 0.069459757
B55: North | C55: =COUNTIF(Flight_Data!$AE$2:$AE$10001,B55) -> 2024 | D55: =COUNTIFS(Flight_Data!$AE$2:$AE$10001,B55,Flight_Data!$R$2:$R$10001,"Yes") -> 126 | E55: =IFERROR(D55/C55,0) -> 0.062252964 | F55: Total | G55: =SUM(G43:G54) -> 616 | H55: =IFERROR(G55/COUNTA(Flight_Data!$A$2:$A$10001),0) -> 0.0616
B56: South | C56: =COUNTIF(Flight_Data!$AE$2:$AE$10001,B56) -> 2955 | D56: =COUNTIFS(Flight_Data!$AE$2:$AE$10001,B56,Flight_Data!$R$2:$R$10001,"Yes") -> 187 | E56: =IFERROR(D56/C56,0) -> 0.063282572
B57: West | C57: =COUNTIF(Flight_Data!$AE$2:$AE$10001,B57) -> 4083 | D57: =COUNTIFS(Flight_Data!$AE$2:$AE$10001,B57,Flight_Data!$R$2:$R$10001,"Yes") -> 247 | E57: =IFERROR(D57/C57,0) -> 0.060494734
B58: Total | C58: =SUM(C54:C57) -> 10000 | D58: =SUM(D54:D57) -> 616 | E58: =IFERROR(D58/C58,0) -> 0.0616

Sheet Passenger Analytics
B1: Passenger Analytics
B5: TOTAL PASSENGERS | C5: TOTAL SEATS (operated) | D5: OVERALL LOAD FACTOR | E5: AVG PAX PER FLIGHT | F5: AVG TICKET PRICE (₹) | G5: EMPTY SEATS
B6: =SUM(Flight_Data!$U$2:$U$10001) -> 1346015 | C6: =SUMIF(Flight_Data!$R$2:$R$10001,"No",Flight_Data!$T$2:$T$10001) -> 1730361 | D6: =IFERROR(B6/C6,0) -> 0.77788103 | E6: =AVERAGEIFS(Flight_Data!$U$2:$U$10001,Flight_Data!$R$2:$R$10001,"No") -> 143.43723 | F6: =AVERAGEIFS(Flight_Data!$X$2:$X$10001,Flight_Data!$R$2:$R$10001,"No") -> 6895.9763 | G6: =C6-B6 -> 384346
B41: Cabin Class Summary | H41: Monthly Passengers
B42: Cabin | C42: Flights | D42: Passengers | E42: Seats | F42: Load Factor | H42: Month | I42: Passengers | J42: Seats | K42: Load Factor
B43: Economy | C43: =COUNTIFS(Flight_Data!$W$2:$W$10001,B43,Flight_Data!$R$2:$R$10001,"No") -> 6830 | D43: =SUMIFS(Flight_Data!$U$2:$U$10001,Flight_Data!$W$2:$W$10001,B43,Flight_Data!$R$2:$R$10001,"No") -> 979298 | E43: =SUMIFS(Flight_Data!$T$2:$T$10001,Flight_Data!$W$2:$W$10001,B43,Flight_Data!$R$2:$R$10001,"No") -> 1259170 | F43: =IFERROR(D43/E43,0) -> 0.77773295 | H43: Jan | I43: =SUMIFS(Flight_Data!$U$2:$U$10001,Flight_Data!$AJ$2:$AJ$10001,H43,Flight_Data!$R$2:$R$10001,"No") -> 113586 | J43: =SUMIFS(Flight_Data!$T$2:$T$10001,Flight_Data!$AJ$2:$AJ$10001,H43,Flight_Data!$R$2:$R$10001,"No") -> 147858 | K43: =IFERROR(I43/J43,0) -> 0.76821004
B44: Business | C44: =COUNTIFS(Flight_Data!$W$2:$W$10001,B44,Flight_Data!$R$2:$R$10001,"No") -> 728 | D44: =SUMIFS(Flight_Data!$U$2:$U$10001,Flight_Data!$W$2:$W$10001,B44,Flight_Data!$R$2:$R$10001,"No") -> 104452 | E44: =SUMIFS(Flight_Data!$T$2:$T$10001,Flight_Data!$W$2:$W$10001,B44,Flight_Data!$R$2:$R$10001,"No") -> 134729 | F44: =IFERROR(D44/E44,0) -> 0.77527481 | H44: Feb | I44: =SUMIFS(Flight_Data!$U$2:$U$10001,Flight_Data!$AJ$2:$AJ$10001,H44,Flight_Data!$R$2:$R$10001,"No") -> 101239 | J44: =SUMIFS(Flight_Data!$T$2:$T$10001,Flight_Data!$AJ$2:$AJ$10001,H44,Flight_Data!$R$2:$R$10001,"No") -> 130240 | K44: =IFERROR(I44/J44,0) -> 0.77732647
B45: Mixed | C45: =COUNTIFS(Flight_Data!$W$2:$W$10001,B45,Flight_Data!$R$2:$R$10001,"No") -> 1826 | D45: =SUMIFS(Flight_Data!$U$2:$U$10001,Flight_Data!$W$2:$W$10001,B45,Flight_Data!$R$2:$R$10001,"No") -> 262265 | E45: =SUMIFS(Flight_Data!$T$2:$T$10001,Flight_Data!$W$2:$W$10001,B45,Flight_Data!$R$2:$R$10001,"No") -> 336462 | F45: =IFERROR(D45/E45,0) -> 0.77947881 | H45: Mar | I45: =SUMIFS(Flight_Data!$U$2:$U$10001,Flight_Data!$AJ$2:$AJ$10001,H45,Flight_Data!$R$2:$R$10001,"No") -> 114048 | J45: =SUMIFS(Flight_Data!$T$2:$T$10001,Flight_Data!$AJ$2:$AJ$10001,H45,Flight_Data!$R$2:$R$10001,"No") -> 145678 | K45: =IFERROR(I45/J45,0) -> 0.7828773
B46: Total | C46: =SUM(C43:C45) -> 9384 | D46: =SUM(D43:D45) -> 1346015 | E46: =SUM(E43:E45) -> 1730361 | F46: =IFERROR(D46/E46,0) -> 0.77788103 | H46: Apr | I46: =SUMIFS(Flight_Data!$U$2:$U$10001,Flight_Data!$AJ$2:$AJ$10001,H46,Flight_Data!$R$2:$R$10001,"No") -> 108012 | J46: =SUMIFS(Flight_Data!$T$2:$T$10001,Flight_Data!$AJ$2:$AJ$10001,H46,Flight_Data!$R$2:$R$10001,"No") -> 139652 | K46: =IFERROR(I46/J46,0) -> 0.77343683
H47: May | I47: =SUMIFS(Flight_Data!$U$2:$U$10001,Flight_Data!$AJ$2:$AJ$10001,H47,Flight_Data!$R$2:$R$10001,"No") -> 113712 | J47: =SUMIFS(Flight_Data!$T$2:$T$10001,Flight_Data!$AJ$2:$AJ$10001,H47,Flight_Data!$R$2:$R$10001,"No") -> 146402 | K47: =IFERROR(I47/J47,0) -> 0.7767107
H48: Jun | I48: =SUMIFS(Flight_Data!$U$2:$U$10001,Flight_Data!$AJ$2:$AJ$10001,H48,Flight_Data!$R$2:$R$10001,"No") -> 110336 | J48: =SUMIFS(Flight_Data!$T$2:$T$10001,Flight_Data!$AJ$2:$AJ$10001,H48,Flight_Data!$R$2:$R$10001,"No") -> 142132 | K48: =IFERROR(I48/J48,0) -> 0.77629246
B49: Demand Level | H49: Jul | I49: =SUMIFS(Flight_Data!$U$2:$U$10001,Flight_Data!$AJ$2:$AJ$10001,H49,Flight_Data!$R$2:$R$10001,"No") -> 119672 | J49: =SUMIFS(Flight_Data!$T$2:$T$10001,Flight_Data!$AJ$2:$AJ$10001,H49,Flight_Data!$R$2:$R$10001,"No") -> 153697 | K49: =IFERROR(I49/J49,0) -> 0.77862287
B50: Demand | C50: Flights | D50: Passengers | E50: Seats | F50: Load Factor | H50: Aug | I50: =SUMIFS(Flight_Data!$U$2:$U$10001,Flight_Data!$AJ$2:$AJ$10001,H50,Flight_Data!$R$2:$R$10001,"No") -> 109343 | J50: =SUMIFS(Flight_Data!$T$2:$T$10001,Flight_Data!$AJ$2:$AJ$10001,H50,Flight_Data!$R$2:$R$10001,"No") -> 139986 | K50: =IFERROR(I50/J50,0) -> 0.78109954
B51: Low | C51: =COUNTIFS(Flight_Data!$AI$2:$AI$10001,B51,Flight_Data!$R$2:$R$10001,"No") -> 2826 | D51: =SUMIFS(Flight_Data!$U$2:$U$10001,Flight_Data!$AI$2:$AI$10001,B51,Flight_Data!$R$2:$R$10001,"No") -> 406582 | E51: =SUMIFS(Flight_Data!$T$2:$T$10001,Flight_Data!$AI$2:$AI$10001,B51,Flight_Data!$R$2:$R$10001,"No") -> 521862 | F51: =IFERROR(D51/E51,0) -> 0.77909869 | H51: Sep | I51: =SUMIFS(Flight_Data!$U$2:$U$10001,Flight_Data!$AJ$2:$AJ$10001,H51,Flight_Data!$R$2:$R$10001,"No") -> 110092 | J51: =SUMIFS(Flight_Data!$T$2:$T$10001,Flight_Data!$AJ$2:$AJ$10001,H51,Flight_Data!$R$2:$R$10001,"No") -> 141514 | K51: =IFERROR(I51/J51,0) -> 0.77795836
B52: Medium | C52: =COUNTIFS(Flight_Data!$AI$2:$AI$10001,B52,Flight_Data!$R$2:$R$10001,"No") -> 4679 | D52: =SUMIFS(Flight_Data!$U$2:$U$10001,Flight_Data!$AI$2:$AI$10001,B52,Flight_Data!$R$2:$R$10001,"No") -> 670650 | E52: =SUMIFS(Flight_Data!$T$2:$T$10001,Flight_Data!$AI$2:$AI$10001,B52,Flight_Data!$R$2:$R$10001,"No") -> 863424 | F52: =IFERROR(D52/E52,0) -> 0.7767331 | H52: Oct | I52: =SUMIFS(Flight_Data!$U$2:$U$10001,Flight_Data!$AJ$2:$AJ$10001,H52,Flight_Data!$R$2:$R$10001,"No") -> 114664 | J52: =SUMIFS(Flight_Data!$T$2:$T$10001,Flight_Data!$AJ$2:$AJ$10001,H52,Flight_Data!$R$2:$R$10001,"No") -> 146809 | K52: =IFERROR(I52/J52,0) -> 0.78104203
B53: High | C53: =COUNTIFS(Flight_Data!$AI$2:$AI$10001,B53,Flight_Data!$R$2:$R$10001,"No") -> 1879 | D53: =SUMIFS(Flight_Data!$U$2:$U$10001,Flight_Data!$AI$2:$AI$10001,B53,Flight_Data!$R$2:$R$10001,"No") -> 268783 | E53: =SUMIFS(Flight_Data!$T$2:$T$10001,Flight_Data!$AI$2:$AI$10001,B53,Flight_Data!$R$2:$R$10001,"No") -> 345075 | F53: =IFERROR(D53/E53,0) -> 0.77891183 | H53: Nov | I53: =SUMIFS(Flight_Data!$U$2:$U$10001,Flight_Data!$AJ$2:$AJ$10001,H53,Flight_Data!$R$2:$R$10001,"No") -> 109135 | J53: =SUMIFS(Flight_Data!$T$2:$T$10001,Flight_Data!$AJ$2:$AJ$10001,H53,Flight_Data!$R$2:$R$10001,"No") -> 141270 | K53: =IFERROR(I53/J53,0) -> 0.77252778
B54: Total | C54: =SUM(C51:C53) -> 9384 | D54: =SUM(D51:D53) -> 1346015 | E54: =SUM(E51:E53) -> 1730361 | F54: =IFERROR(D54/E54,0) -> 0.77788103 | H54: Dec | I54: =SUMIFS(Flight_Data!$U$2:$U$10001,Flight_Data!$AJ$2:$AJ$10001,H54,Flight_Data!$R$2:$R$10001,"No") -> 122176 | J54: =SUMIFS(Flight_Data!$T$2:$T$10001,Flight_Data!$AJ$2:$AJ$10001,H54,Flight_Data!$R$2:$R$10001,"No") -> 155123 | K54: =IFERROR(I54/J54,0) -> 0.78760725
H55: Total | I55: =SUM(I43:I54) -> 1346015 | J55: =SUM(J43:J54) -> 1730361 | K55: =IFERROR(I55/J55,0) -> 0.77788103
B57: Booking Channel
B58: Channel | C58: Passengers | D58: % Share
B59: Online | C59: =SUMIFS(Flight_Data!$U$2:$U$10001,Flight_Data!$AH$2:$AH$10001,B59,Flight_Data!$R$2:$R$10001,"No") -> 744458 | D59: =IFERROR(C59/SUM(Flight_Data!$U$2:$U$10001),0) -> 0.55308299
B60: Travel Agent | C60: =SUMIFS(Flight_Data!$U$2:$U$10001,Flight_Data!$AH$2:$AH$10001,B60,Flight_Data!$R$2:$R$10001,"No") -> 246664 | D60: =IFERROR(C60/SUM(Flight_Data!$U$2:$U$10001),0) -> 0.18325502
B61: Corporate | C61: =SUMIFS(Flight_Data!$U$2:$U$10001,Flight_Data!$AH$2:$AH$10001,B61,Flight_Data!$R$2:$R$10001,"No") -> 222962 | D61: =IFERROR(C61/SUM(Flight_Data!$U$2:$U$10001),0) -> 0.165646
B62: Airport Counter | C62: =SUMIFS(Flight_Data!$U$2:$U$10001,Flight_Data!$AH$2:$AH$10001,B62,Flight_Data!$R$2:$R$10001,"No") -> 131931 | D62: =IFERROR(C62/SUM(Flight_Data!$U$2:$U$10001),0) -> 0.098015995
B63: Total | C63: =SUM(C59:C62) -> 1346015 | D63: =SUM(D59:D62) -> 1

Sheet Route Analytics
B1: Route Analytics
B5: TOP ROUTE (by pax) | C5: TOP ROUTE PASSENGERS | D5: AVG DISTANCE (KM) | E5: LONGEST ROUTE (KM) | F5: SHORTEST ROUTE (KM) | G5: TOP-10 SHARE OF PAX
B6: =INDEX(E27:E36,MATCH(MAX(G27:G36),G27:G36,0)) -> Ahmedabad - Goa | C6: =MAX(G27:G36) -> 19700 | D6: =AVERAGE(Flight_Data!$I$2:$I$10001) -> 1371.7468 | E6: =MAX(Flight_Data!$I$2:$I$10001) -> 2399 | F6: =MIN(Flight_Data!$I$2:$I$10001) -> 350 | G6: =IFERROR(G37/SUM(Flight_Data!$U$2:$U$10001),0) -> 0.13082246
B25: Top 10 Routes (ranked by passengers)
B26: Rank | C26: Origin | D26: Destination | E26: Route | F26: Flights | G26: Passengers | H26: Avg Distance (KM) | I26: Revenue (₹ Cr) | J26: Load Factor
B27: 1 | C27: Ahmedabad | D27: Goa | E27: =C27&" - "&D27 -> Ahmedabad - Goa | F27: =COUNTIFS(Flight_Data!$G$2:$G$10001,C27,Flight_Data!$H$2:$H$10001,D27,Flight_Data!$R$2:$R$10001,"No") -> 139 | G27: =SUMIFS(Flight_Data!$U$2:$U$10001,Flight_Data!$G$2:$G$10001,C27,Flight_Data!$H$2:$H$10001,D27,Flight_Data!$R$2:$R$10001,"No") -> 19700 | H27: =AVERAGEIFS(Flight_Data!$I$2:$I$10001,Flight_Data!$G$2:$G$10001,C27,Flight_Data!$H$2:$H$10001,D27) -> 1408.3904 | I27: =SUMIFS(Flight_Data!$AB$2:$AB$10001,Flight_Data!$G$2:$G$10001,C27,Flight_Data!$H$2:$H$10001,D27)/10000000 -> 15.214373 | J27: =IFERROR(G27/SUMIFS(Flight_Data!$T$2:$T$10001,Flight_Data!$G$2:$G$10001,C27,Flight_Data!$H$2:$H$10001,D27,Flight_Data!$R$2:$R$10001,"No"),0) -> 0.77801035
B28: 2 | C28: Jaipur | D28: Chennai | E28: =C28&" - "&D28 -> Jaipur - Chennai | F28: =COUNTIFS(Flight_Data!$G$2:$G$10001,C28,Flight_Data!$H$2:$H$10001,D28,Flight_Data!$R$2:$R$10001,"No") -> 130 | G28: =SUMIFS(Flight_Data!$U$2:$U$10001,Flight_Data!$G$2:$G$10001,C28,Flight_Data!$H$2:$H$10001,D28,Flight_Data!$R$2:$R$10001,"No") -> 18776 | H28: =AVERAGEIFS(Flight_Data!$I$2:$I$10001,Flight_Data!$G$2:$G$10001,C28,Flight_Data!$H$2:$H$10001,D28) -> 1393.4 | I28: =SUMIFS(Flight_Data!$AB$2:$AB$10001,Flight_Data!$G$2:$G$10001,C28,Flight_Data!$H$2:$H$10001,D28)/10000000 -> 14.769963 | J28: =IFERROR(G28/SUMIFS(Flight_Data!$T$2:$T$10001,Flight_Data!$G$2:$G$10001,C28,Flight_Data!$H$2:$H$10001,D28,Flight_Data!$R$2:$R$10001,"No"),0) -> 0.78870873
B29: 3 | C29: Pune | D29: Mumbai | E29: =C29&" - "&D29 -> Pune - Mumbai | F29: =COUNTIFS(Flight_Data!$G$2:$G$10001,C29,Flight_Data!$H$2:$H$10001,D29,Flight_Data!$R$2:$R$10001,"No") -> 124 | G29: =SUMIFS(Flight_Data!$U$2:$U$10001,Flight_Data!$G$2:$G$10001,C29,Flight_Data!$H$2:$H$10001,D29,Flight_Data!$R$2:$R$10001,"No") -> 17690 | H29: =AVERAGEIFS(Flight_Data!$I$2:$I$10001,Flight_Data!$G$2:$G$10001,C29,Flight_Data!$H$2:$H$10001,D29) -> 1401.7537 | I29: =SUMIFS(Flight_Data!$AB$2:$AB$10001,Flight_Data!$G$2:$G$10001,C29,Flight_Data!$H$2:$H$10001,D29)/10000000 -> 13.409962 | J29: =IFERROR(G29/SUMIFS(Flight_Data!$T$2:$T$10001,Flight_Data!$G$2:$G$10001,C29,Flight_Data!$H$2:$H$10001,D29,Flight_Data!$R$2:$R$10001,"No"),0) -> 0.78350607
B30: 4 | C30: Pune | D30: Bengaluru | E30: =C30&" - "&D30 -> Pune - Bengaluru | F30: =COUNTIFS(Flight_Data!$G$2:$G$10001,C30,Flight_Data!$H$2:$H$10001,D30,Flight_Data!$R$2:$R$10001,"No") -> 122 | G30: =SUMIFS(Flight_Data!$U$2:$U$10001,Flight_Data!$G$2:$G$10001,C30,Flight_Data!$H$2:$H$10001,D30,Flight_Data!$R$2:$R$10001,"No") -> 17347 | H30: =AVERAGEIFS(Flight_Data!$I$2:$I$10001,Flight_Data!$G$2:$G$10001,C30,Flight_Data!$H$2:$H$10001,D30) -> 1374.3101 | I30: =SUMIFS(Flight_Data!$AB$2:$AB$10001,Flight_Data!$G$2:$G$10001,C30,Flight_Data!$H$2:$H$10001,D30)/10000000 -> 12.886634 | J30: =IFERROR(G30/SUMIFS(Flight_Data!$T$2:$T$10001,Flight_Data!$G$2:$G$10001,C30,Flight_Data!$H$2:$H$10001,D30,Flight_Data!$R$2:$R$10001,"No"),0) -> 0.76223745
B31: 5 | C31: Ahmedabad | D31: Jaipur | E31: =C31&" - "&D31 -> Ahmedabad - Jaipur | F31: =COUNTIFS(Flight_Data!$G$2:$G$10001,C31,Flight_Data!$H$2:$H$10001,D31,Flight_Data!$R$2:$R$10001,"No") -> 121 | G31: =SUMIFS(Flight_Data!$U$2:$U$10001,Flight_Data!$G$2:$G$10001,C31,Flight_Data!$H$2:$H$10001,D31,Flight_Data!$R$2:$R$10001,"No") -> 17263 | H31: =AVERAGEIFS(Flight_Data!$I$2:$I$10001,Flight_Data!$G$2:$G$10001,C31,Flight_Data!$H$2:$H$10001,D31) -> 1426.056 | I31: =SUMIFS(Flight_Data!$AB$2:$AB$10001,Flight_Data!$G$2:$G$10001,C31,Flight_Data!$H$2:$H$10001,D31)/10000000 -> 13.42818 | J31: =IFERROR(G31/SUMIFS(Flight_Data!$T$2:$T$10001,Flight_Data!$G$2:$G$10001,C31,Flight_Data!$H$2:$H$10001,D31,Flight_Data!$R$2:$R$10001,"No"),0) -> 0.77139282
B32: 6 | C32: Hyderabad | D32: Pune | E32: =C32&" - "&D32 -> Hyderabad - Pune | F32: =COUNTIFS(Flight_Data!$G$2:$G$10001,C32,Flight_Data!$H$2:$H$10001,D32,Flight_Data!$R$2:$R$10001,"No") -> 119 | G32: =SUMIFS(Flight_Data!$U$2:$U$10001,Flight_Data!$G$2:$G$10001,C32,Flight_Data!$H$2:$H$10001,D32,Flight_Data!$R$2:$R$10001,"No") -> 17153 | H32: =AVERAGEIFS(Flight_Data!$I$2:$I$10001,Flight_Data!$G$2:$G$10001,C32,Flight_Data!$H$2:$H$10001,D32) -> 1360.2778 | I32: =SUMIFS(Flight_Data!$AB$2:$AB$10001,Flight_Data!$G$2:$G$10001,C32,Flight_Data!$H$2:$H$10001,D32)/10000000 -> 12.801141 | J32: =IFERROR(G32/SUMIFS(Flight_Data!$T$2:$T$10001,Flight_Data!$G$2:$G$10001,C32,Flight_Data!$H$2:$H$10001,D32,Flight_Data!$R$2:$R$10001,"No"),0) -> 0.77384282
B33: 7 | C33: Chennai | D33: Bengaluru | E33: =C33&" - "&D33 -> Chennai - Bengaluru | F33: =COUNTIFS(Flight_Data!$G$2:$G$10001,C33,Flight_Data!$H$2:$H$10001,D33,Flight_Data!$R$2:$R$10001,"No") -> 118 | G33: =SUMIFS(Flight_Data!$U$2:$U$10001,Flight_Data!$G$2:$G$10001,C33,Flight_Data!$H$2:$H$10001,D33,Flight_Data!$R$2:$R$10001,"No") -> 17083 | H33: =AVERAGEIFS(Flight_Data!$I$2:$I$10001,Flight_Data!$G$2:$G$10001,C33,Flight_Data!$H$2:$H$10001,D33) -> 1353.7615 | I33: =SUMIFS(Flight_Data!$AB$2:$AB$10001,Flight_Data!$G$2:$G$10001,C33,Flight_Data!$H$2:$H$10001,D33)/10000000 -> 12.991003 | J33: =IFERROR(G33/SUMIFS(Flight_Data!$T$2:$T$10001,Flight_Data!$G$2:$G$10001,C33,Flight_Data!$H$2:$H$10001,D33,Flight_Data!$R$2:$R$10001,"No"),0) -> 0.78222446
B34: 8 | C34: Hyderabad | D34: Delhi | E34: =C34&" - "&D34 -> Hyderabad - Delhi | F34: =COUNTIFS(Flight_Data!$G$2:$G$10001,C34,Flight_Data!$H$2:$H$10001,D34,Flight_Data!$R$2:$R$10001,"No") -> 117 | G34: =SUMIFS(Flight_Data!$U$2:$U$10001,Flight_Data!$G$2:$G$10001,C34,Flight_Data!$H$2:$H$10001,D34,Flight_Data!$R$2:$R$10001,"No") -> 17048 | H34: =AVERAGEIFS(Flight_Data!$I$2:$I$10001,Flight_Data!$G$2:$G$10001,C34,Flight_Data!$H$2:$H$10001,D34) -> 1367.4496 | I34: =SUMIFS(Flight_Data!$AB$2:$AB$10001,Flight_Data!$G$2:$G$10001,C34,Flight_Data!$H$2:$H$10001,D34)/10000000 -> 13.527563 | J34: =IFERROR(G34/SUMIFS(Flight_Data!$T$2:$T$10001,Flight_Data!$G$2:$G$10001,C34,Flight_Data!$H$2:$H$10001,D34,Flight_Data!$R$2:$R$10001,"No"),0) -> 0.78812815
B35: 9 | C35: Ahmedabad | D35: Bengaluru | E35: =C35&" - "&D35 -> Ahmedabad - Bengaluru | F35: =COUNTIFS(Flight_Data!$G$2:$G$10001,C35,Flight_Data!$H$2:$H$10001,D35,Flight_Data!$R$2:$R$10001,"No") -> 116 | G35: =SUMIFS(Flight_Data!$U$2:$U$10001,Flight_Data!$G$2:$G$10001,C35,Flight_Data!$H$2:$H$10001,D35,Flight_Data!$R$2:$R$10001,"No") -> 17044 | H35: =AVERAGEIFS(Flight_Data!$I$2:$I$10001,Flight_Data!$G$2:$G$10001,C35,Flight_Data!$H$2:$H$10001,D35) -> 1360.7851 | I35: =SUMIFS(Flight_Data!$AB$2:$AB$10001,Flight_Data!$G$2:$G$10001,C35,Flight_Data!$H$2:$H$10001,D35)/10000000 -> 13.660535 | J35: =IFERROR(G35/SUMIFS(Flight_Data!$T$2:$T$10001,Flight_Data!$G$2:$G$10001,C35,Flight_Data!$H$2:$H$10001,D35,Flight_Data!$R$2:$R$10001,"No"),0) -> 0.79123532
B36: 10 | C36: Goa | D36: Bengaluru | E36: =C36&" - "&D36 -> Goa - Bengaluru | F36: =COUNTIFS(Flight_Data!$G$2:$G$10001,C36,Flight_Data!$H$2:$H$10001,D36,Flight_Data!$R$2:$R$10001,"No") -> 121 | G36: =SUMIFS(Flight_Data!$U$2:$U$10001,Flight_Data!$G$2:$G$10001,C36,Flight_Data!$H$2:$H$10001,D36,Flight_Data!$R$2:$R$10001,"No") -> 16985 | H36: =AVERAGEIFS(Flight_Data!$I$2:$I$10001,Flight_Data!$G$2:$G$10001,C36,Flight_Data!$H$2:$H$10001,D36) -> 1303.7619 | I36: =SUMIFS(Flight_Data!$AB$2:$AB$10001,Flight_Data!$G$2:$G$10001,C36,Flight_Data!$H$2:$H$10001,D36)/10000000 -> 13.047887 | J36: =IFERROR(G36/SUMIFS(Flight_Data!$T$2:$T$10001,Flight_Data!$G$2:$G$10001,C36,Flight_Data!$H$2:$H$10001,D36,Flight_Data!$R$2:$R$10001,"No"),0) -> 0.75485534
B37: Total | F37: =SUM(F27:F36) -> 1227 | G37: =SUM(G27:G36) -> 176089 | I37: =SUM(I27:I36) -> 135.73724
B40: Route Heatmap – Operated Flights (Origin vs Destination)
B41: Origin \ Dest | C41: Ahmedabad | D41: Bengaluru | E41: Chennai | F41: Delhi | G41: Goa | H41: Hyderabad | I41: Jaipur | J41: Kolkata | K41: Mumbai | L41: Pune
B42: Ahmedabad | C42: =COUNTIFS(Flight_Data!$G$2:$G$10001,$B42,Flight_Data!$H$2:$H$10001,C$41,Flight_Data!$R$2:$R$10001,"No") -> 0 | D42: =COUNTIFS(Flight_Data!$G$2:$G$10001,$B42,Flight_Data!$H$2:$H$10001,D$41,Flight_Data!$R$2:$R$10001,"No") -> 116 | E42: =COUNTIFS(Flight_Data!$G$2:$G$10001,$B42,Flight_Data!$H$2:$H$10001,E$41,Flight_Data!$R$2:$R$10001,"No") -> 99 | F42: =COUNTIFS(Flight_Data!$G$2:$G$10001,$B42,Flight_Data!$H$2:$H$10001,F$41,Flight_Data!$R$2:$R$10001,"No") -> 94 | G42: =COUNTIFS(Flight_Data!$G$2:$G$10001,$B42,Flight_Data!$H$2:$H$10001,G$41,Flight_Data!$R$2:$R$10001,"No") -> 139 | H42: =COUNTIFS(Flight_Data!$G$2:$G$10001,$B42,Flight_Data!$H$2:$H$10001,H$41,Flight_Data!$R$2:$R$10001,"No") -> 90 | I42: =COUNTIFS(Flight_Data!$G$2:$G$10001,$B42,Flight_Data!$H$2:$H$10001,I$41,Flight_Data!$R$2:$R$10001,"No") -> 121 | J42: =COUNTIFS(Flight_Data!$G$2:$G$10001,$B42,Flight_Data!$H$2:$H$10001,J$41,Flight_Data!$R$2:$R$10001,"No") -> 115 | ... L42: =COUNTIFS(Flight_Data!$G$2:$G$10001,$B42,Flight_Data!$H$2:$H$10001,L$41,Flight_Data!$R$2:$R$10001,"No") -> 90
B43: Bengaluru | C43: =COUNTIFS(Flight_Data!$G$2:$G$10001,$B43,Flight_Data!$H$2:$H$10001,C$41,Flight_Data!$R$2:$R$10001,"No") -> 94 | D43: =COUNTIFS(Flight_Data!$G$2:$G$10001,$B43,Flight_Data!$H$2:$H$10001,D$41,Flight_Data!$R$2:$R$10001,"No") -> 0 | E43: =COUNTIFS(Flight_Data!$G$2:$G$10001,$B43,Flight_Data!$H$2:$H$10001,E$41,Flight_Data!$R$2:$R$10001,"No") -> 116 | F43: =COUNTIFS(Flight_Data!$G$2:$G$10001,$B43,Flight_Data!$H$2:$H$10001,F$41,Flight_Data!$R$2:$R$10001,"No") -> 117 | G43: =COUNTIFS(Flight_Data!$G$2:$G$10001,$B43,Flight_Data!$H$2:$H$10001,G$41,Flight_Data!$R$2:$R$10001,"No") -> 100 | H43: =COUNTIFS(Flight_Data!$G$2:$G$10001,$B43,Flight_Data!$H$2:$H$10001,H$41,Flight_Data!$R$2:$R$10001,"No") -> 103 | I43: =COUNTIFS(Flight_Data!$G$2:$G$10001,$B43,Flight_Data!$H$2:$H$10001,I$41,Flight_Data!$R$2:$R$10001,"No") -> 113 | J43: =COUNTIFS(Flight_Data!$G$2:$G$10001,$B43,Flight_Data!$H$2:$H$10001,J$41,Flight_Data!$R$2:$R$10001,"No") -> 98 | ... L43: =COUNTIFS(Flight_Data!$G$2:$G$10001,$B43,Flight_Data!$H$2:$H$10001,L$41,Flight_Data!$R$2:$R$10001,"No") -> 91
B44: Chennai | C44: =COUNTIFS(Flight_Data!$G$2:$G$10001,$B44,Flight_Data!$H$2:$H$10001,C$41,Flight_Data!$R$2:$R$10001,"No") -> 93 | D44: =COUNTIFS(Flight_Data!$G$2:$G$10001,$B44,Flight_Data!$H$2:$H$10001,D$41,Flight_Data!$R$2:$R$10001,"No") -> 118 | E44: =COUNTIFS(Flight_Data!$G$2:$G$10001,$B44,Flight_Data!$H$2:$H$10001,E$41,Flight_Data!$R$2:$R$10001,"No") -> 0 | F44: =COUNTIFS(Flight_Data!$G$2:$G$10001,$B44,Flight_Data!$H$2:$H$10001,F$41,Flight_Data!$R$2:$R$10001,"No") -> 102 | G44: =COUNTIFS(Flight_Data!$G$2:$G$10001,$B44,Flight_Data!$H$2:$H$10001,G$41,Flight_Data!$R$2:$R$10001,"No") -> 96 | H44: =COUNTIFS(Flight_Data!$G$2:$G$10001,$B44,Flight_Data!$H$2:$H$10001,H$41,Flight_Data!$R$2:$R$10001,"No") -> 113 | I44: =COUNTIFS(Flight_Data!$G$2:$G$10001,$B44,Flight_Data!$H$2:$H$10001,I$41,Flight_Data!$R$2:$R$10001,"No") -> 94 | J44: =COUNTIFS(Flight_Data!$G$2:$G$10001,$B44,Flight_Data!$H$2:$H$10001,J$41,Flight_Data!$R$2:$R$10001,"No") -> 108 | ... L44: =COUNTIFS(Flight_Data!$G$2:$G$10001,$B44,Flight_Data!$H$2:$H$10001,L$41,Flight_Data!$R$2:$R$10001,"No") -> 83
B45: Delhi | C45: =COUNTIFS(Flight_Data!$G$2:$G$10001,$B45,Flight_Data!$H$2:$H$10001,C$41,Flight_Data!$R$2:$R$10001,"No") -> 89 | D45: =COUNTIFS(Flight_Data!$G$2:$G$10001,$B45,Flight_Data!$H$2:$H$10001,D$41,Flight_Data!$R$2:$R$10001,"No") -> 103 | E45: =COUNTIFS(Flight_Data!$G$2:$G$10001,$B45,Flight_Data!$H$2:$H$10001,E$41,Flight_Data!$R$2:$R$10001,"No") -> 110 | F45: =COUNTIFS(Flight_Data!$G$2:$G$10001,$B45,Flight_Data!$H$2:$H$10001,F$41,Flight_Data!$R$2:$R$10001,"No") -> 0 | G45: =COUNTIFS(Flight_Data!$G$2:$G$10001,$B45,Flight_Data!$H$2:$H$10001,G$41,Flight_Data!$R$2:$R$10001,"No") -> 118 | H45: =COUNTIFS(Flight_Data!$G$2:$G$10001,$B45,Flight_Data!$H$2:$H$10001,H$41,Flight_Data!$R$2:$R$10001,"No") -> 113 | I45: =COUNTIFS(Flight_Data!$G$2:$G$10001,$B45,Flight_Data!$H$2:$H$10001,I$41,Flight_Data!$R$2:$R$10001,"No") -> 101 | J45: =COUNTIFS(Flight_Data!$G$2:$G$10001,$B45,Flight_Data!$H$2:$H$10001,J$41,Flight_Data!$R$2:$R$10001,"No") -> 104 | ... L45: =COUNTIFS(Flight_Data!$G$2:$G$10001,$B45,Flight_Data!$H$2:$H$10001,L$41,Flight_Data!$R$2:$R$10001,"No") -> 103
B46: Goa | C46: =COUNTIFS(Flight_Data!$G$2:$G$10001,$B46,Flight_Data!$H$2:$H$10001,C$41,Flight_Data!$R$2:$R$10001,"No") -> 104 | D46: =COUNTIFS(Flight_Data!$G$2:$G$10001,$B46,Flight_Data!$H$2:$H$10001,D$41,Flight_Data!$R$2:$R$10001,"No") -> 121 | E46: =COUNTIFS(Flight_Data!$G$2:$G$10001,$B46,Flight_Data!$H$2:$H$10001,E$41,Flight_Data!$R$2:$R$10001,"No") -> 101 | F46: =COUNTIFS(Flight_Data!$G$2:$G$10001,$B46,Flight_Data!$H$2:$H$10001,F$41,Flight_Data!$R$2:$R$10001,"No") -> 103 | G46: =COUNTIFS(Flight_Data!$G$2:$G$10001,$B46,Flight_Data!$H$2:$H$10001,G$41,Flight_Data!$R$2:$R$10001,"No") -> 0 | H46: =COUNTIFS(Flight_Data!$G$2:$G$10001,$B46,Flight_Data!$H$2:$H$10001,H$41,Flight_Data!$R$2:$R$10001,"No") -> 100 | I46: =COUNTIFS(Flight_Data!$G$2:$G$10001,$B46,Flight_Data!$H$2:$H$10001,I$41,Flight_Data!$R$2:$R$10001,"No") -> 84 | J46: =COUNTIFS(Flight_Data!$G$2:$G$10001,$B46,Flight_Data!$H$2:$H$10001,J$41,Flight_Data!$R$2:$R$10001,"No") -> 103 | ... L46: =COUNTIFS(Flight_Data!$G$2:$G$10001,$B46,Flight_Data!$H$2:$H$10001,L$41,Flight_Data!$R$2:$R$10001,"No") -> 107
B47: Hyderabad | C47: =COUNTIFS(Flight_Data!$G$2:$G$10001,$B47,Flight_Data!$H$2:$H$10001,C$41,Flight_Data!$R$2:$R$10001,"No") -> 103 | D47: =COUNTIFS(Flight_Data!$G$2:$G$10001,$B47,Flight_Data!$H$2:$H$10001,D$41,Flight_Data!$R$2:$R$10001,"No") -> 98 | E47: =COUNTIFS(Flight_Data!$G$2:$G$10001,$B47,Flight_Data!$H$2:$H$10001,E$41,Flight_Data!$R$2:$R$10001,"No") -> 95 | F47: =COUNTIFS(Flight_Data!$G$2:$G$10001,$B47,Flight_Data!$H$2:$H$10001,F$41,Flight_Data!$R$2:$R$10001,"No") -> 117 | G47: =COUNTIFS(Flight_Data!$G$2:$G$10001,$B47,Flight_Data!$H$2:$H$10001,G$41,Flight_Data!$R$2:$R$10001,"No") -> 85 | H47: =COUNTIFS(Flight_Data!$G$2:$G$10001,$B47,Flight_Data!$H$2:$H$10001,H$41,Flight_Data!$R$2:$R$10001,"No") -> 0 | I47: =COUNTIFS(Flight_Data!$G$2:$G$10001,$B47,Flight_Data!$H$2:$H$10001,I$41,Flight_Data!$R$2:$R$10001,"No") -> 108 | J47: =COUNTIFS(Flight_Data!$G$2:$G$10001,$B47,Flight_Data!$H$2:$H$10001,J$41,Flight_Data!$R$2:$R$10001,"No") -> 109 | ... L47: =COUNTIFS(Flight_Data!$G$2:$G$10001,$B47,Flight_Data!$H$2:$H$10001,L$41,Flight_Data!$R$2:$R$10001,"No") -> 119
B48: Jaipur | C48: =COUNTIFS(Flight_Data!$G$2:$G$10001,$B48,Flight_Data!$H$2:$H$10001,C$41,Flight_Data!$R$2:$R$10001,"No") -> 90 | D48: =COUNTIFS(Flight_Data!$G$2:$G$10001,$B48,Flight_Data!$H$2:$H$10001,D$41,Flight_Data!$R$2:$R$10001,"No") -> 114 | E48: =COUNTIFS(Flight_Data!$G$2:$G$10001,$B48,Flight_Data!$H$2:$H$10001,E$41,Flight_Data!$R$2:$R$10001,"No") -> 130 | F48: =COUNTIFS(Flight_Data!$G$2:$G$10001,$B48,Flight_Data!$H$2:$H$10001,F$41,Flight_Data!$R$2:$R$10001,"No") -> 111 | G48: =COUNTIFS(Flight_Data!$G$2:$G$10001,$B48,Flight_Data!$H$2:$H$10001,G$41,Flight_Data!$R$2:$R$10001,"No") -> 112 | H48: =COUNTIFS(Flight_Data!$G$2:$G$10001,$B48,Flight_Data!$H$2:$H$10001,H$41,Flight_Data!$R$2:$R$10001,"No") -> 114 | I48: =COUNTIFS(Flight_Data!$G$2:$G$10001,$B48,Flight_Data!$H$2:$H$10001,I$41,Flight_Data!$R$2:$R$10001,"No") -> 0 | J48: =COUNTIFS(Flight_Data!$G$2:$G$10001,$B48,Flight_Data!$H$2:$H$10001,J$41,Flight_Data!$R$2:$R$10001,"No") -> 111 | ... L48: =COUNTIFS(Flight_Data!$G$2:$G$10001,$B48,Flight_Data!$H$2:$H$10001,L$41,Flight_Data!$R$2:$R$10001,"No") -> 104
B49: Kolkata | C49: =COUNTIFS(Flight_Data!$G$2:$G$10001,$B49,Flight_Data!$H$2:$H$10001,C$41,Flight_Data!$R$2:$R$10001,"No") -> 97 | D49: =COUNTIFS(Flight_Data!$G$2:$G$10001,$B49,Flight_Data!$H$2:$H$10001,D$41,Flight_Data!$R$2:$R$10001,"No") -> 99 | E49: =COUNTIFS(Flight_Data!$G$2:$G$10001,$B49,Flight_Data!$H$2:$H$10001,E$41,Flight_Data!$R$2:$R$10001,"No") -> 97 | F49: =COUNTIFS(Flight_Data!$G$2:$G$10001,$B49,Flight_Data!$H$2:$H$10001,F$41,Flight_Data!$R$2:$R$10001,"No") -> 105 | G49: =COUNTIFS(Flight_Data!$G$2:$G$10001,$B49,Flight_Data!$H$2:$H$10001,G$41,Flight_Data!$R$2:$R$10001,"No") -> 112 | H49: =COUNTIFS(Flight_Data!$G$2:$G$10001,$B49,Flight_Data!$H$2:$H$10001,H$41,Flight_Data!$R$2:$R$10001,"No") -> 95 | I49: =COUNTIFS(Flight_Data!$G$2:$G$10001,$B49,Flight_Data!$H$2:$H$10001,I$41,Flight_Data!$R$2:$R$10001,"No") -> 87 | J49: =COUNTIFS(Flight_Data!$G$2:$G$10001,$B49,Flight_Data!$H$2:$H$10001,J$41,Flight_Data!$R$2:$R$10001,"No") -> 0 | ... L49: =COUNTIFS(Flight_Data!$G$2:$G$10001,$B49,Flight_Data!$H$2:$H$10001,L$41,Flight_Data!$R$2:$R$10001,"No") -> 103
B50: Mumbai | C50: =COUNTIFS(Flight_Data!$G$2:$G$10001,$B50,Flight_Data!$H$2:$H$10001,C$41,Flight_Data!$R$2:$R$10001,"No") -> 106 | D50: =COUNTIFS(Flight_Data!$G$2:$G$10001,$B50,Flight_Data!$H$2:$H$10001,D$41,Flight_Data!$R$2:$R$10001,"No") -> 117 | E50: =COUNTIFS(Flight_Data!$G$2:$G$10001,$B50,Flight_Data!$H$2:$H$10001,E$41,Flight_Data!$R$2:$R$10001,"No") -> 94 | F50: =COUNTIFS(Flight_Data!$G$2:$G$10001,$B50,Flight_Data!$H$2:$H$10001,F$41,Flight_Data!$R$2:$R$10001,"No") -> 106 | G50: =COUNTIFS(Flight_Data!$G$2:$G$10001,$B50,Flight_Data!$H$2:$H$10001,G$41,Flight_Data!$R$2:$R$10001,"No") -> 94 | H50: =COUNTIFS(Flight_Data!$G$2:$G$10001,$B50,Flight_Data!$H$2:$H$10001,H$41,Flight_Data!$R$2:$R$10001,"No") -> 120 | I50: =COUNTIFS(Flight_Data!$G$2:$G$10001,$B50,Flight_Data!$H$2:$H$10001,I$41,Flight_Data!$R$2:$R$10001,"No") -> 100 | J50: =COUNTIFS(Flight_Data!$G$2:$G$10001,$B50,Flight_Data!$H$2:$H$10001,J$41,Flight_Data!$R$2:$R$10001,"No") -> 96 | ... L50: =COUNTIFS(Flight_Data!$G$2:$G$10001,$B50,Flight_Data!$H$2:$H$10001,L$41,Flight_Data!$R$2:$R$10001,"No") -> 115
B51: Pune | C51: =COUNTIFS(Flight_Data!$G$2:$G$10001,$B51,Flight_Data!$H$2:$H$10001,C$41,Flight_Data!$R$2:$R$10001,"No") -> 105 | D51: =COUNTIFS(Flight_Data!$G$2:$G$10001,$B51,Flight_Data!$H$2:$H$10001,D$41,Flight_Data!$R$2:$R$10001,"No") -> 122 | E51: =COUNTIFS(Flight_Data!$G$2:$G$10001,$B51,Flight_Data!$H$2:$H$10001,E$41,Flight_Data!$R$2:$R$10001,"No") -> 110 | F51: =COUNTIFS(Flight_Data!$G$2:$G$10001,$B51,Flight_Data!$H$2:$H$10001,F$41,Flight_Data!$R$2:$R$10001,"No") -> 86 | G51: =COUNTIFS(Flight_Data!$G$2:$G$10001,$B51,Flight_Data!$H$2:$H$10001,G$41,Flight_Data!$R$2:$R$10001,"No") -> 106 | H51: =COUNTIFS(Flight_Data!$G$2:$G$10001,$B51,Flight_Data!$H$2:$H$10001,H$41,Flight_Data!$R$2:$R$10001,"No") -> 117 | I51: =COUNTIFS(Flight_Data!$G$2:$G$10001,$B51,Flight_Data!$H$2:$H$10001,I$41,Flight_Data!$R$2:$R$10001,"No") -> 106 | J51: =COUNTIFS(Flight_Data!$G$2:$G$10001,$B51,Flight_Data!$H$2:$H$10001,J$41,Flight_Data!$R$2:$R$10001,"No") -> 114 | ... L51: =COUNTIFS(Flight_Data!$G$2:$G$10001,$B51,Flight_Data!$H$2:$H$10001,L$41,Flight_Data!$R$2:$R$10001,"No") -> 0

Sheet Airport Performance
B1: Airport Performance
B5: AIRPORTS | C5: TOTAL DEPARTURES | D5: BUSIEST AIRPORT | E5: HIGHEST DELAY RATE | F5: HIGHEST CANCEL RATE | G5: BEST ON-TIME AIRPORT
B6: =COUNTA(B43:B52) -> 10 | C6: =COUNTA(Flight_Data!$A$2:$A$10001) -> 10000 | D6: =INDEX(B43:B52,MATCH(MAX(C43:C52),C43:C52,0)) -> Pune (PNQ) | E6: =INDEX(B43:B52,MATCH(MAX(F43:F52),F43:F52,0)) -> Kolkata (CCU) | F6: =INDEX(B43:B52,MATCH(MAX(H43:H52),H43:H52,0)) -> Delhi (DEL) | G6: =INDEX(B43:B52,MATCH(MIN(F43:F52),F43:F52,0)) -> Pune (PNQ)
B41: Airport Summary
B42: Airport | C42: Departures | D42: Arrivals | E42: Delayed | F42: Delay Rate | G42: Cancelled | H42: Cancel Rate | I42: Avg Dep Delay (min) | J42: Passengers
B43: Ahmedabad (AMD) | C43: =COUNTIF(Flight_Data!$E$2:$E$10001,B43) -> 1026 | D43: =COUNTIF(Flight_Data!$F$2:$F$10001,B43) -> 940 | E43: =COUNTIFS(Flight_Data!$E$2:$E$10001,B43,Flight_Data!$Q$2:$Q$10001,"Delayed*") -> 787 | F43: =IFERROR(E43/(C43-G43),0) -> 0.80967078 | G43: =COUNTIFS(Flight_Data!$E$2:$E$10001,B43,Flight_Data!$R$2:$R$10001,"Yes") -> 54 | H43: =IFERROR(G43/C43,0) -> 0.052631579 | I43: =AVERAGEIFS(Flight_Data!$O$2:$O$10001,Flight_Data!$E$2:$E$10001,B43,Flight_Data!$R$2:$R$10001,"No") -> 17.12963 | J43: =SUMIF(Flight_Data!$E$2:$E$10001,B43,Flight_Data!$U$2:$U$10001) -> 140231
B44: Bengaluru (BLR) | C44: =COUNTIF(Flight_Data!$E$2:$E$10001,B44) -> 985 | D44: =COUNTIF(Flight_Data!$F$2:$F$10001,B44) -> 1076 | E44: =COUNTIFS(Flight_Data!$E$2:$E$10001,B44,Flight_Data!$Q$2:$Q$10001,"Delayed*") -> 747 | F44: =IFERROR(E44/(C44-G44),0) -> 0.80409042 | G44: =COUNTIFS(Flight_Data!$E$2:$E$10001,B44,Flight_Data!$R$2:$R$10001,"Yes") -> 56 | H44: =IFERROR(G44/C44,0) -> 0.056852792 | I44: =AVERAGEIFS(Flight_Data!$O$2:$O$10001,Flight_Data!$E$2:$E$10001,B44,Flight_Data!$R$2:$R$10001,"No") -> 17.618945 | J44: =SUMIF(Flight_Data!$E$2:$E$10001,B44,Flight_Data!$U$2:$U$10001) -> 132484
B45: Chennai (MAA) | C45: =COUNTIF(Flight_Data!$E$2:$E$10001,B45) -> 971 | D45: =COUNTIF(Flight_Data!$F$2:$F$10001,B45) -> 1013 | E45: =COUNTIFS(Flight_Data!$E$2:$E$10001,B45,Flight_Data!$Q$2:$Q$10001,"Delayed*") -> 747 | F45: =IFERROR(E45/(C45-G45),0) -> 0.81997805 | G45: =COUNTIFS(Flight_Data!$E$2:$E$10001,B45,Flight_Data!$R$2:$R$10001,"Yes") -> 60 | H45: =IFERROR(G45/C45,0) -> 0.061791967 | I45: =AVERAGEIFS(Flight_Data!$O$2:$O$10001,Flight_Data!$E$2:$E$10001,B45,Flight_Data!$R$2:$R$10001,"No") -> 17.498353 | J45: =SUMIF(Flight_Data!$E$2:$E$10001,B45,Flight_Data!$U$2:$U$10001) -> 130643
B46: Delhi (DEL) | C46: =COUNTIF(Flight_Data!$E$2:$E$10001,B46) -> 1001 | D46: =COUNTIF(Flight_Data!$F$2:$F$10001,B46) -> 1004 | E46: =COUNTIFS(Flight_Data!$E$2:$E$10001,B46,Flight_Data!$Q$2:$Q$10001,"Delayed*") -> 749 | F46: =IFERROR(E46/(C46-G46),0) -> 0.80885529 | G46: =COUNTIFS(Flight_Data!$E$2:$E$10001,B46,Flight_Data!$R$2:$R$10001,"Yes") -> 75 | H46: =IFERROR(G46/C46,0) -> 0.074925075 | I46: =AVERAGEIFS(Flight_Data!$O$2:$O$10001,Flight_Data!$E$2:$E$10001,B46,Flight_Data!$R$2:$R$10001,"No") -> 16.448164 | J46: =SUMIF(Flight_Data!$E$2:$E$10001,B46,Flight_Data!$U$2:$U$10001) -> 133492
B47: Goa (GOI) | C47: =COUNTIF(Flight_Data!$E$2:$E$10001,B47) -> 985 | D47: =COUNTIF(Flight_Data!$F$2:$F$10001,B47) -> 1018 | E47: =COUNTIFS(Flight_Data!$E$2:$E$10001,B47,Flight_Data!$Q$2:$Q$10001,"Delayed*") -> 739 | F47: =IFERROR(E47/(C47-G47),0) -> 0.79805616 | G47: =COUNTIFS(Flight_Data!$E$2:$E$10001,B47,Flight_Data!$R$2:$R$10001,"Yes") -> 59 | H47: =IFERROR(G47/C47,0) -> 0.059898477 | I47: =AVERAGEIFS(Flight_Data!$O$2:$O$10001,Flight_Data!$E$2:$E$10001,B47,Flight_Data!$R$2:$R$10001,"No") -> 16.408207 | J47: =SUMIF(Flight_Data!$E$2:$E$10001,B47,Flight_Data!$U$2:$U$10001) -> 131467
B48: Hyderabad (HYD) | C48: =COUNTIF(Flight_Data!$E$2:$E$10001,B48) -> 999 | D48: =COUNTIF(Flight_Data!$F$2:$F$10001,B48) -> 1021 | E48: =COUNTIFS(Flight_Data!$E$2:$E$10001,B48,Flight_Data!$Q$2:$Q$10001,"Delayed*") -> 741 | F48: =IFERROR(E48/(C48-G48),0) -> 0.79849138 | G48: =COUNTIFS(Flight_Data!$E$2:$E$10001,B48,Flight_Data!$R$2:$R$10001,"Yes") -> 71 | H48: =IFERROR(G48/C48,0) -> 0.071071071 | I48: =AVERAGEIFS(Flight_Data!$O$2:$O$10001,Flight_Data!$E$2:$E$10001,B48,Flight_Data!$R$2:$R$10001,"No") -> 17.241379 | J48: =SUMIF(Flight_Data!$E$2:$E$10001,B48,Flight_Data!$U$2:$U$10001) -> 134451
B49: Jaipur (JAI) | C49: =COUNTIF(Flight_Data!$E$2:$E$10001,B49) -> 1023 | D49: =COUNTIF(Flight_Data!$F$2:$F$10001,B49) -> 973 | E49: =COUNTIFS(Flight_Data!$E$2:$E$10001,B49,Flight_Data!$Q$2:$Q$10001,"Delayed*") -> 788 | F49: =IFERROR(E49/(C49-G49),0) -> 0.81069959 | G49: =COUNTIFS(Flight_Data!$E$2:$E$10001,B49,Flight_Data!$R$2:$R$10001,"Yes") -> 51 | H49: =IFERROR(G49/C49,0) -> 0.049853372 | I49: =AVERAGEIFS(Flight_Data!$O$2:$O$10001,Flight_Data!$E$2:$E$10001,B49,Flight_Data!$R$2:$R$10001,"No") -> 17.083333 | J49: =SUMIF(Flight_Data!$E$2:$E$10001,B49,Flight_Data!$U$2:$U$10001) -> 139756
B50: Kolkata (CCU) | C50: =COUNTIF(Flight_Data!$E$2:$E$10001,B50) -> 938 | D50: =COUNTIF(Flight_Data!$F$2:$F$10001,B50) -> 1018 | E50: =COUNTIFS(Flight_Data!$E$2:$E$10001,B50,Flight_Data!$Q$2:$Q$10001,"Delayed*") -> 725 | F50: =IFERROR(E50/(C50-G50),0) -> 0.82199546 | G50: =COUNTIFS(Flight_Data!$E$2:$E$10001,B50,Flight_Data!$R$2:$R$10001,"Yes") -> 56 | H50: =IFERROR(G50/C50,0) -> 0.059701493 | I50: =AVERAGEIFS(Flight_Data!$O$2:$O$10001,Flight_Data!$E$2:$E$10001,B50,Flight_Data!$R$2:$R$10001,"No") -> 16.165533 | J50: =SUMIF(Flight_Data!$E$2:$E$10001,B50,Flight_Data!$U$2:$U$10001) -> 126447
B51: Mumbai (BOM) | C51: =COUNTIF(Flight_Data!$E$2:$E$10001,B51) -> 1022 | D51: =COUNTIF(Flight_Data!$F$2:$F$10001,B51) -> 958 | E51: =COUNTIFS(Flight_Data!$E$2:$E$10001,B51,Flight_Data!$Q$2:$Q$10001,"Delayed*") -> 775 | F51: =IFERROR(E51/(C51-G51),0) -> 0.81751055 | G51: =COUNTIFS(Flight_Data!$E$2:$E$10001,B51,Flight_Data!$R$2:$R$10001,"Yes") -> 74 | H51: =IFERROR(G51/C51,0) -> 0.072407045 | I51: =AVERAGEIFS(Flight_Data!$O$2:$O$10001,Flight_Data!$E$2:$E$10001,B51,Flight_Data!$R$2:$R$10001,"No") -> 16.753165 | J51: =SUMIF(Flight_Data!$E$2:$E$10001,B51,Flight_Data!$U$2:$U$10001) -> 135846
B52: Pune (PNQ) | C52: =COUNTIF(Flight_Data!$E$2:$E$10001,B52) -> 1050 | D52: =COUNTIF(Flight_Data!$F$2:$F$10001,B52) -> 979 | E52: =COUNTIFS(Flight_Data!$E$2:$E$10001,B52,Flight_Data!$Q$2:$Q$10001,"Delayed*") -> 778 | F52: =IFERROR(E52/(C52-G52),0) -> 0.78585859 | G52: =COUNTIFS(Flight_Data!$E$2:$E$10001,B52,Flight_Data!$R$2:$R$10001,"Yes") -> 60 | H52: =IFERROR(G52/C52,0) -> 0.057142857 | I52: =AVERAGEIFS(Flight_Data!$O$2:$O$10001,Flight_Data!$E$2:$E$10001,B52,Flight_Data!$R$2:$R$10001,"No") -> 15.893939 | J52: =SUMIF(Flight_Data!$E$2:$E$10001,B52,Flight_Data!$U$2:$U$10001) -> 141198
B53: Total | C53: =SUM(C43:C52) -> 10000 | D53: =SUM(D43:D52) -> 10000 | E53: =SUM(E43:E52) -> 7576 | F53: =IFERROR(E53/(C53-G53),0) -> 0.80733163 | G53: =SUM(G43:G52) -> 616 | H53: =IFERROR(G53/C53,0) -> 0.0616 | I53: =AVERAGEIFS(Flight_Data!$O$2:$O$10001,Flight_Data!$R$2:$R$10001,"No") -> 16.822677 | J53: =SUM(J43:J52) -> 1346015
B57: Region Summary (origin)
B58: Region | C58: Departures | D58: Delay Rate | E58: Cancel Rate | F58: Passengers
B59: East | C59: =COUNTIF(Flight_Data!$AE$2:$AE$10001,B59) -> 938 | D59: =IFERROR(COUNTIFS(Flight_Data!$AE$2:$AE$10001,B59,Flight_Data!$Q$2:$Q$10001,"Delayed*")/COUNTIFS(Flight_Data!$AE$2:$AE$10001,B59,Flight_Data!$R$2:$R$10001,"No"),0) -> 0.82199546 | E59: =IFERROR(COUNTIFS(Flight_Data!$AE$2:$AE$10001,B59,Flight_Data!$R$2:$R$10001,"Yes")/C59,0) -> 0.059701493 | F59: =SUMIF(Flight_Data!$AE$2:$AE$10001,B59,Flight_Data!$U$2:$U$10001) -> 126447
B60: North | C60: =COUNTIF(Flight_Data!$AE$2:$AE$10001,B60) -> 2024 | D60: =IFERROR(COUNTIFS(Flight_Data!$AE$2:$AE$10001,B60,Flight_Data!$Q$2:$Q$10001,"Delayed*")/COUNTIFS(Flight_Data!$AE$2:$AE$10001,B60,Flight_Data!$R$2:$R$10001,"No"),0) -> 0.80979979 | E60: =IFERROR(COUNTIFS(Flight_Data!$AE$2:$AE$10001,B60,Flight_Data!$R$2:$R$10001,"Yes")/C60,0) -> 0.062252964 | F60: =SUMIF(Flight_Data!$AE$2:$AE$10001,B60,Flight_Data!$U$2:$U$10001) -> 273248
B61: South | C61: =COUNTIF(Flight_Data!$AE$2:$AE$10001,B61) -> 2955 | D61: =IFERROR(COUNTIFS(Flight_Data!$AE$2:$AE$10001,B61,Flight_Data!$Q$2:$Q$10001,"Delayed*")/COUNTIFS(Flight_Data!$AE$2:$AE$10001,B61,Flight_Data!$R$2:$R$10001,"No"),0) -> 0.8074422 | E61: =IFERROR(COUNTIFS(Flight_Data!$AE$2:$AE$10001,B61,Flight_Data!$R$2:$R$10001,"Yes")/C61,0) -> 0.063282572 | F61: =SUMIF(Flight_Data!$AE$2:$AE$10001,B61,Flight_Data!$U$2:$U$10001) -> 397578
B62: West | C62: =COUNTIF(Flight_Data!$AE$2:$AE$10001,B62) -> 4083 | D62: =IFERROR(COUNTIFS(Flight_Data!$AE$2:$AE$10001,B62,Flight_Data!$Q$2:$Q$10001,"Delayed*")/COUNTIFS(Flight_Data!$AE$2:$AE$10001,B62,Flight_Data!$R$2:$R$10001,"No"),0) -> 0.80265902 | E62: =IFERROR(COUNTIFS(Flight_Data!$AE$2:$AE$10001,B62,Flight_Data!$R$2:$R$10001,"Yes")/C62,0) -> 0.060494734 | F62: =SUMIF(Flight_Data!$AE$2:$AE$10001,B62,Flight_Data!$U$2:$U$10001) -> 548742

Sheet Airline Performance
B1: Airline Performance
B5: AIRLINES | C5: MOST FLIGHTS | D5: TOP REVENUE | E5: TOP PROFIT | F5: BEST ON-TIME (lowest delay rate) | G5: HIGHEST LOAD FACTOR
B6: =COUNTA(B43:B48) -> 6 | C6: =INDEX(B43:B48,MATCH(MAX(C43:C48),C43:C48,0)) -> IndiGo | D6: =INDEX(B43:B48,MATCH(MAX(K43:K48),K43:K48,0)) -> IndiGo | E6: =INDEX(B43:B48,MATCH(MAX(L43:L48),L43:L48,0)) -> IndiGo | F6: =INDEX(B43:B48,MATCH(MIN(F43:F48),F43:F48,0)) -> Vistara | G6: =INDEX(B43:B48,MATCH(MAX(J43:J48),J43:J48,0)) -> Air India
B41: Airline Scorecard
B42: Airline | C42: Flights | D42: Operated | E42: Delayed | F42: Delay Rate | G42: Cancelled | H42: Cancel Rate | I42: Passengers | J42: Load Factor | K42: Revenue (₹ Cr) | L42: Profit (₹ Cr) | M42: Profit Margin
B43: IndiGo | C43: =COUNTIF(Flight_Data!$C$2:$C$10001,B43) -> 3206 | D43: =COUNTIFS(Flight_Data!$C$2:$C$10001,B43,Flight_Data!$R$2:$R$10001,"No") -> 2995 | E43: =COUNTIFS(Flight_Data!$C$2:$C$10001,B43,Flight_Data!$Q$2:$Q$10001,"Delayed*") -> 2451 | F43: =IFERROR(E43/D43,0) -> 0.81836394 | G43: =COUNTIFS(Flight_Data!$C$2:$C$10001,B43,Flight_Data!$R$2:$R$10001,"Yes") -> 211 | H43: =IFERROR(G43/C43,0) -> 0.065814099 | I43: =SUMIF(Flight_Data!$C$2:$C$10001,B43,Flight_Data!$U$2:$U$10001) -> 429346 | J43: =IFERROR(I43/SUMIFS(Flight_Data!$T$2:$T$10001,Flight_Data!$C$2:$C$10001,B43,Flight_Data!$R$2:$R$10001,"No"),0) -> 0.77807136 | K43: =SUMIF(Flight_Data!$C$2:$C$10001,B43,Flight_Data!$AB$2:$AB$10001)/10000000 -> 331.79649 | L43: =SUMIF(Flight_Data!$C$2:$C$10001,B43,Flight_Data!$AD$2:$AD$10001)/10000000 -> 89.959682 | M43: =IFERROR(L43/K43,0) -> 0.27112909
B44: Air India | C44: =COUNTIF(Flight_Data!$C$2:$C$10001,B44) -> 1812 | D44: =COUNTIFS(Flight_Data!$C$2:$C$10001,B44,Flight_Data!$R$2:$R$10001,"No") -> 1716 | E44: =COUNTIFS(Flight_Data!$C$2:$C$10001,B44,Flight_Data!$Q$2:$Q$10001,"Delayed*") -> 1374 | F44: =IFERROR(E44/D44,0) -> 0.8006993 | G44: =COUNTIFS(Flight_Data!$C$2:$C$10001,B44,Flight_Data!$R$2:$R$10001,"Yes") -> 96 | H44: =IFERROR(G44/C44,0) -> 0.052980132 | I44: =SUMIF(Flight_Data!$C$2:$C$10001,B44,Flight_Data!$U$2:$U$10001) -> 246118 | J44: =IFERROR(I44/SUMIFS(Flight_Data!$T$2:$T$10001,Flight_Data!$C$2:$C$10001,B44,Flight_Data!$R$2:$R$10001,"No"),0) -> 0.78033856 | K44: =SUMIF(Flight_Data!$C$2:$C$10001,B44,Flight_Data!$AB$2:$AB$10001)/10000000 -> 190.352 | L44: =SUMIF(Flight_Data!$C$2:$C$10001,B44,Flight_Data!$AD$2:$AD$10001)/10000000 -> 51.709169 | M44: =IFERROR(L44/K44,0) -> 0.27165026
B45: Vistara | C45: =COUNTIF(Flight_Data!$C$2:$C$10001,B45) -> 1460 | D45: =COUNTIFS(Flight_Data!$C$2:$C$10001,B45,Flight_Data!$R$2:$R$10001,"No") -> 1366 | E45: =COUNTIFS(Flight_Data!$C$2:$C$10001,B45,Flight_Data!$Q$2:$Q$10001,"Delayed*") -> 1085 | F45: =IFERROR(E45/D45,0) -> 0.7942899 | G45: =COUNTIFS(Flight_Data!$C$2:$C$10001,B45,Flight_Data!$R$2:$R$10001,"Yes") -> 94 | H45: =IFERROR(G45/C45,0) -> 0.064383562 | I45: =SUMIF(Flight_Data!$C$2:$C$10001,B45,Flight_Data!$U$2:$U$10001) -> 195348 | J45: =IFERROR(I45/SUMIFS(Flight_Data!$T$2:$T$10001,Flight_Data!$C$2:$C$10001,B45,Flight_Data!$R$2:$R$10001,"No"),0) -> 0.77601576 | K45: =SUMIF(Flight_Data!$C$2:$C$10001,B45,Flight_Data!$AB$2:$AB$10001)/10000000 -> 150.1106 | L45: =SUMIF(Flight_Data!$C$2:$C$10001,B45,Flight_Data!$AD$2:$AD$10001)/10000000 -> 40.641004 | M45: =IFERROR(L45/K45,0) -> 0.27074039
B46: SpiceJet | C46: =COUNTIF(Flight_Data!$C$2:$C$10001,B46) -> 1321 | D46: =COUNTIFS(Flight_Data!$C$2:$C$10001,B46,Flight_Data!$R$2:$R$10001,"No") -> 1246 | E46: =COUNTIFS(Flight_Data!$C$2:$C$10001,B46,Flight_Data!$Q$2:$Q$10001,"Delayed*") -> 990 | F46: =IFERROR(E46/D46,0) -> 0.79454254 | G46: =COUNTIFS(Flight_Data!$C$2:$C$10001,B46,Flight_Data!$R$2:$R$10001,"Yes") -> 75 | H46: =IFERROR(G46/C46,0) -> 0.05677517 | I46: =SUMIF(Flight_Data!$C$2:$C$10001,B46,Flight_Data!$U$2:$U$10001) -> 178702 | J46: =IFERROR(I46/SUMIFS(Flight_Data!$T$2:$T$10001,Flight_Data!$C$2:$C$10001,B46,Flight_Data!$R$2:$R$10001,"No"),0) -> 0.77852565 | K46: =SUMIF(Flight_Data!$C$2:$C$10001,B46,Flight_Data!$AB$2:$AB$10001)/10000000 -> 137.52137 | L46: =SUMIF(Flight_Data!$C$2:$C$10001,B46,Flight_Data!$AD$2:$AD$10001)/10000000 -> 36.871575 | M46: =IFERROR(L46/K46,0) -> 0.26811523
B47: Akasa Air | C47: =COUNTIF(Flight_Data!$C$2:$C$10001,B47) -> 1222 | D47: =COUNTIFS(Flight_Data!$C$2:$C$10001,B47,Flight_Data!$R$2:$R$10001,"No") -> 1142 | E47: =COUNTIFS(Flight_Data!$C$2:$C$10001,B47,Flight_Data!$Q$2:$Q$10001,"Delayed*") -> 940 | F47: =IFERROR(E47/D47,0) -> 0.82311734 | G47: =COUNTIFS(Flight_Data!$C$2:$C$10001,B47,Flight_Data!$R$2:$R$10001,"Yes") -> 80 | H47: =IFERROR(G47/C47,0) -> 0.065466448 | I47: =SUMIF(Flight_Data!$C$2:$C$10001,B47,Flight_Data!$U$2:$U$10001) -> 164727 | J47: =IFERROR(I47/SUMIFS(Flight_Data!$T$2:$T$10001,Flight_Data!$C$2:$C$10001,B47,Flight_Data!$R$2:$R$10001,"No"),0) -> 0.7790905 | K47: =SUMIF(Flight_Data!$C$2:$C$10001,B47,Flight_Data!$AB$2:$AB$10001)/10000000 -> 124.41753 | L47: =SUMIF(Flight_Data!$C$2:$C$10001,B47,Flight_Data!$AD$2:$AD$10001)/10000000 -> 33.220623 | M47: =IFERROR(L47/K47,0) -> 0.26700918
B48: Air India Express | C48: =COUNTIF(Flight_Data!$C$2:$C$10001,B48) -> 979 | D48: =COUNTIFS(Flight_Data!$C$2:$C$10001,B48,Flight_Data!$R$2:$R$10001,"No") -> 919 | E48: =COUNTIFS(Flight_Data!$C$2:$C$10001,B48,Flight_Data!$Q$2:$Q$10001,"Delayed*") -> 736 | F48: =IFERROR(E48/D48,0) -> 0.80087051 | G48: =COUNTIFS(Flight_Data!$C$2:$C$10001,B48,Flight_Data!$R$2:$R$10001,"Yes") -> 60 | H48: =IFERROR(G48/C48,0) -> 0.061287028 | I48: =SUMIF(Flight_Data!$C$2:$C$10001,B48,Flight_Data!$U$2:$U$10001) -> 131774 | J48: =IFERROR(I48/SUMIFS(Flight_Data!$T$2:$T$10001,Flight_Data!$C$2:$C$10001,B48,Flight_Data!$R$2:$R$10001,"No"),0) -> 0.77310382 | K48: =SUMIF(Flight_Data!$C$2:$C$10001,B48,Flight_Data!$AB$2:$AB$10001)/10000000 -> 102.3127 | L48: =SUMIF(Flight_Data!$C$2:$C$10001,B48,Flight_Data!$AD$2:$AD$10001)/10000000 -> 27.475497 | M48: =IFERROR(L48/K48,0) -> 0.26854434
B49: Total | C49: =SUM(C43:C48) -> 10000 | D49: =SUM(D43:D48) -> 9384 | E49: =SUM(E43:E48) -> 7576 | F49: =IFERROR(E49/D49,0) -> 0.80733163 | G49: =SUM(G43:G48) -> 616 | H49: =IFERROR(G49/C49,0) -> 0.0616 | I49: =SUM(I43:I48) -> 1346015 | J49: =IFERROR(I49/SUMIFS(Flight_Data!$T$2:$T$10001,Flight_Data!$R$2:$R$10001,"No"),0) -> 0.77788103 | K49: =SUM(K43:K48) -> 1036.5107 | L49: =SUM(L43:L48) -> 279.87755 | M49: =IFERROR(L49/K49,0) -> 0.27001897
B52: Passengers by Airline & Cabin
B53: Airline | C53: Economy | D53: Business | E53: Mixed | F53: Total
B54: IndiGo | C54: =SUMIFS(Flight_Data!$U$2:$U$10001,Flight_Data!$C$2:$C$10001,B54,Flight_Data!$W$2:$W$10001,C$53) -> 307204 | D54: =SUMIFS(Flight_Data!$U$2:$U$10001,Flight_Data!$C$2:$C$10001,B54,Flight_Data!$W$2:$W$10001,D$53) -> 33945 | E54: =SUMIFS(Flight_Data!$U$2:$U$10001,Flight_Data!$C$2:$C$10001,B54,Flight_Data!$W$2:$W$10001,E$53) -> 88197 | F54: =SUM(C54:E54) -> 429346
B55: Air India | C55: =SUMIFS(Flight_Data!$U$2:$U$10001,Flight_Data!$C$2:$C$10001,B55,Flight_Data!$W$2:$W$10001,C$53) -> 180404 | D55: =SUMIFS(Flight_Data!$U$2:$U$10001,Flight_Data!$C$2:$C$10001,B55,Flight_Data!$W$2:$W$10001,D$53) -> 17720 | E55: =SUMIFS(Flight_Data!$U$2:$U$10001,Flight_Data!$C$2:$C$10001,B55,Flight_Data!$W$2:$W$10001,E$53) -> 47994 | F55: =SUM(C55:E55) -> 246118
B56: Vistara | C56: =SUMIFS(Flight_Data!$U$2:$U$10001,Flight_Data!$C$2:$C$10001,B56,Flight_Data!$W$2:$W$10001,C$53) -> 143330 | D56: =SUMIFS(Flight_Data!$U$2:$U$10001,Flight_Data!$C$2:$C$10001,B56,Flight_Data!$W$2:$W$10001,D$53) -> 16375 | E56: =SUMIFS(Flight_Data!$U$2:$U$10001,Flight_Data!$C$2:$C$10001,B56,Flight_Data!$W$2:$W$10001,E$53) -> 35643 | F56: =SUM(C56:E56) -> 195348
B57: SpiceJet | C57: =SUMIFS(Flight_Data!$U$2:$U$10001,Flight_Data!$C$2:$C$10001,B57,Flight_Data!$W$2:$W$10001,C$53) -> 131360 | D57: =SUMIFS(Flight_Data!$U$2:$U$10001,Flight_Data!$C$2:$C$10001,B57,Flight_Data!$W$2:$W$10001,D$53) -> 15253 | E57: =SUMIFS(Flight_Data!$U$2:$U$10001,Flight_Data!$C$2:$C$10001,B57,Flight_Data!$W$2:$W$10001,E$53) -> 32089 | F57: =SUM(C57:E57) -> 178702
B58: Akasa Air | C58: =SUMIFS(Flight_Data!$U$2:$U$10001,Flight_Data!$C$2:$C$10001,B58,Flight_Data!$W$2:$W$10001,C$53) -> 121321 | D58: =SUMIFS(Flight_Data!$U$2:$U$10001,Flight_Data!$C$2:$C$10001,B58,Flight_Data!$W$2:$W$10001,D$53) -> 11647 | E58: =SUMIFS(Flight_Data!$U$2:$U$10001,Flight_Data!$C$2:$C$10001,B58,Flight_Data!$W$2:$W$10001,E$53) -> 31759 | F58: =SUM(C58:E58) -> 164727
B59: Air India Express | C59: =SUMIFS(Flight_Data!$U$2:$U$10001,Flight_Data!$C$2:$C$10001,B59,Flight_Data!$W$2:$W$10001,C$53) -> 95679 | D59: =SUMIFS(Flight_Data!$U$2:$U$10001,Flight_Data!$C$2:$C$10001,B59,Flight_Data!$W$2:$W$10001,D$53) -> 9512 | E59: =SUMIFS(Flight_Data!$U$2:$U$10001,Flight_Data!$C$2:$C$10001,B59,Flight_Data!$W$2:$W$10001,E$53) -> 26583 | F59: =SUM(C59:E59) -> 131774
B60: Total | C60: =SUM(C54:C59) -> 979298 | D60: =SUM(D54:D59) -> 104452 | E60: =SUM(E54:E59) -> 262265 | F60: =SUM(F54:F59) -> 1346015

Sheet Revenue Dashboard
B1: Revenue Dashboard
B5: TOTAL REVENUE | C5: TICKET REVENUE | D5: BAGGAGE REVENUE | E5: ANCILLARY REVENUE | F5: OPERATING COST | G5: NET PROFIT | H5: PROFIT MARGIN
B6: =SUM(Flight_Data!$AB$2:$AB$10001)/10000000 -> 1036.5107 | C6: =SUM(Flight_Data!$Y$2:$Y$10001)/10000000 -> 928.80041 | D6: =SUM(Flight_Data!$Z$2:$Z$10001)/10000000 -> 46.964298 | E6: =SUM(Flight_Data!$AA$2:$AA$10001)/10000000 -> 60.745986 | F6: =SUM(Flight_Data!$AC$2:$AC$10001)/10000000 -> 756.63315 | G6: =SUM(Flight_Data!$AD$2:$AD$10001)/10000000 -> 279.87755 | H6: =IFERROR(G6/B6,0) -> 0.27001897
B41: Revenue Components | F41: Monthly Revenue, Cost & Profit | L41: Revenue by Cabin Class
B42: Component | C42: Amount (₹ Cr) | D42: % of Total | F42: Month | G42: Revenue (₹ Cr) | H42: Op. Cost (₹ Cr) | I42: Profit (₹ Cr) | J42: Margin | L42: Cabin | M42: Revenue (₹ Cr) | N42: Profit (₹ Cr) | O42: Margin
B43: Ticket Revenue | C43: =SUM(Flight_Data!$Y$2:$Y$10001)/10000000 -> 928.80041 | D43: =IFERROR(C43/SUM(Flight_Data!$AB$2:$AB$10001)/10000000,0) -> 8.9608377e-15 | F43: Jan | G43: =SUMIF(Flight_Data!$AJ$2:$AJ$10001,F43,Flight_Data!$AB$2:$AB$10001)/10000000 -> 87.525623 | H43: =SUMIF(Flight_Data!$AJ$2:$AJ$10001,F43,Flight_Data!$AC$2:$AC$10001)/10000000 -> 64.193786 | I43: =SUMIF(Flight_Data!$AJ$2:$AJ$10001,F43,Flight_Data!$AD$2:$AD$10001)/10000000 -> 23.331837 | J43: =IFERROR(I43/G43,0) -> 0.26657151 | L43: Economy | M43: =SUMIF(Flight_Data!$W$2:$W$10001,L43,Flight_Data!$AB$2:$AB$10001)/10000000 -> 756.71716 | N43: =SUMIF(Flight_Data!$W$2:$W$10001,L43,Flight_Data!$AD$2:$AD$10001)/10000000 -> 203.94411 | O43: =IFERROR(N43/M43,0) -> 0.26951168
B44: Baggage Revenue | C44: =SUM(Flight_Data!$Z$2:$Z$10001)/10000000 -> 46.964298 | D44: =IFERROR(C44/SUM(Flight_Data!$AB$2:$AB$10001)/10000000,0) -> 4.5309999e-16 | F44: Feb | G44: =SUMIF(Flight_Data!$AJ$2:$AJ$10001,F44,Flight_Data!$AB$2:$AB$10001)/10000000 -> 77.467217 | H44: =SUMIF(Flight_Data!$AJ$2:$AJ$10001,F44,Flight_Data!$AC$2:$AC$10001)/10000000 -> 56.688896 | I44: =SUMIF(Flight_Data!$AJ$2:$AJ$10001,F44,Flight_Data!$AD$2:$AD$10001)/10000000 -> 20.778321 | J44: =IFERROR(I44/G44,0) -> 0.26822083 | L44: Business | M44: =SUMIF(Flight_Data!$W$2:$W$10001,L44,Flight_Data!$AB$2:$AB$10001)/10000000 -> 80.782769 | N44: =SUMIF(Flight_Data!$W$2:$W$10001,L44,Flight_Data!$AD$2:$AD$10001)/10000000 -> 21.830849 | O44: =IFERROR(N44/M44,0) -> 0.27024141
B45: Ancillary Revenue | C45: =SUM(Flight_Data!$AA$2:$AA$10001)/10000000 -> 60.745986 | D45: =IFERROR(C45/SUM(Flight_Data!$AB$2:$AB$10001)/10000000,0) -> 5.8606231e-16 | F45: Mar | G45: =SUMIF(Flight_Data!$AJ$2:$AJ$10001,F45,Flight_Data!$AB$2:$AB$10001)/10000000 -> 87.693495 | H45: =SUMIF(Flight_Data!$AJ$2:$AJ$10001,F45,Flight_Data!$AC$2:$AC$10001)/10000000 -> 63.73141 | I45: =SUMIF(Flight_Data!$AJ$2:$AJ$10001,F45,Flight_Data!$AD$2:$AD$10001)/10000000 -> 23.962085 | J45: =IFERROR(I45/G45,0) -> 0.27324815 | L45: Mixed | M45: =SUMIF(Flight_Data!$W$2:$W$10001,L45,Flight_Data!$AB$2:$AB$10001)/10000000 -> 199.01077 | N45: =SUMIF(Flight_Data!$W$2:$W$10001,L45,Flight_Data!$AD$2:$AD$10001)/10000000 -> 54.102589 | O45: =IFERROR(N45/M45,0) -> 0.2718576
B46: Total Revenue | C46: =SUM(C43:C45) -> 1036.5107 | D46: =SUM(D43:D45) -> 1e-14 | F46: Apr | G46: =SUMIF(Flight_Data!$AJ$2:$AJ$10001,F46,Flight_Data!$AB$2:$AB$10001)/10000000 -> 82.182226 | H46: =SUMIF(Flight_Data!$AJ$2:$AJ$10001,F46,Flight_Data!$AC$2:$AC$10001)/10000000 -> 60.004469 | I46: =SUMIF(Flight_Data!$AJ$2:$AJ$10001,F46,Flight_Data!$AD$2:$AD$10001)/10000000 -> 22.177757 | J46: =IFERROR(I46/G46,0) -> 0.26986075 | L46: Total | M46: =SUM(M43:M45) -> 1036.5107 | N46: =SUM(N43:N45) -> 279.87755 | O46: =IFERROR(N46/M46,0) -> 0.27001897
F47: May | G47: =SUMIF(Flight_Data!$AJ$2:$AJ$10001,F47,Flight_Data!$AB$2:$AB$10001)/10000000 -> 87.744761 | H47: =SUMIF(Flight_Data!$AJ$2:$AJ$10001,F47,Flight_Data!$AC$2:$AC$10001)/10000000 -> 64.002138 | I47: =SUMIF(Flight_Data!$AJ$2:$AJ$10001,F47,Flight_Data!$AD$2:$AD$10001)/10000000 -> 23.742624 | J47: =IFERROR(I47/G47,0) -> 0.27058737
F48: Jun | G48: =SUMIF(Flight_Data!$AJ$2:$AJ$10001,F48,Flight_Data!$AB$2:$AB$10001)/10000000 -> 84.231061 | H48: =SUMIF(Flight_Data!$AJ$2:$AJ$10001,F48,Flight_Data!$AC$2:$AC$10001)/10000000 -> 61.552196 | I48: =SUMIF(Flight_Data!$AJ$2:$AJ$10001,F48,Flight_Data!$AD$2:$AD$10001)/10000000 -> 22.678864 | J48: =IFERROR(I48/G48,0) -> 0.26924586
F49: Jul | G49: =SUMIF(Flight_Data!$AJ$2:$AJ$10001,F49,Flight_Data!$AB$2:$AB$10001)/10000000 -> 91.826147 | H49: =SUMIF(Flight_Data!$AJ$2:$AJ$10001,F49,Flight_Data!$AC$2:$AC$10001)/10000000 -> 66.673275 | I49: =SUMIF(Flight_Data!$AJ$2:$AJ$10001,F49,Flight_Data!$AD$2:$AD$10001)/10000000 -> 25.152871 | J49: =IFERROR(I49/G49,0) -> 0.2739184 | L49: Revenue by Origin Region
F50: Aug | G50: =SUMIF(Flight_Data!$AJ$2:$AJ$10001,F50,Flight_Data!$AB$2:$AB$10001)/10000000 -> 84.723312 | H50: =SUMIF(Flight_Data!$AJ$2:$AJ$10001,F50,Flight_Data!$AC$2:$AC$10001)/10000000 -> 62.137824 | I50: =SUMIF(Flight_Data!$AJ$2:$AJ$10001,F50,Flight_Data!$AD$2:$AD$10001)/10000000 -> 22.585489 | J50: =IFERROR(I50/G50,0) -> 0.26657939 | L50: Region | M50: Revenue (₹ Cr) | N50: Profit (₹ Cr) | O50: Margin
B51: Revenue by Booking Channel | F51: Sep | G51: =SUMIF(Flight_Data!$AJ$2:$AJ$10001,F51,Flight_Data!$AB$2:$AB$10001)/10000000 -> 85.010841 | H51: =SUMIF(Flight_Data!$AJ$2:$AJ$10001,F51,Flight_Data!$AC$2:$AC$10001)/10000000 -> 62.108317 | I51: =SUMIF(Flight_Data!$AJ$2:$AJ$10001,F51,Flight_Data!$AD$2:$AD$10001)/10000000 -> 22.902524 | J51: =IFERROR(I51/G51,0) -> 0.2694071 | L51: East | M51: =SUMIF(Flight_Data!$AE$2:$AE$10001,L51,Flight_Data!$AB$2:$AB$10001)/10000000 -> 97.139527 | N51: =SUMIF(Flight_Data!$AE$2:$AE$10001,L51,Flight_Data!$AD$2:$AD$10001)/10000000 -> 26.220264 | O51: =IFERROR(N51/M51,0) -> 0.26992374
B52: Channel | C52: Revenue (₹ Cr) | D52: Profit (₹ Cr) | E52: % Share | F52: Oct | G52: =SUMIF(Flight_Data!$AJ$2:$AJ$10001,F52,Flight_Data!$AB$2:$AB$10001)/10000000 -> 89.659753 | H52: =SUMIF(Flight_Data!$AJ$2:$AJ$10001,F52,Flight_Data!$AC$2:$AC$10001)/10000000 -> 65.440568 | I52: =SUMIF(Flight_Data!$AJ$2:$AJ$10001,F52,Flight_Data!$AD$2:$AD$10001)/10000000 -> 24.219185 | J52: =IFERROR(I52/G52,0) -> 0.27012326 | L52: North | M52: =SUMIF(Flight_Data!$AE$2:$AE$10001,L52,Flight_Data!$AB$2:$AB$10001)/10000000 -> 212.53333 | N52: =SUMIF(Flight_Data!$AE$2:$AE$10001,L52,Flight_Data!$AD$2:$AD$10001)/10000000 -> 57.034654 | O52: =IFERROR(N52/M52,0) -> 0.26835628
B53: Online | C53: =SUMIF(Flight_Data!$AH$2:$AH$10001,B53,Flight_Data!$AB$2:$AB$10001)/10000000 -> 572.25177 | D53: =SUMIF(Flight_Data!$AH$2:$AH$10001,B53,Flight_Data!$AD$2:$AD$10001)/10000000 -> 155.26686 | E53: =IFERROR(C53/SUM(Flight_Data!$AB$2:$AB$10001)/10000000,0) -> 5.5209441e-15 | F53: Nov | G53: =SUMIF(Flight_Data!$AJ$2:$AJ$10001,F53,Flight_Data!$AB$2:$AB$10001)/10000000 -> 85.087324 | H53: =SUMIF(Flight_Data!$AJ$2:$AJ$10001,F53,Flight_Data!$AC$2:$AC$10001)/10000000 -> 61.972636 | I53: =SUMIF(Flight_Data!$AJ$2:$AJ$10001,F53,Flight_Data!$AD$2:$AD$10001)/10000000 -> 23.114688 | J53: =IFERROR(I53/G53,0) -> 0.27165842 | L53: South | M53: =SUMIF(Flight_Data!$AE$2:$AE$10001,L53,Flight_Data!$AB$2:$AB$10001)/10000000 -> 304.46402 | N53: =SUMIF(Flight_Data!$AE$2:$AE$10001,L53,Flight_Data!$AD$2:$AD$10001)/10000000 -> 83.03906 | O53: =IFERROR(N53/M53,0) -> 0.2727385
B54: Travel Agent | C54: =SUMIF(Flight_Data!$AH$2:$AH$10001,B54,Flight_Data!$AB$2:$AB$10001)/10000000 -> 190.53814 | D54: =SUMIF(Flight_Data!$AH$2:$AH$10001,B54,Flight_Data!$AD$2:$AD$10001)/10000000 -> 51.453198 | E54: =IFERROR(C54/SUM(Flight_Data!$AB$2:$AB$10001)/10000000,0) -> 1.838265e-15 | F54: Dec | G54: =SUMIF(Flight_Data!$AJ$2:$AJ$10001,F54,Flight_Data!$AB$2:$AB$10001)/10000000 -> 93.358938 | H54: =SUMIF(Flight_Data!$AJ$2:$AJ$10001,F54,Flight_Data!$AC$2:$AC$10001)/10000000 -> 68.127634 | I54: =SUMIF(Flight_Data!$AJ$2:$AJ$10001,F54,Flight_Data!$AD$2:$AD$10001)/10000000 -> 25.231304 | J54: =IFERROR(I54/G54,0) -> 0.27026126 | L54: West | M54: =SUMIF(Flight_Data!$AE$2:$AE$10001,L54,Flight_Data!$AB$2:$AB$10001)/10000000 -> 422.37381 | N54: =SUMIF(Flight_Data!$AE$2:$AE$10001,L54,Flight_Data!$AD$2:$AD$10001)/10000000 -> 113.58357 | O54: =IFERROR(N54/M54,0) -> 0.26891717
B55: Corporate | C55: =SUMIF(Flight_Data!$AH$2:$AH$10001,B55,Flight_Data!$AB$2:$AB$10001)/10000000 -> 170.96956 | D55: =SUMIF(Flight_Data!$AH$2:$AH$10001,B55,Flight_Data!$AD$2:$AD$10001)/10000000 -> 45.893647 | E55: =IFERROR(C55/SUM(Flight_Data!$AB$2:$AB$10001)/10000000,0) -> 1.6494722e-15 | F55: Total | G55: =SUM(G43:G54) -> 1036.5107 | H55: =SUM(H43:H54) -> 756.63315 | I55: =SUM(I43:I54) -> 279.87755 | J55: =IFERROR(I55/G55,0) -> 0.27001897 | L55: Total | M55: =SUM(M51:M54) -> 1036.5107 | N55: =SUM(N51:N54) -> 279.87755 | O55: =IFERROR(N55/M55,0) -> 0.27001897
B56: Airport Counter | C56: =SUMIF(Flight_Data!$AH$2:$AH$10001,B56,Flight_Data!$AB$2:$AB$10001)/10000000 -> 102.75123 | D56: =SUMIF(Flight_Data!$AH$2:$AH$10001,B56,Flight_Data!$AD$2:$AD$10001)/10000000 -> 27.263841 | E56: =IFERROR(C56/SUM(Flight_Data!$AB$2:$AB$10001)/10000000,0) -> 9.913186e-16
B57: Total | C57: =SUM(C53:C56) -> 1036.5107 | D57: =SUM(D53:D56) -> 279.87755 | E57: =SUM(E53:E56) -> 1e-14

Sheet Flight_Data
A1: Flight_ID | B1: Flight_Date | C1: Airline | D1: Flight_Number | E1: Origin_Airport | F1: Destination_Airport | G1: Origin_City | H1: Destination_City | I1: Distance_KM | J1: Scheduled_Departure | K1: Scheduled_Arrival | L1: Actual_Departure | M1: Actual_Arrival | N1: Flight_Duration_Min | O1: Departure_Delay_Min | P1: Arrival_Delay_Min | Q1: Flight_Status | R1: Cancelled | S1: Cancellation_Reason | T1: Total_Seats | U1: Passengers | V1: Load_Factor_Pct | W1: Cabin_Class | X1: Average_Ticket_Price | Y1: Ticket_Revenue | Z1: Baggage_Revenue | AA1: Ancillary_Revenue | AB1: Total_Revenue | AC1: Operating_Cost | AD1: Profit | AE1: Origin_Region | AF1: Destination_Region | AG1: Flight_Type | AH1: Booking_Channel | AI1: Demand_Level | AJ1: Month
A2: FL00001 | B2: 45764 | C2: Air India | D2: AI5834 | E2: Mumbai (BOM) | F2: Pune (PNQ) | G2: Mumbai | H2: Pune | I2: 816 | J2: 12:00 | K2: 14:17 | L2: 12:00 | M2: 14:17 | N2: 137 | O2: 0 | P2: -3 | Q2: On Time | R2: No | S2: Not Cancelled | T2: 189 | U2: 149 | V2: 78.84 | W2: Mixed | X2: 5233 | Y2: 779717 | Z2: 50809 | AA2: 56024 | AB2: 886550 | AC2: 678427 | AD2: 208123 | AE2: West | AF2: West | AG2: Domestic | AH2: Travel Agent | AI2: Low | AJ2: =TEXT(B2,"mmm") -> Apr
A3: FL00002 | B3: 45827 | C3: IndiGo | D3: 6E289 | E3: Pune (PNQ) | F3: Chennai (MAA) | G3: Pune | H3: Chennai | I3: 912 | J3: 20:30 | K3: 22:19 | N3: 139 | O3: 0 | P3: 0 | Q3: Cancelled | R3: Yes | S3: Technical Issue | T3: 220 | U3: 0 | V3: 0 | W3: Economy | X3: 8193 | Y3: 0 | Z3: 0 | AA3: 0 | AB3: 0 | AC3: 0 | AD3: 0 | AE3: West | AF3: South | AG3: Domestic | AH3: Corporate | AI3: Medium | AJ3: =TEXT(B3,"mmm") -> Jun
A4: FL00003 | B4: 45749 | C4: IndiGo | D4: 6E9770 | E4: Jaipur (JAI) | F4: Bengaluru (BLR) | G4: Jaipur | H4: Bengaluru | I4: 1125 | J4: 19:45 | K4: 22:03 | L4: 19:32 | M4: 22:19 | N4: 183 | O4: 32 | P4: 16 | Q4: Delayed <30 min | R4: No | S4: Not Cancelled | T4: 180 | U4: 176 | V4: 97.78 | W4: Economy | X4: 9673 | Y4: 1702448 | Z4: 33968 | AA4: 45936 | AB4: 1782352 | AC4: 1245053 | AD4: 537299 | AE4: North | AF4: South | AG4: Domestic | AH4: Airport Counter | AI4: Medium | AJ4: =TEXT(B4,"mmm") -> Apr
A5: FL00004 | B5: 45872 | C5: Air India | D5: AI6963 | E5: Goa (GOI) | F5: Kolkata (CCU) | G5: Goa | H5: Kolkata | I5: 687 | J5: 12:00 | K5: 13:47 | L5: 12:41 | M5: 14:32 | N5: 107 | O5: 41 | P5: 45 | Q5: Delayed 30-120 min | R5: No | S5: Not Cancelled | T5: 180 | U5: 149 | V5: 82.78 | W5: Economy | X5: 2864 | Y5: 426736 | Z5: 73606 | AA5: 92380 | AB5: 592722 | AC5: 481096 | AD5: 111626 | AE5: West | AF5: East | AG5: Domestic | AH5: Online | AI5: Low | AJ5: =TEXT(B5,"mmm") -> Aug
A6: FL00005 | B6: 45820 | C6: SpiceJet | D6: SG5992 | E6: Goa (GOI) | F6: Jaipur (JAI) | G6: Goa | H6: Jaipur | I6: 550 | J6: 07:00 | K6: 08:29 | L6: 07:07 | M6: 08:32 | N6: 89 | O6: 7 | P6: 3 | Q6: Delayed <30 min | R6: No | S6: Not Cancelled | T6: 180 | U6: 157 | V6: 87.22 | W6: Mixed | X6: 7856 | Y6: 1233392 | Z6: 59032 | AA6: 111784 | AB6: 1404208 | AC6: 1223786 | AD6: 180422 | AE6: West | AF6: North | AG6: Domestic | AH6: Corporate | AI6: Medium | AJ6: =TEXT(B6,"mmm") -> Jun
A7: FL00006 | B7: 46016 | C7: IndiGo | D7: 6E5234 | E7: Mumbai (BOM) | F7: Kolkata (CCU) | G7: Mumbai | H7: Kolkata | I7: 2231 | J7: 13:30 | K7: 18:40 | L7: 13:45 | M7: 19:29 | N7: 340 | O7: 45 | P7: 49 | Q7: Delayed 30-120 min | R7: No | S7: Not Cancelled | T7: 180 | U7: 133 | V7: 73.89 | W7: Economy | X7: 4557 | Y7: 606081 | Z7: 50540 | AA7: 100282 | AB7: 756903 | AC7: 610567 | AD7: 146336 | AE7: West | AF7: East | AG7: Domestic | AH7: Online | AI7: Low | AJ7: =TEXT(B7,"mmm") -> Dec
A8: FL00007 | B8: 45941 | C8: IndiGo | D8: 6E9889 | E8: Jaipur (JAI) | F8: Chennai (MAA) | G8: Jaipur | H8: Chennai | I8: 1145 | J8: 06:15 | K8: 08:32 | L8: 06:14 | M8: 09:03 | N8: 152 | O8: 14 | P8: 31 | Q8: Delayed 30-120 min | R8: No | S8: Not Cancelled | T8: 189 | U8: 140 | V8: 74.07 | W8: Economy | X8: 4106 | Y8: 574840 | Z8: 37800 | AA8: 101780 | AB8: 714420 | AC8: 489928 | AD8: 224492 | AE8: North | AF8: South | AG8: Domestic | AH8: Online | AI8: Low | AJ8: =TEXT(B8,"mmm") -> Oct
A9: FL00008 | B9: 45822 | C9: Vistara | D9: UK763 | E9: Pune (PNQ) | F9: Goa (GOI) | G9: Pune | H9: Goa | I9: 2348 | J9: 05:30 | K9: 10:41 | L9: 05:28 | M9: 10:41 | N9: 341 | O9: 28 | P9: 0 | Q9: Delayed <30 min | R9: No | S9: Not Cancelled | T9: 150 | U9: 139 | V9: 92.67 | W9: Economy | X9: 4091 | Y9: 568649 | Z9: 61716 | AA9: 67415 | AB9: 697780 | AC9: 553814 | AD9: 143966 | AE9: West | AF9: West | AG9: Domestic | AH9: Online | AI9: High | AJ9: =TEXT(B9,"mmm") -> Jun
A10: FL00009 | B10: 45787 | C10: IndiGo | D10: 6E7492 | E10: Delhi (DEL) | F10: Bengaluru (BLR) | G10: Delhi | H10: Bengaluru | I10: 2011 | J10: 09:45 | K10: 13:58 | L10: 09:40 | M10: 14:52 | N10: 298 | O10: 40 | P10: 54 | Q10: Delayed 30-120 min | R10: No | S10: Not Cancelled | T10: 180 | U10: 123 | V10: 68.33 | W10: Economy | X10: 2997 | Y10: 368631 | Z10: 66912 | AA10: 75030 | AB10: 510573 | AC10: 309962 | AD10: 200611 | AE10: North | AF10: South | AG10: Domestic | AH10: Corporate | AI10: Medium | AJ10: =TEXT(B10,"mmm") -> May
A11: FL00010 | B11: 45805 | C11: IndiGo | D11: 6E9661 | E11: Delhi (DEL) | F11: Hyderabad (HYD) | G11: Delhi | H11: Hyderabad | I11: 2336 | J11: 08:30 | K11: 12:43 | L11: 08:46 | M11: 13:38 | N11: 283 | O11: 46 | P11: 55 | Q11: Delayed 30-120 min | R11: No | S11: Not Cancelled | T11: 189 | U11: 91 | V11: 48.15 | W11: Economy | X11: 10920 | Y11: 993720 | Z11: 27300 | AA11: 46774 | AB11: 1067794 | AC11: 900365 | AD11: 167429 | AE11: North | AF11: South | AG11: Domestic | AH11: Online | AI11: Medium | AJ11: =TEXT(B11,"mmm") -> May
A12: FL00011 | B12: 45659 | C12: SpiceJet | D12: SG4648 | E12: Pune (PNQ) | F12: Kolkata (CCU) | G12: Pune | H12: Kolkata | I12: 1533 | J12: 05:45 | K12: 08:23 | L12: 05:44 | M12: 08:56 | N12: 203 | O12: 44 | P12: 33 | Q12: Delayed 30-120 min | R12: No | S12: Not Cancelled | T12: 220 | U12: 178 | V12: 80.91 | W12: Economy | X12: 4448 | Y12: 791744 | Z12: 45034 | AA12: 62834 | AB12: 899612 | AC12: 524257 | AD12: 375355 | AE12: West | AF12: East | AG12: Domestic | AH12: Online | AI12: Medium | AJ12: =TEXT(B12,"mmm") -> Jan
A13: FL00012 | B13: 45851 | C13: IndiGo | D13: 6E1056 | E13: Jaipur (JAI) | F13: Delhi (DEL) | G13: Jaipur | H13: Delhi | I13: 2054 | J13: 07:45 | K13: 12:01 | L13: 07:20 | M13: 12:04 | N13: 301 | O13: 20 | P13: 3 | Q13: Delayed <30 min | R13: No | S13: Not Cancelled | T13: 180 | U13: 139 | V13: 77.22 | W13: Business | X13: 4018 | Y13: 558502 | Z13: 38503 | AA13: 18348 | AB13: 615353 | AC13: 457060 | AD13: 158293 | AE13: North | AF13: North | AG13: Domestic | AH13: Online | AI13: Medium | AJ13: =TEXT(B13,"mmm") -> Jul
A14: FL00013 | B14: 45695 | C14: IndiGo | D14: 6E8854 | E14: Hyderabad (HYD) | F14: Bengaluru (BLR) | G14: Hyderabad | H14: Bengaluru | I14: 2149 | J14: 10:00 | K14: 14:35 | L14: 11:20 | M14: 15:59 | N14: 275 | O14: 80 | P14: 84 | Q14: Delayed 30-120 min | R14: No | S14: Not Cancelled | T14: 180 | U14: 153 | V14: 85 | W14: Economy | X14: 7442 | Y14: 1138626 | Z14: 52173 | AA14: 22644 | AB14: 1213443 | AC14: 719670 | AD14: 493773 | AE14: South | AF14: South | AG14: Domestic | AH14: Airport Counter | AI14: Medium | AJ14: =TEXT(B14,"mmm") -> Feb
A15: FL00014 | B15: 45756 | C15: IndiGo | D15: 6E2427 | E15: Delhi (DEL) | F15: Pune (PNQ) | G15: Delhi | H15: Pune | I15: 651 | J15: 13:00 | K15: 14:34 | N15: 94 | O15: 0 | P15: 0 | Q15: Cancelled | R15: Yes | S15: Operational Issue | T15: 180 | U15: 0 | V15: 0 | W15: Economy | X15: 8902 | Y15: 0 | Z15: 0 | AA15: 0 | AB15: 0 | AC15: 0 | AD15: 0 | AE15: North | AF15: West | AG15: Domestic | AH15: Online | AI15: Medium | AJ15: =TEXT(B15,"mmm") -> Apr
A16: FL00015 | B16: 46017 | C16: SpiceJet | D16: SG7555 | E16: Ahmedabad (AMD) | F16: Hyderabad (HYD) | G16: Ahmedabad | H16: Hyderabad | I16: 2036 | J16: 18:45 | K16: 23:01 | L16: 18:20 | M16: 23:32 | N16: 301 | O16: 20 | P16: 31 | Q16: Delayed 30-120 min | R16: No | S16: Not Cancelled | T16: 189 | U16: 125 | V16: 66.14 | W16: Economy | X16: 5606 | Y16: 700750 | Z16: 21875 | AA16: 63375 | AB16: 786000 | AC16: 671222 | AD16: 114778 | AE16: West | AF16: South | AG16: Domestic | AH16: Online | AI16: Medium | AJ16: =TEXT(B16,"mmm") -> Dec
A17: FL00016 | B17: 45921 | C17: SpiceJet | D17: SG9263 | E17: Ahmedabad (AMD) | F17: Mumbai (BOM) | G17: Ahmedabad | H17: Mumbai | I17: 2256 | J17: 18:45 | K17: 23:12 | L17: 18:46 | M17: 00:03 | N17: 312 | O17: 46 | P17: 51 | Q17: Delayed 30-120 min | R17: No | S17: Not Cancelled | T17: 150 | U17: 101 | V17: 67.33 | W17: Economy | X17: 3374 | Y17: 340774 | Z17: 34239 | AA17: 22624 | AB17: 397637 | AC17: 330706 | AD17: 66931 | AE17: West | AF17: West | AG17: Domestic | AH17: Corporate | AI17: Low | AJ17: =TEXT(B17,"mmm") -> Sep
A18: FL00017 | B18: 45711 | C18: IndiGo | D18: 6E3224 | E18: Mumbai (BOM) | F18: Pune (PNQ) | G18: Mumbai | H18: Pune | I18: 1945 | J18: 15:45 | K18: 19:42 | L18: 16:11 | M18: 21:23 | N18: 282 | O18: 71 | P18: 101 | Q18: Delayed 30-120 min | R18: No | S18: Not Cancelled | T18: 189 | U18: 101 | V18: 53.44 | W18: Business | X18: 3630 | Y18: 366630 | Z18: 42824 | AA18: 71003 | AB18: 480457 | AC18: 385909 | AD18: 94548 | AE18: West | AF18: West | AG18: Domestic | AH18: Online | AI18: Low | AJ18: =TEXT(B18,"mmm") -> Feb
A19: FL00018 | B19: 45786 | C19: IndiGo | D19: 6E7905 | E19: Delhi (DEL) | F19: Jaipur (JAI) | G19: Delhi | H19: Jaipur | I19: 1491 | J19: 05:30 | K19: 08:14 | L19: 05:16 | M19: 08:38 | N19: 194 | O19: 16 | P19: 24 | Q19: Delayed <30 min | R19: No | S19: Not Cancelled | T19: 189 | U19: 184 | V19: 97.35 | W19: Economy | X19: 5947 | Y19: 1094248 | Z19: 55752 | AA19: 138920 | AB19: 1288920 | AC19: 808918 | AD19: 480002 | AE19: North | AF19: North | AG19: Domestic | AH19: Online | AI19: Medium | AJ19: =TEXT(B19,"mmm") -> May
A20: FL00019 | B20: 45751 | C20: IndiGo | D20: 6E6717 | E20: Kolkata (CCU) | F20: Mumbai (BOM) | G20: Kolkata | H20: Mumbai | I20: 900 | J20: 18:15 | K20: 20:19 | L20: 18:01 | M20: 20:25 | N20: 139 | O20: 1 | P20: 6 | Q20: Delayed <30 min | R20: No | S20: Not Cancelled | T20: 220 | U20: 163 | V20: 74.09 | W20: Economy | X20: 5289 | Y20: 862107 | Z20: 39935 | AA20: 69112 | AB20: 971154 | AC20: 762539 | AD20: 208615 | AE20: East | AF20: West | AG20: Domestic | AH20: Travel Agent | AI20: High | AJ20: =TEXT(B20,"mmm") -> Apr
A21: FL00020 | B21: 45997 | C21: Air India Express | D21: IX2527 | E21: Hyderabad (HYD) | F21: Kolkata (CCU) | G21: Hyderabad | H21: Kolkata | I21: 1918 | J21: 16:15 | K21: 20:20 | L21: 16:25 | M21: 20:45 | N21: 260 | O21: 25 | P21: 25 | Q21: Delayed <30 min | R21: No | S21: Not Cancelled | T21: 220 | U21: 187 | V21: 85 | W21: Mixed | X21: 10523 | Y21: 1967801 | Z21: 81158 | AA21: 92752 | AB21: 2141711 | AC21: 1380068 | AD21: 761643 | AE21: South | AF21: East | AG21: Domestic | AH21: Online | AI21: Low | AJ21: =TEXT(B21,"mmm") -> Dec
A22: FL00021 | B22: 45994 | C22: Vistara | D22: UK9917 | E22: Jaipur (JAI) | F22: Kolkata (CCU) | G22: Jaipur | H22: Kolkata | I22: 767 | J22: 12:00 | K22: 14:05 | L22: 12:00 | M22: 14:27 | N22: 125 | O22: 0 | P22: 22 | Q22: Delayed <30 min | R22: No | S22: Not Cancelled | T22: 220 | U22: 169 | V22: 76.82 | W22: Mixed | X22: 8788 | Y22: 1485172 | Z22: 57629 | AA22: 133172 | AB22: 1675973 | AC22: 1339930 | AD22: 336043 | AE22: North | AF22: East | AG22: Domestic | AH22: Online | AI22: Low | AJ22: =TEXT(B22,"mmm") -> Dec
A23: FL00022 | B23: 45847 | C23: Vistara | D23: UK3540 | E23: Bengaluru (BLR) | F23: Kolkata (CCU) | G23: Bengaluru | H23: Kolkata | I23: 1898 | J23: 09:45 | K23: 12:59 | L23: 09:00 | M23: 13:11 | N23: 239 | O23: 0 | P23: 12 | Q23: Delayed <30 min | R23: No | S23: Not Cancelled | T23: 180 | U23: 91 | V23: 50.56 | W23: Economy | X23: 7292 | Y23: 663572 | Z23: 30576 | AA23: 10738 | AB23: 704886 | AC23: 491136 | AD23: 213750 | AE23: South | AF23: East | AG23: Domestic | AH23: Online | AI23: High | AJ23: =TEXT(B23,"mmm") -> Jul
A24: FL00023 | B24: 45941 | C24: IndiGo | D24: 6E5046 | E24: Ahmedabad (AMD) | F24: Goa (GOI) | G24: Ahmedabad | H24: Goa | I24: 1740 | J24: 18:30 | K24: 22:26 | L24: 18:40 | M24: 23:41 | N24: 266 | O24: 40 | P24: 75 | Q24: Delayed 30-120 min | R24: No | S24: Not Cancelled | T24: 180 | U24: 176 | V24: 97.78 | W24: Mixed | X24: 10041 | Y24: 1767216 | Z24: 70752 | AA24: 57904 | AB24: 1895872 | AC24: 1147442 | AD24: 748430 | AE24: West | AF24: West | AG24: Domestic | AH24: Travel Agent | AI24: Low | AJ24: =TEXT(B24,"mmm") -> Oct
A25: FL00024 | B25: 45662 | C25: SpiceJet | D25: SG9680 | E25: Ahmedabad (AMD) | F25: Bengaluru (BLR) | G25: Ahmedabad | H25: Bengaluru | I25: 2206 | J25: 09:15 | K25: 13:24 | L25: 09:22 | M25: 13:51 | N25: 264 | O25: 22 | P25: 27 | Q25: Delayed <30 min | R25: No | S25: Not Cancelled | T25: 180 | U25: 158 | V25: 87.78 | W25: Economy | X25: 4610 | Y25: 728380 | Z25: 81054 | AA25: 44398 | AB25: 853832 | AC25: 675829 | AD25: 178003 | AE25: West | AF25: South | AG25: Domestic | AH25: Online | AI25: Medium | AJ25: =TEXT(B25,"mmm") -> Jan
A26: FL00025 | B26: 45798 | C26: Air India | D26: AI3809 | E26: Chennai (MAA) | F26: Jaipur (JAI) | G26: Chennai | H26: Jaipur | I26: 1431 | J26: 22:45 | K26: 01:06 | L26: 22:25 | M26: 01:44 | N26: 186 | O26: 25 | P26: 38 | Q26: Delayed 30-120 min | R26: No | S26: Not Cancelled | T26: 189 | U26: 135 | V26: 71.43 | W26: Economy | X26: 10376 | Y26: 1400760 | Z26: 62235 | AA26: 29160 | AB26: 1492155 | AC26: 1296633 | AD26: 195522 | AE26: South | AF26: North | AG26: Domestic | AH26: Online | AI26: High | AJ26: =TEXT(B26,"mmm") -> May
A27: FL00026 | B27: 45737 | C27: IndiGo | D27: 6E5448 | E27: Bengaluru (BLR) | F27: Hyderabad (HYD) | G27: Bengaluru | H27: Hyderabad | I27: 2049 | J27: 15:45 | K27: 19:29 | N27: 269 | O27: 0 | P27: 0 | Q27: Cancelled | R27: Yes | S27: Technical Issue | T27: 189 | U27: 0 | V27: 0 | W27: Economy | X27: 6286 | Y27: 0 | Z27: 0 | AA27: 0 | AB27: 0 | AC27: 0 | AD27: 0 | AE27: South | AF27: South | AG27: Domestic | AH27: Online | AI27: Medium | AJ27: =TEXT(B27,"mmm") -> Mar
A28: FL00027 | B28: 45881 | C28: Air India Express | D28: IX8649 | E28: Goa (GOI) | F28: Mumbai (BOM) | G28: Goa | H28: Mumbai | I28: 1017 | J28: 20:45 | K28: 22:34 | L28: 20:00 | M28: 23:00 | N28: 154 | O28: 0 | P28: 26 | Q28: Delayed <30 min | R28: No | S28: Not Cancelled | T28: 180 | U28: 123 | V28: 68.33 | W28: Economy | X28: 8842 | Y28: 1087566 | Z28: 36162 | AA28: 36900 | AB28: 1160628 | AC28: 780938 | AD28: 379690 | AE28: West | AF28: West | AG28: Domestic | AH28: Corporate | AI28: Medium | AJ28: =TEXT(B28,"mmm") -> Aug
A29: FL00028 | B29: 45692 | C29: IndiGo | D29: 6E7126 | E29: Kolkata (CCU) | F29: Delhi (DEL) | G29: Kolkata | H29: Delhi | I29: 605 | J29: 10:15 | K29: 11:36 | L29: 10:00 | M29: 11:36 | N29: 96 | O29: 0 | P29: -10 | Q29: On Time | R29: No | S29: Not Cancelled | T29: 180 | U29: 144 | V29: 80 | W29: Business | X29: 4993 | Y29: 718992 | Z29: 53712 | AA29: 48672 | AB29: 821376 | AC29: 513462 | AD29: 307914 | AE29: East | AF29: North | AG29: Domestic | AH29: Travel Agent | AI29: Medium | AJ29: =TEXT(B29,"mmm") -> Feb
A30: FL00029 | B30: 45834 | C30: Air India Express | D30: IX1733 | E30: Bengaluru (BLR) | F30: Jaipur (JAI) | G30: Bengaluru | H30: Jaipur | I30: 860 | J30: 17:00 | K30: 19:16 | L30: 17:18 | M30: 19:41 | N30: 136 | O30: 18 | P30: 25 | Q30: Delayed <30 min | R30: No | S30: Not Cancelled | T30: 220 | U30: 171 | V30: 77.73 | W30: Business | X30: 7609 | Y30: 1301139 | Z30: 39672 | AA30: 41724 | AB30: 1382535 | AC30: 901862 | AD30: 480673 | AE30: South | AF30: North | AG30: Domestic | AH30: Online | AI30: Low | AJ30: =TEXT(B30,"mmm") -> Jun
A31: FL00030 | B31: 45945 | C31: IndiGo | D31: 6E7339 | E31: Delhi (DEL) | F31: Chennai (MAA) | G31: Delhi | H31: Chennai | I31: 1924 | J31: 06:45 | K31: 10:06 | L31: 06:13 | M31: 10:23 | N31: 246 | O31: 13 | P31: 17 | Q31: Delayed <30 min | R31: No | S31: Not Cancelled | T31: 220 | U31: 212 | V31: 96.36 | W31: Economy | X31: 10701 | Y31: 2268612 | Z31: 84800 | AA31: 106000 | AB31: 2459412 | AC31: 1525338 | AD31: 934074 | AE31: North | AF31: South | AG31: Domestic | AH31: Online | AI31: Medium | AJ31: =TEXT(B31,"mmm") -> Oct
A32: FL00031 | B32: 45732 | C32: Vistara | D32: UK6981 | E32: Ahmedabad (AMD) | F32: Bengaluru (BLR) | G32: Ahmedabad | H32: Bengaluru | I32: 1679 | J32: 11:15 | K32: 14:43 | L32: 11:34 | M32: 15:17 | N32: 223 | O32: 34 | P32: 34 | Q32: Delayed 30-120 min | R32: No | S32: Not Cancelled | T32: 180 | U32: 172 | V32: 95.56 | W32: Economy | X32: 7654 | Y32: 1316488 | Z32: 43860 | AA32: 113864 | AB32: 1474212 | AC32: 1163584 | AD32: 310628 | AE32: West | AF32: South | AG32: Domestic | AH32: Corporate | AI32: Medium | AJ32: =TEXT(B32,"mmm") -> Mar
A33: FL00032 | B33: 45997 | C33: SpiceJet | D33: SG8041 | E33: Mumbai (BOM) | F33: Goa (GOI) | G33: Mumbai | H33: Goa | I33: 1823 | J33: 09:15 | K33: 13:18 | L33: 09:13 | M33: 13:32 | N33: 258 | O33: 13 | P33: 14 | Q33: Delayed <30 min | R33: No | S33: Not Cancelled | T33: 150 | U33: 115 | V33: 76.67 | W33: Economy | X33: 9038 | Y33: 1039370 | Z33: 60145 | AA33: 71185 | AB33: 1170700 | AC33: 742247 | AD33: 428453 | AE33: West | AF33: West | AG33: Domestic | AH33: Travel Agent | AI33: Medium | AJ33: =TEXT(B33,"mmm") -> Dec
A34: FL00033 | B34: 45750 | C34: SpiceJet | D34: SG6877 | E34: Bengaluru (BLR) | F34: Jaipur (JAI) | G34: Bengaluru | H34: Jaipur | I34: 1378 | J34: 22:00 | K34: 01:20 | L34: 22:13 | M34: 01:28 | N34: 200 | O34: 13 | P34: 8 | Q34: Delayed <30 min | R34: No | S34: Not Cancelled | T34: 186 | U34: 162 | V34: 87.1 | W34: Economy | X34: 10040 | Y34: 1626480 | Z34: 69822 | AA34: 56376 | AB34: 1752678 | AC34: 1269541 | AD34: 483137 | AE34: South | AF34: North | AG34: Domestic | AH34: Travel Agent | AI34: Medium | AJ34: =TEXT(B34,"mmm") -> Apr
A35: FL00034 | B35: 45718 | C35: IndiGo | D35: 6E1376 | E35: Kolkata (CCU) | F35: Bengaluru (BLR) | G35: Kolkata | H35: Bengaluru | I35: 2065 | J35: 21:15 | K35: 01:59 | L35: 21:04 | M35: 02:41 | N35: 299 | O35: 4 | P35: 42 | Q35: Delayed 30-120 min | R35: No | S35: Not Cancelled | T35: 180 | U35: 133 | V35: 73.89 | W35: Economy | X35: 3164 | Y35: 420812 | Z35: 40299 | AA35: 83125 | AB35: 544236 | AC35: 339778 | AD35: 204458 | AE35: East | AF35: South | AG35: Domestic | AH35: Online | AI35: Medium | AJ35: =TEXT(B35,"mmm") -> Mar
A36: FL00035 | B36: 45951 | C36: SpiceJet | D36: SG3186 | E36: Mumbai (BOM) | F36: Jaipur (JAI) | G36: Mumbai | H36: Jaipur | I36: 1565 | J36: 07:30 | K36: 10:48 | L36: 07:00 | M36: 10:48 | N36: 228 | O36: 0 | P36: -10 | Q36: On Time | R36: No | S36: Not Cancelled | T36: 150 | U36: 120 | V36: 80 | W36: Economy | X36: 3032 | Y36: 363840 | Z36: 30960 | AA36: 29400 | AB36: 424200 | AC36: 257097 | AD36: 167103 | AE36: West | AF36: North | AG36: Domestic | AH36: Online | AI36: Medium | AJ36: =TEXT(B36,"mmm") -> Oct
A37: FL00036 | B37: 45699 | C37: Akasa Air | D37: QP2839 | E37: Jaipur (JAI) | F37: Mumbai (BOM) | G37: Jaipur | H37: Mumbai | I37: 1655 | J37: 13:00 | K37: 16:39 | L37: 13:34 | M37: 16:44 | N37: 219 | O37: 34 | P37: 5 | Q37: Delayed <30 min | R37: No | S37: Not Cancelled | T37: 220 | U37: 171 | V37: 77.73 | W37: Economy | X37: 4533 | Y37: 775143 | Z37: 37449 | AA37: 102942 | AB37: 915534 | AC37: 664991 | AD37: 250543 | AE37: North | AF37: West | AG37: Domestic | AH37: Corporate | AI37: Low | AJ37: =TEXT(B37,"mmm") -> Feb
A38: FL00037 | B38: 45968 | C38: SpiceJet | D38: SG8534 | E38: Bengaluru (BLR) | F38: Pune (PNQ) | G38: Bengaluru | H38: Pune | I38: 1413 | J38: 13:30 | K38: 16:06 | N38: 186 | O38: 0 | P38: 0 | Q38: Cancelled | R38: Yes | S38: Operational Issue | T38: 186 | U38: 0 | V38: 0 | W38: Business | X38: 8360 | Y38: 0 | Z38: 0 | AA38: 0 | AB38: 0 | AC38: 0 | AD38: 0 | AE38: South | AF38: West | AG38: Domestic | AH38: Corporate | AI38: Low | AJ38: =TEXT(B38,"mmm") -> Nov
A39: FL00038 | B39: 45932 | C39: Air India Express | D39: IX4308 | E39: Ahmedabad (AMD) | F39: Chennai (MAA) | G39: Ahmedabad | H39: Chennai | I39: 908 | J39: 05:45 | K39: 07:08 | L39: 05:23 | M39: 07:34 | N39: 128 | O39: 23 | P39: 26 | Q39: Delayed <30 min | R39: No | S39: Not Cancelled | T39: 220 | U39: 148 | V39: 67.27 | W39: Economy | X39: 6544 | Y39: 968512 | Z39: 79772 | AA39: 116772 | AB39: 1165056 | AC39: 834506 | AD39: 330550 | AE39: West | AF39: South | AG39: Domestic | AH39: Online | AI39: Medium | AJ39: =TEXT(B39,"mmm") -> Oct
A40: FL00039 | B40: 45787 | C40: IndiGo | D40: 6E2932 | E40: Chennai (MAA) | F40: Hyderabad (HYD) | G40: Chennai | H40: Hyderabad | I40: 2344 | J40: 05:30 | K40: 10:11 | L40: 05:06 | M40: 10:22 | N40: 311 | O40: 6 | P40: 11 | Q40: Delayed <30 min | R40: No | S40: Not Cancelled | T40: 220 | U40: 156 | V40: 70.91 | W40: Mixed | X40: 6330 | Y40: 987480 | Z40: 44616 | AA40: 107172 | AB40: 1139268 | AC40: 790388 | AD40: 348880 | AE40: South | AF40: South | AG40: Domestic | AH40: Airport Counter | AI40: Medium | AJ40: =TEXT(B40,"mmm") -> May
A41: FL00040 | B41: 45924 | C41: IndiGo | D41: 6E6513 | E41: Ahmedabad (AMD) | F41: Jaipur (JAI) | G41: Ahmedabad | H41: Jaipur | I41: 2201 | J41: 13:00 | K41: 18:22 | L41: 13:49 | M41: 19:22 | N41: 322 | O41: 49 | P41: 60 | Q41: Delayed 30-120 min | R41: No | S41: Not Cancelled | T41: 186 | U41: 168 | V41: 90.32 | W41: Economy | X41: 3865 | Y41: 649320 | Z41: 39984 | AA41: 84168 | AB41: 773472 | AC41: 638098 | AD41: 135374 | AE41: West | AF41: North | AG41: Domestic | AH41: Online | AI41: Medium | AJ41: =TEXT(B41,"mmm") -> Sep
A42: FL00041 | B42: 46010 | C42: Air India | D42: AI2812 | E42: Chennai (MAA) | F42: Mumbai (BOM) | G42: Chennai | H42: Mumbai | I42: 1598 | J42: 19:00 | K42: 22:45 | L42: 19:00 | M42: 23:09 | N42: 225 | O42: 0 | P42: 24 | Q42: Delayed <30 min | R42: No | S42: Not Cancelled | T42: 180 | U42: 160 | V42: 88.89 | W42: Economy | X42: 8542 | Y42: 1366720 | Z42: 48960 | AA42: 62080 | AB42: 1477760 | AC42: 1093599 | AD42: 384161 | AE42: South | AF42: West | AG42: Domestic | AH42: Corporate | AI42: Medium | AJ42: =TEXT(B42,"mmm") -> Dec
A43: FL00042 | B43: 45946 | C43: IndiGo | D43: 6E4712 | E43: Bengaluru (BLR) | F43: Jaipur (JAI) | G43: Bengaluru | H43: Jaipur | I43: 2008 | J43: 08:15 | K43: 12:10 | L43: 08:39 | M43: 12:18 | N43: 250 | O43: 39 | P43: 8 | Q43: Delayed <30 min | R43: No | S43: Not Cancelled | T43: 180 | U43: 154 | V43: 85.56 | W43: Economy | X43: 6028 | Y43: 928312 | Z43: 43890 | AA43: 55440 | AB43: 1027642 | AC43: 745972 | AD43: 281670 | AE43: South | AF43: North | AG43: Domestic | AH43: Online | AI43: Medium | AJ43: =TEXT(B43,"mmm") -> Oct
A44: FL00043 | B44: 45949 | C44: IndiGo | D44: 6E2216 | E44: Hyderabad (HYD) | F44: Jaipur (JAI) | G44: Hyderabad | H44: Jaipur | I44: 2033 | J44: 15:30 | K44: 19:57 | L44: 15:00 | M44: 20:22 | N44: 297 | O44: 0 | P44: 25 | Q44: Delayed <30 min | R44: No | S44: Not Cancelled | T44: 180 | U44: 144 | V44: 80 | W44: Economy | X44: 10590 | Y44: 1524960 | Z44: 36432 | AA44: 112608 | AB44: 1674000 | AC44: 1439029 | AD44: 234971 | AE44: South | AF44: North | AG44: Domestic | AH44: Travel Agent | AI44: Medium | AJ44: =TEXT(B44,"mmm") -> Oct
A45: FL00044 | B45: 45784 | C45: Air India Express | D45: IX8895 | E45: Ahmedabad (AMD) | F45: Jaipur (JAI) | G45: Ahmedabad | H45: Jaipur | I45: 2278 | J45: 14:00 | K45: 19:07 | L45: 15:18 | M45: 20:13 | N45: 307 | O45: 78 | P45: 66 | Q45: Delayed 30-120 min | R45: No | S45: Not Cancelled | T45: 220 | U45: 168 | V45: 76.36 | W45: Mixed | X45: 5830 | Y45: 979440 | Z45: 77616 | AA45: 16800 | AB45: 1073856 | AC45: 903079 | AD45: 170777 | AE45: West | AF45: North | AG45: Domestic | AH45: Online | AI45: Medium | AJ45: =TEXT(B45,"mmm") -> May
A46: FL00045 | B46: 45966 | C46: Air India | D46: AI3607 | E46: Goa (GOI) | F46: Delhi (DEL) | G46: Goa | H46: Delhi | I46: 466 | J46: 13:15 | K46: 14:19 | L46: 13:38 | M46: 14:56 | N46: 79 | O46: 38 | P46: 37 | Q46: Delayed 30-120 min | R46: No | S46: Not Cancelled | T46: 220 | U46: 130 | V46: 59.09 | W46: Mixed | X46: 9583 | Y46: 1245790 | Z46: 66690 | AA46: 36140 | AB46: 1348620 | AC46: 882628 | AD46: 465992 | AE46: West | AF46: North | AG46: Domestic | AH46: Travel Agent | AI46: Low | AJ46: =TEXT(B46,"mmm") -> Nov
A47: FL00046 | B47: 45834 | C47: IndiGo | D47: 6E2813 | E47: Hyderabad (HYD) | F47: Pune (PNQ) | G47: Hyderabad | H47: Pune | I47: 1842 | J47: 15:15 | K47: 19:07 | N47: 247 | O47: 0 | P47: 0 | Q47: Cancelled | R47: Yes | S47: Technical Issue | T47: 186 | U47: 0 | V47: 0 | W47: Mixed | X47: 7982 | Y47: 0 | Z47: 0 | AA47: 0 | AB47: 0 | AC47: 0 | AD47: 0 | AE47: South | AF47: West | AG47: Domestic | AH47: Travel Agent | AI47: Low | AJ47: =TEXT(B47,"mmm") -> Jun
A48: FL00047 | B48: 45868 | C48: Akasa Air | D48: QP9792 | E48: Pune (PNQ) | F48: Mumbai (BOM) | G48: Pune | H48: Mumbai | I48: 635 | J48: 21:00 | K48: 22:34 | L48: 21:37 | M48: 22:58 | N48: 94 | O48: 37 | P48: 24 | Q48: Delayed <30 min | R48: No | S48: Not Cancelled | T48: 186 | U48: 110 | V48: 59.14 | W48: Economy | X48: 7726 | Y48: 849860 | Z48: 30910 | AA48: 39930 | AB48: 920700 | AC48: 772039 | AD48: 148661 | AE48: West | AF48: West | AG48: Domestic | AH48: Airport Counter | AI48: Medium | AJ48: =TEXT(B48,"mmm") -> Jul
A49: FL00048 | B49: 45744 | C49: IndiGo | D49: 6E932 | E49: Hyderabad (HYD) | F49: Ahmedabad (AMD) | G49: Hyderabad | H49: Ahmedabad | I49: 662 | J49: 22:30 | K49: 23:52 | L49: 23:21 | M49: 01:17 | N49: 112 | O49: 81 | P49: 85 | Q49: Delayed 30-120 min | R49: No | S49: Not Cancelled | T49: 180 | U49: 137 | V49: 76.11 | W49: Economy | X49: 5854 | Y49: 801998 | Z49: 56581 | AA49: 70829 | AB49: 929408 | AC49: 763596 | AD49: 165812 | AE49: South | AF49: West | AG49: Domestic | AH49: Airport Counter | AI49: Medium | AJ49: =TEXT(B49,"mmm") -> Mar
A50: FL00049 | B50: 45822 | C50: SpiceJet | D50: SG922 | E50: Mumbai (BOM) | F50: Ahmedabad (AMD) | G50: Mumbai | H50: Ahmedabad | I50: 1293 | J50: 18:30 | K50: 21:24 | L50: 18:29 | M50: 22:03 | N50: 204 | O50: 29 | P50: 39 | Q50: Delayed 30-120 min | R50: No | S50: Not Cancelled | T50: 150 | U50: 122 | V50: 81.33 | W50: Economy | X50: 9652 | Y50: 1177544 | Z50: 19520 | AA50: 59170 | AB50: 1256234 | AC50: 865441 | AD50: 390793 | AE50: West | AF50: West | AG50: Domestic | AH50: Online | AI50: High | AJ50: =TEXT(B50,"mmm") -> Jun
A51: FL00050 | B51: 45883 | C51: Air India | D51: AI5719 | E51: Delhi (DEL) | F51: Jaipur (JAI) | G51: Delhi | H51: Jaipur | I51: 1737 | J51: 16:30 | K51: 20:21 | L51: 16:33 | M51: 21:11 | N51: 261 | O51: 33 | P51: 50 | Q51: Delayed 30-120 min | R51: No | S51: Not Cancelled | T51: 189 | U51: 146 | V51: 77.25 | W51: Economy | X51: 5986 | Y51: 873956 | Z51: 52268 | AA51: 91250 | AB51: 1017474 | AC51: 816529 | AD51: 200945 | AE51: North | AF51: North | AG51: Domestic | AH51: Travel Agent | AI51: Medium | AJ51: =TEXT(B51,"mmm") -> Aug
A52: FL00051 | B52: 45892 | C52: IndiGo | D52: 6E6909 | E52: Bengaluru (BLR) | F52: Chennai (MAA) | G52: Bengaluru | H52: Chennai | I52: 791 | J52: 18:45 | K52: 19:50 | L52: 18:35 | M52: 20:36 | N52: 110 | O52: 35 | P52: 46 | Q52: Delayed 30-120 min | R52: No | S52: Not Cancelled | T52: 186 | U52: 144 | V52: 77.42 | W52: Economy | X52: 8596 | Y52: 1237824 | Z52: 43488 | AA52: 68688 | AB52: 1350000 | AC52: 1074682 | AD52: 275318 | AE52: South | AF52: South | AG52: Domestic | AH52: Online | AI52: Low | AJ52: =TEXT(B52,"mmm") -> Aug
A53: FL00052 | B53: 45791 | C53: IndiGo | D53: 6E6236 | E53: Hyderabad (HYD) | F53: Chennai (MAA) | G53: Hyderabad | H53: Chennai | I53: 804 | J53: 12:15 | K53: 14:00 | L53: 12:45 | M53: 15:09 | N53: 120 | O53: 45 | P53: 69 | Q53: Delayed 30-120 min | R53: No | S53: Not Cancelled | T53: 180 | U53: 129 | V53: 71.67 | W53: Economy | X53: 8741 | Y53: 1127589 | Z53: 66048 | AA53: 102168 | AB53: 1295805 | AC53: 986037 | AD53: 309768 | AE53: South | AF53: South | AG53: Domestic | AH53: Online | AI53: Medium | AJ53: =TEXT(B53,"mmm") -> May
A54: FL00053 | B54: 45770 | C54: IndiGo | D54: 6E9542 | E54: Hyderabad (HYD) | F54: Jaipur (JAI) | G54: Hyderabad | H54: Jaipur | I54: 1683 | J54: 11:45 | K54: 14:50 | L54: 11:14 | M54: 15:09 | N54: 230 | O54: 14 | P54: 19 | Q54: Delayed <30 min | R54: No | S54: Not Cancelled | T54: 180 | U54: 127 | V54: 70.56 | W54: Economy | X54: 8922 | Y54: 1133094 | Z54: 44450 | AA54: 32131 | AB54: 1209675 | AC54: 873713 | AD54: 335962 | AE54: South | AF54: North | AG54: Domestic | AH54: Online | AI54: Medium | AJ54: =TEXT(B54,"mmm") -> Apr
A55: FL00054 | B55: 45761 | C55: Air India | D55: AI8070 | E55: Pune (PNQ) | F55: Ahmedabad (AMD) | G55: Pune | H55: Ahmedabad | I55: 480 | J55: 14:00 | K55: 15:31 | L55: 14:15 | M55: 15:44 | N55: 91 | O55: 15 | P55: 13 | Q55: Delayed <30 min | R55: No | S55: Not Cancelled | T55: 189 | U55: 132 | V55: 69.84 | W55: Mixed | X55: 7936 | Y55: 1047552 | Z55: 63228 | AA55: 88176 | AB55: 1198956 | AC55: 855816 | AD55: 343140 | AE55: West | AF55: West | AG55: Domestic | AH55: Online | AI55: Medium | AJ55: =TEXT(B55,"mmm") -> Apr
A56: FL00055 | B56: 45806 | C56: SpiceJet | D56: SG5704 | E56: Delhi (DEL) | F56: Goa (GOI) | G56: Delhi | H56: Goa | I56: 1059 | J56: 21:30 | K56: 23:17 | L56: 21:45 | M56: 00:20 | N56: 137 | O56: 45 | P56: 63 | Q56: Delayed 30-120 min | R56: No | S56: Not Cancelled | T56: 150 | U56: 111 | V56: 74 | W56: Economy | X56: 8713 | Y56: 967143 | Z56: 26085 | AA56: 38739 | AB56: 1031967 | AC56: 695397 | AD56: 336570 | AE56: North | AF56: West | AG56: Domestic | AH56: Online | AI56: Medium | AJ56: =TEXT(B56,"mmm") -> May
A57: FL00056 | B57: 45972 | C57: IndiGo | D57: 6E5185 | E57: Ahmedabad (AMD) | F57: Jaipur (JAI) | G57: Ahmedabad | H57: Jaipur | I57: 1284 | J57: 22:30 | K57: 01:02 | L57: 22:14 | M57: 01:39 | N57: 182 | O57: 14 | P57: 37 | Q57: Delayed 30-120 min | R57: No | S57: Not Cancelled | T57: 180 | U57: 168 | V57: 93.33 | W57: Economy | X57: 10780 | Y57: 1811040 | Z57: 41496 | AA57: 38640 | AB57: 1891176 | AC57: 1491923 | AD57: 399253 | AE57: West | AF57: North | AG57: Domestic | AH57: Online | AI57: Medium | AJ57: =TEXT(B57,"mmm") -> Nov
A58: FL00057 | B58: 45661 | C58: IndiGo | D58: 6E8784 | E58: Mumbai (BOM) | F58: Pune (PNQ) | G58: Mumbai | H58: Pune | I58: 1799 | J58: 17:15 | K58: 20:40 | L58: 17:18 | M58: 21:00 | N58: 220 | O58: 18 | P58: 20 | Q58: Delayed <30 min | R58: No | S58: Not Cancelled | T58: 150 | U58: 109 | V58: 72.67 | W58: Mixed | X58: 10006 | Y58: 1090654 | Z58: 49159 | AA58: 13952 | AB58: 1153765 | AC58: 934730 | AD58: 219035 | AE58: West | AF58: West | AG58: Domestic | AH58: Online | AI58: Medium | AJ58: =TEXT(B58,"mmm") -> Jan
A59: FL00058 | B59: 45893 | C59: Vistara | D59: UK4461 | E59: Pune (PNQ) | F59: Mumbai (BOM) | G59: Pune | H59: Mumbai | I59: 1270 | J59: 19:00 | K59: 22:06 | L59: 19:00 | M59: 22:06 | N59: 186 | O59: 0 | P59: -10 | Q59: On Time | R59: No | S59: Not Cancelled | T59: 220 | U59: 163 | V59: 74.09 | W59: Economy | X59: 7188 | Y59: 1171644 | Z59: 49226 | AA59: 86553 | AB59: 1307423 | AC59: 765315 | AD59: 542108 | AE59: West | AF59: West | AG59: Domestic | AH59: Airport Counter | AI59: Medium | AJ59: =TEXT(B59,"mmm") -> Aug
... A66: FL00065 | B66: 45850 | C66: IndiGo | D66: 6E7537 | E66: Mumbai (BOM) | F66: Hyderabad (HYD) | G66: Mumbai | H66: Hyderabad | I66: 1053 | J66: 22:15 | K66: 00:26 | L66: 22:39 | M66: 01:33 | N66: 146 | O66: 39 | P66: 67 | Q66: Delayed 30-120 min | R66: No | S66: Not Cancelled | T66: 180 | U66: 164 | V66: 91.11 | W66: Economy | X66: 6156 | Y66: 1009584 | Z66: 25092 | AA66: 32472 | AB66: 1067148 | AC66: 763454 | AD66: 303694 | AE66: West | AF66: South | AG66: Domestic | AH66: Online | AI66: Medium | AJ66: =TEXT(B66,"mmm") -> Jul
A67: FL00066 | B67: 45787 | C67: Akasa Air | D67: QP3255 | E67: Hyderabad (HYD) | F67: Kolkata (CCU) | G67: Hyderabad | H67: Kolkata | I67: 1912 | J67: 19:15 | K67: 22:53 | N67: 233 | O67: 0 | P67: 0 | Q67: Cancelled | R67: Yes | S67: Weather | T67: 189 | U67: 0 | V67: 0 | W67: Mixed | X67: 6979 | Y67: 0 | Z67: 0 | AA67: 0 | AB67: 0 | AC67: 0 | AD67: 0 | AE67: South | AF67: East | AG67: Domestic | AH67: Airport Counter | AI67: Medium | AJ67: =TEXT(B67,"mmm") -> May
A68: FL00067 | B68: 45819 | C68: SpiceJet | D68: SG3156 | E68: Mumbai (BOM) | F68: Pune (PNQ) | G68: Mumbai | H68: Pune | I68: 1142 | J68: 07:45 | K68: 09:34 | L68: 08:14 | M68: 10:26 | N68: 154 | O68: 74 | P68: 52 | Q68: Delayed 30-120 min | R68: No | S68: Not Cancelled | T68: 180 | U68: 136 | V68: 75.56 | W68: Economy | X68: 9142 | Y68: 1243312 | Z68: 72896 | AA68: 60928 | AB68: 1377136 | AC68: 852961 | AD68: 524175 | AE68: West | AF68: West | AG68: Domestic | AH68: Online | AI68: High | AJ68: =TEXT(B68,"mmm") -> Jun
A69: FL00068 | B69: 45672 | C69: Vistara | D69: UK1975 | E69: Kolkata (CCU) | F69: Delhi (DEL) | G69: Kolkata | H69: Delhi | I69: 2113 | J69: 18:30 | K69: 22:36 | L69: 18:00 | M69: 22:45 | N69: 276 | O69: 0 | P69: 9 | Q69: Delayed <30 min | R69: No | S69: Not Cancelled | T69: 180 | U69: 118 | V69: 65.56 | W69: Economy | X69: 3383 | Y69: 399194 | Z69: 64192 | AA69: 19234 | AB69: 482620 | AC69: 345829 | AD69: 136791 | AE69: East | AF69: North | AG69: Domestic | AH69: Online | AI69: Low | AJ69: =TEXT(B69,"mmm") -> Jan
A70: FL00069 | B70: 45689 | C70: Air India | D70: AI9020 | E70: Chennai (MAA) | F70: Mumbai (BOM) | G70: Chennai | H70: Mumbai | I70: 2393 | J70: 15:00 | K70: 19:52 | L70: 15:00 | M70: 19:54 | N70: 292 | O70: 0 | P70: 2 | Q70: On Time | R70: No | S70: Not Cancelled | T70: 180 | U70: 176 | V70: 97.78 | W70: Economy | X70: 8847 | Y70: 1557072 | Z70: 68816 | AA70: 17776 | AB70: 1643664 | AC70: 1216759 | AD70: 426905 | AE70: South | AF70: West | AG70: Domestic | AH70: Corporate | AI70: Low | AJ70: =TEXT(B70,"mmm") -> Feb
A71: FL00070 | B71: 45760 | C71: SpiceJet | D71: SG7114 | E71: Bengaluru (BLR) | F71: Goa (GOI) | G71: Bengaluru | H71: Goa | I71: 439 | J71: 06:15 | K71: 07:15 | L71: 06:11 | M71: 07:21 | N71: 75 | O71: 11 | P71: 6 | Q71: Delayed <30 min | R71: No | S71: Not Cancelled | T71: 150 | U71: 108 | V71: 72 | W71: Economy | X71: 8882 | Y71: 959256 | Z71: 29376 | AA71: 11664 | AB71: 1000296 | AC71: 861118 | AD71: 139178 | AE71: South | AF71: West | AG71: Domestic | AH71: Online | AI71: Medium | AJ71: =TEXT(B71,"mmm") -> Apr
A72: FL00071 | B72: 45985 | C72: Akasa Air | D72: QP3489 | E72: Delhi (DEL) | F72: Goa (GOI) | G72: Delhi | H72: Goa | I72: 1457 | J72: 22:45 | K72: 01:30 | L72: 22:44 | M72: 02:19 | N72: 210 | O72: 44 | P72: 49 | Q72: Delayed 30-120 min | R72: No | S72: Not Cancelled | T72: 180 | U72: 149 | V72: 82.78 | W72: Business | X72: 9979 | Y72: 1486871 | Z72: 35164 | AA72: 92827 | AB72: 1614862 | AC72: 1013912 | AD72: 600950 | AE72: North | AF72: West | AG72: Domestic | AH72: Corporate | AI72: Low | AJ72: =TEXT(B72,"mmm") -> Nov
A73: FL00072 | B73: 45878 | C73: Air India Express | D73: IX7157 | E73: Chennai (MAA) | F73: Jaipur (JAI) | G73: Chennai | H73: Jaipur | I73: 1011 | J73: 16:15 | K73: 18:34 | L73: 17:06 | M73: 19:30 | N73: 154 | O73: 66 | P73: 56 | Q73: Delayed 30-120 min | R73: No | S73: Not Cancelled | T73: 180 | U73: 140 | V73: 77.78 | W73: Economy | X73: 8878 | Y73: 1242920 | Z73: 49840 | AA73: 63280 | AB73: 1356040 | AC73: 1128409 | AD73: 227631 | AE73: South | AF73: North | AG73: Domestic | AH73: Online | AI73: High | AJ73: =TEXT(B73,"mmm") -> Aug
A74: FL00073 | B74: 45950 | C74: Air India | D74: AI9679 | E74: Bengaluru (BLR) | F74: Pune (PNQ) | G74: Bengaluru | H74: Pune | I74: 1305 | J74: 08:45 | K74: 11:28 | L74: 08:00 | M74: 12:01 | N74: 208 | O74: 0 | P74: 33 | Q74: Delayed 30-120 min | R74: No | S74: Not Cancelled | T74: 189 | U74: 171 | V74: 90.48 | W74: Mixed | X74: 4194 | Y74: 717174 | Z74: 57285 | AA74: 58995 | AB74: 833454 | AC74: 573204 | AD74: 260250 | AE74: South | AF74: West | AG74: Domestic | AH74: Online | AI74: Medium | AJ74: =TEXT(B74,"mmm") -> Oct
A75: FL00074 | B75: 45665 | C75: SpiceJet | D75: SG9231 | E75: Bengaluru (BLR) | F75: Goa (GOI) | G75: Bengaluru | H75: Goa | I75: 875 | J75: 08:45 | K75: 09:57 | L75: 08:11 | M75: 10:10 | N75: 117 | O75: 11 | P75: 13 | Q75: Delayed <30 min | R75: No | S75: Not Cancelled | T75: 180 | U75: 165 | V75: 91.67 | W75: Mixed | X75: 4446 | Y75: 733590 | Z75: 26895 | AA75: 99495 | AB75: 859980 | AC75: 648273 | AD75: 211707 | AE75: South | AF75: West | AG75: Domestic | AH75: Travel Agent | AI75: Low | AJ75: =TEXT(B75,"mmm") -> Jan
A76: FL00075 | B76: 45685 | C76: Akasa Air | D76: QP9544 | E76: Jaipur (JAI) | F76: Ahmedabad (AMD) | G76: Jaipur | H76: Ahmedabad | I76: 610 | J76: 06:30 | K76: 07:43 | L76: 06:00 | M76: 07:43 | N76: 103 | O76: 0 | P76: -1 | Q76: On Time | R76: No | S76: Not Cancelled | T76: 150 | U76: 118 | V76: 78.67 | W76: Economy | X76: 6232 | Y76: 735376 | Z76: 47908 | AA76: 27376 | AB76: 810660 | AC76: 530669 | AD76: 279991 | AE76: North | AF76: West | AG76: Domestic | AH76: Travel Agent | AI76: Medium | AJ76: =TEXT(B76,"mmm") -> Jan
A77: FL00076 | B77: 45941 | C77: IndiGo | D77: 6E2834 | E77: Jaipur (JAI) | F77: Bengaluru (BLR) | G77: Jaipur | H77: Bengaluru | I77: 2370 | J77: 15:00 | K77: 20:09 | L77: 15:00 | M77: 20:09 | N77: 309 | O77: 0 | P77: -4 | Q77: On Time | R77: No | S77: Not Cancelled | T77: 220 | U77: 215 | V77: 97.73 | W77: Economy | X77: 4074 | Y77: 875910 | Z77: 111585 | AA77: 93095 | AB77: 1080590 | AC77: 645248 | AD77: 435342 | AE77: North | AF77: South | AG77: Domestic | AH77: Online | AI77: High | AJ77: =TEXT(B77,"mmm") -> Oct
A78: FL00077 | B78: 45855 | C78: IndiGo | D78: 6E5278 | E78: Hyderabad (HYD) | F78: Goa (GOI) | G78: Hyderabad | H78: Goa | I78: 1534 | J78: 09:00 | K78: 12:30 | L78: 09:15 | M78: 12:54 | N78: 210 | O78: 15 | P78: 24 | Q78: Delayed <30 min | R78: No | S78: Not Cancelled | T78: 220 | U78: 197 | V78: 89.55 | W78: Economy | X78: 10395 | Y78: 2047815 | Z78: 87271 | AA78: 49250 | AB78: 2184336 | AC78: 1286556 | AD78: 897780 | AE78: South | AF78: West | AG78: Domestic | AH78: Online | AI78: Medium | AJ78: =TEXT(B78,"mmm") -> Jul
A79: FL00078 | B79: 45998 | C79: IndiGo | D79: 6E6912 | E79: Delhi (DEL) | F79: Goa (GOI) | G79: Delhi | H79: Goa | I79: 1731 | J79: 05:30 | K79: 08:33 | L79: 05:00 | M79: 08:49 | N79: 213 | O79: 0 | P79: 16 | Q79: Delayed <30 min | R79: No | S79: Not Cancelled | T79: 220 | U79: 184 | V79: 83.64 | W79: Economy | X79: 9057 | Y79: 1666488 | Z79: 54096 | AA79: 117208 | AB79: 1837792 | AC79: 1544979 | AD79: 292813 | AE79: North | AF79: West | AG79: Domestic | AH79: Travel Agent | AI79: Low | AJ79: =TEXT(B79,"mmm") -> Dec
... A83: FL00082 | B83: 45948 | C83: IndiGo | D83: 6E205 | E83: Hyderabad (HYD) | F83: Delhi (DEL) | G83: Hyderabad | H83: Delhi | I83: 1793 | J83: 12:45 | K83: 15:48 | L83: 12:21 | M83: 15:56 | N83: 228 | O83: 21 | P83: 8 | Q83: Delayed <30 min | R83: No | S83: Not Cancelled | T83: 220 | U83: 173 | V83: 78.64 | W83: Business | X83: 6454 | Y83: 1116542 | Z83: 79753 | AA83: 58820 | AB83: 1255115 | AC83: 941579 | AD83: 313536 | AE83: South | AF83: North | AG83: Domestic | AH83: Online | AI83: High | AJ83: =TEXT(B83,"mmm") -> Oct
A84: FL00083 | B84: 45967 | C84: Air India | D84: AI5595 | E84: Delhi (DEL) | F84: Ahmedabad (AMD) | G84: Delhi | H84: Ahmedabad | I84: 2058 | J84: 05:45 | K84: 09:24 | N84: 264 | O84: 0 | P84: 0 | Q84: Cancelled | R84: Yes | S84: Crew Shortage | T84: 189 | U84: 0 | V84: 0 | W84: Economy | X84: 2809 | Y84: 0 | Z84: 0 | AA84: 0 | AB84: 0 | AC84: 0 | AD84: 0 | AE84: North | AF84: West | AG84: Domestic | AH84: Airport Counter | AI84: Medium | AJ84: =TEXT(B84,"mmm") -> Nov
A85: FL00084 | B85: 45725 | C85: IndiGo | D85: 6E6774 | E85: Chennai (MAA) | F85: Delhi (DEL) | G85: Chennai | H85: Delhi | I85: 495 | J85: 22:45 | K85: 23:20 | L85: 22:22 | M85: 23:27 | N85: 80 | O85: 22 | P85: 7 | Q85: Delayed <30 min | R85: No | S85: Not Cancelled | T85: 180 | U85: 134 | V85: 74.44 | W85: Mixed | X85: 3430 | Y85: 459620 | Z85: 39932 | AA85: 101974 | AB85: 601526 | AC85: 353150 | AD85: 248376 | AE85: South | AF85: North | AG85: Domestic | AH85: Travel Agent | AI85: Medium | AJ85: =TEXT(B85,"mmm") -> Mar
A86: FL00085 | B86: 45735 | C86: Vistara | D86: UK8732 | E86: Mumbai (BOM) | F86: Delhi (DEL) | G86: Mumbai | H86: Delhi | I86: 1270 | J86: 17:00 | K86: 19:39 | L86: 17:00 | M86: 20:06 | N86: 159 | O86: 0 | P86: 27 | Q86: Delayed <30 min | R86: No | S86: Not Cancelled | T86: 180 | U86: 161 | V86: 89.44 | W86: Mixed | X86: 5149 | Y86: 828989 | Z86: 27048 | AA86: 109319 | AB86: 965356 | AC86: 769679 | AD86: 195677 | AE86: West | AF86: North | AG86: Domestic | AH86: Travel Agent | AI86: Low | AJ86: =TEXT(B86,"mmm") -> Mar
A87: FL00086 | B87: 45730 | C87: IndiGo | D87: 6E5289 | E87: Hyderabad (HYD) | F87: Jaipur (JAI) | G87: Hyderabad | H87: Jaipur | I87: 1057 | J87: 12:00 | K87: 14:35 | L87: 12:39 | M87: 15:09 | N87: 155 | O87: 39 | P87: 34 | Q87: Delayed 30-120 min | R87: No | S87: Not Cancelled | T87: 189 | U87: 152 | V87: 80.42 | W87: Economy | X87: 4535 | Y87: 689320 | Z87: 30248 | AA87: 25232 | AB87: 744800 | AC87: 551068 | AD87: 193732 | AE87: South | AF87: North | AG87: Domestic | AH87: Online | AI87: Medium | AJ87: =TEXT(B87,"mmm") -> Mar
A88: FL00087 | B88: 45829 | C88: Akasa Air | D88: QP9524 | E88: Jaipur (JAI) | F88: Kolkata (CCU) | G88: Jaipur | H88: Kolkata | I88: 1844 | J88: 06:15 | K88: 10:10 | L88: 06:25 | M88: 10:39 | N88: 250 | O88: 25 | P88: 29 | Q88: Delayed <30 min | R88: No | S88: Not Cancelled | T88: 180 | U88: 119 | V88: 66.11 | W88: Economy | X88: 5293 | Y88: 629867 | Z88: 36533 | AA88: 87108 | AB88: 753508 | AC88: 622805 | AD88: 130703 | AE88: North | AF88: East | AG88: Domestic | AH88: Online | AI88: Medium | AJ88: =TEXT(B88,"mmm") -> Jun
A89: FL00088 | B89: 45801 | C89: Air India Express | D89: IX4543 | E89: Delhi (DEL) | F89: Hyderabad (HYD) | G89: Delhi | H89: Hyderabad | I89: 979 | J89: 17:30 | K89: 19:08 | L89: 17:27 | M89: 19:56 | N89: 128 | O89: 27 | P89: 48 | Q89: Delayed 30-120 min | R89: No | S89: Not Cancelled | T89: 186 | U89: 148 | V89: 79.57 | W89: Economy | X89: 9921 | Y89: 1468308 | Z89: 56240 | AA89: 38480 | AB89: 1563028 | AC89: 1191880 | AD89: 371148 | AE89: North | AF89: South | AG89: Domestic | AH89: Online | AI89: Low | AJ89: =TEXT(B89,"mmm") -> May
A90: FL00089 | B90: 45808 | C90: IndiGo | D90: 6E9893 | E90: Hyderabad (HYD) | F90: Jaipur (JAI) | G90: Hyderabad | H90: Jaipur | I90: 690 | J90: 22:00 | K90: 23:52 | L90: 22:44 | M90: 00:39 | N90: 112 | O90: 44 | P90: 47 | Q90: Delayed 30-120 min | R90: No | S90: Not Cancelled | T90: 180 | U90: 150 | V90: 83.33 | W90: Economy | X90: 8235 | Y90: 1235250 | Z90: 37500 | AA90: 51450 | AB90: 1324200 | AC90: 850868 | AD90: 473332 | AE90: South | AF90: North | AG90: Domestic | AH90: Airport Counter | AI90: Low | AJ90: =TEXT(B90,"mmm") -> May
A91: FL00090 | B91: 45815 | C91: SpiceJet | D91: SG7729 | E91: Hyderabad (HYD) | F91: Goa (GOI) | G91: Hyderabad | H91: Goa | I91: 483 | J91: 14:15 | K91: 15:30 | L91: 14:00 | M91: 15:30 | N91: 90 | O91: 0 | P91: -5 | Q91: On Time | R91: No | S91: Not Cancelled | T91: 150 | U91: 134 | V91: 89.33 | W91: Economy | X91: 5778 | Y91: 774252 | Z91: 47570 | AA91: 48910 | AB91: 870732 | AC91: 719872 | AD91: 150860 | AE91: South | AF91: West | AG91: Domestic | AH91: Online | AI91: High | AJ91: =TEXT(B91,"mmm") -> Jun
A92: FL00091 | B92: 45978 | C92: Air India Express | D92: IX5017 | E92: Mumbai (BOM) | F92: Kolkata (CCU) | G92: Mumbai | H92: Kolkata | I92: 587 | J92: 18:45 | K92: 19:43 | L92: 18:00 | M92: 19:43 | N92: 103 | O92: 0 | P92: -1 | Q92: On Time | R92: No | S92: Not Cancelled | T92: 180 | U92: 151 | V92: 83.89 | W92: Economy | X92: 3645 | Y92: 550395 | Z92: 25519 | AA92: 114307 | AB92: 690221 | AC92: 457841 | AD92: 232380 | AE92: West | AF92: East | AG92: Domestic | AH92: Corporate | AI92: Low | AJ92: =TEXT(B92,"mmm") -> Nov
A93: FL00092 | B93: 45717 | C93: IndiGo | D93: 6E6588 | E93: Delhi (DEL) | F93: Bengaluru (BLR) | G93: Delhi | H93: Bengaluru | I93: 991 | J93: 09:30 | K93: 11:25 | L93: 09:13 | M93: 11:25 | N93: 145 | O93: 13 | P93: -6 | Q93: Delayed <30 min | R93: No | S93: Not Cancelled | T93: 180 | U93: 159 | V93: 88.33 | W93: Economy | X93: 8248 | Y93: 1311432 | Z93: 48495 | AA93: 45951 | AB93: 1405878 | AC93: 927339 | AD93: 478539 | AE93: North | AF93: South | AG93: Domestic | AH93: Online | AI93: Medium | AJ93: =TEXT(B93,"mmm") -> Mar
A94: FL00093 | B94: 45760 | C94: Vistara | D94: UK1482 | E94: Delhi (DEL) | F94: Chennai (MAA) | G94: Delhi | H94: Chennai | I94: 1753 | J94: 12:00 | K94: 16:10 | L94: 12:00 | M94: 16:27 | N94: 250 | O94: 0 | P94: 17 | Q94: Delayed <30 min | R94: No | S94: Not Cancelled | T94: 150 | U94: 114 | V94: 76 | W94: Economy | X94: 4349 | Y94: 495786 | Z94: 43092 | AA94: 79458 | AB94: 618336 | AC94: 537424 | AD94: 80912 | AE94: North | AF94: South | AG94: Domestic | AH94: Online | AI94: Low | AJ94: =TEXT(B94,"mmm") -> Apr
A95: FL00094 | B95: 45806 | C95: Air India | D95: AI8093 | E95: Goa (GOI) | F95: Pune (PNQ) | G95: Goa | H95: Pune | I95: 2261 | J95: 14:30 | K95: 18:56 | L95: 14:36 | M95: 19:34 | N95: 296 | O95: 36 | P95: 38 | Q95: Delayed 30-120 min | R95: No | S95: Not Cancelled | T95: 150 | U95: 127 | V95: 84.67 | W95: Economy | X95: 7598 | Y95: 964946 | Z95: 58039 | AA95: 35814 | AB95: 1058799 | AC95: 661507 | AD95: 397292 | AE95: West | AF95: West | AG95: Domestic | AH95: Online | AI95: High | AJ95: =TEXT(B95,"mmm") -> May
A96: FL00095 | B96: 45889 | C96: IndiGo | D96: 6E9751 | E96: Jaipur (JAI) | F96: Delhi (DEL) | G96: Jaipur | H96: Delhi | I96: 2298 | J96: 07:00 | K96: 12:07 | L96: 07:00 | M96: 12:25 | N96: 307 | O96: 0 | P96: 18 | Q96: Delayed <30 min | R96: No | S96: Not Cancelled | T96: 189 | U96: 111 | V96: 58.73 | W96: Mixed | X96: 6697 | Y96: 743367 | Z96: 42291 | AA96: 42513 | AB96: 828171 | AC96: 638652 | AD96: 189519 | AE96: North | AF96: North | AG96: Domestic | AH96: Travel Agent | AI96: High | AJ96: =TEXT(B96,"mmm") -> Aug
... A124: FL00123 | B124: 45849 | C124: Air India | D124: AI6476 | E124: Kolkata (CCU) | F124: Hyderabad (HYD) | G124: Kolkata | H124: Hyderabad | I124: 2150 | J124: 14:30 | K124: 18:22 | L124: 14:15 | M124: 18:59 | N124: 262 | O124: 15 | P124: 37 | Q124: Delayed 30-120 min | R124: No | S124: Not Cancelled | T124: 220 | U124: 160 | V124: 72.73 | W124: Economy | X124: 4317 | Y124: 690720 | Z124: 47360 | AA124: 69120 | AB124: 807200 | AC124: 693245 | AD124: 113955 | AE124: East | AF124: South | AG124: Domestic | AH124: Online | AI124: Medium | AJ124: =TEXT(B124,"mmm") -> Jul
A125: FL00124 | B125: 45766 | C125: Akasa Air | D125: QP3411 | E125: Ahmedabad (AMD) | F125: Jaipur (JAI) | G125: Ahmedabad | H125: Jaipur | I125: 2302 | J125: 16:00 | K125: 20:39 | N125: 279 | O125: 0 | P125: 0 | Q125: Cancelled | R125: Yes | S125: Operational Issue | T125: 150 | U125: 0 | V125: 0 | W125: Economy | X125: 6541 | Y125: 0 | Z125: 0 | AA125: 0 | AB125: 0 | AC125: 0 | AD125: 0 | AE125: West | AF125: North | AG125: Domestic | AH125: Travel Agent | AI125: Low | AJ125: =TEXT(B125,"mmm") -> Apr
A126: FL00125 | B126: 45739 | C126: Air India | D126: AI1874 | E126: Hyderabad (HYD) | F126: Jaipur (JAI) | G126: Hyderabad | H126: Jaipur | I126: 1285 | J126: 09:30 | K126: 11:49 | L126: 09:06 | M126: 11:49 | N126: 169 | O126: 6 | P126: 0 | Q126: Delayed <30 min | R126: No | S126: Not Cancelled | T126: 220 | U126: 203 | V126: 92.27 | W126: Economy | X126: 7458 | Y126: 1513974 | Z126: 54201 | AA126: 96628 | AB126: 1664803 | AC126: 1042660 | AD126: 622143 | AE126: South | AF126: North | AG126: Domestic | AH126: Online | AI126: Medium | AJ126: =TEXT(B126,"mmm") -> Mar
A127: FL00126 | B127: 46007 | C127: Akasa Air | D127: QP4108 | E127: Chennai (MAA) | F127: Mumbai (BOM) | G127: Chennai | H127: Mumbai | I127: 617 | J127: 12:15 | K127: 13:44 | L127: 12:40 | M127: 14:18 | N127: 104 | O127: 40 | P127: 34 | Q127: Delayed 30-120 min | R127: No | S127: Not Cancelled | T127: 150 | U127: 118 | V127: 78.67 | W127: Economy | X127: 7118 | Y127: 839924 | Z127: 50504 | AA127: 59826 | AB127: 950254 | AC127: 737100 | AD127: 213154 | AE127: South | AF127: West | AG127: Domestic | AH127: Corporate | AI127: Medium | AJ127: =TEXT(B127,"mmm") -> Dec
A128: FL00127 | B128: 45730 | C128: Air India | D128: AI3359 | E128: Chennai (MAA) | F128: Jaipur (JAI) | G128: Chennai | H128: Jaipur | I128: 2239 | J128: 10:15 | K128: 15:06 | L128: 10:49 | M128: 16:04 | N128: 306 | O128: 49 | P128: 58 | Q128: Delayed 30-120 min | R128: No | S128: Not Cancelled | T128: 150 | U128: 112 | V128: 74.67 | W128: Economy | X128: 6161 | Y128: 690032 | Z128: 34160 | AA128: 11872 | AB128: 736064 | AC128: 458404 | AD128: 277660 | AE128: South | AF128: North | AG128: Domestic | AH128: Corporate | AI128: Medium | AJ128: =TEXT(B128,"mmm") -> Mar
A129: FL00128 | B129: 45859 | C129: IndiGo | D129: 6E1542 | E129: Hyderabad (HYD) | F129: Mumbai (BOM) | G129: Hyderabad | H129: Mumbai | I129: 1800 | J129: 22:45 | K129: 02:10 | L129: 22:10 | M129: 02:10 | N129: 250 | O129: 10 | P129: 0 | Q129: Delayed <30 min | R129: No | S129: Not Cancelled | T129: 189 | U129: 152 | V129: 80.42 | W129: Economy | X129: 6499 | Y129: 987848 | Z129: 53656 | AA129: 88920 | AB129: 1130424 | AC129: 809610 | AD129: 320814 | AE129: South | AF129: West | AG129: Domestic | AH129: Travel Agent | AI129: Low | AJ129: =TEXT(B129,"mmm") -> Jul
A130: FL00129 | B130: 45724 | C130: Air India | D130: AI8039 | E130: Jaipur (JAI) | F130: Pune (PNQ) | G130: Jaipur | H130: Pune | I130: 1528 | J130: 15:00 | K130: 18:48 | L130: 15:00 | M130: 18:48 | N130: 228 | O130: 0 | P130: -10 | Q130: On Time | R130: No | S130: Not Cancelled | T130: 180 | U130: 139 | V130: 77.22 | W130: Economy | X130: 4969 | Y130: 690691 | Z130: 38086 | AA130: 90072 | AB130: 818849 | AC130: 709758 | AD130: 109091 | AE130: North | AF130: West | AG130: Domestic | AH130: Online | AI130: High | AJ130: =TEXT(B130,"mmm") -> Mar
A131: FL00130 | B131: 45942 | C131: Vistara | D131: UK5719 | E131: Goa (GOI) | F131: Delhi (DEL) | G131: Goa | H131: Delhi | I131: 2286 | J131: 17:30 | K131: 22:12 | L131: 17:00 | M131: 22:12 | N131: 312 | O131: 0 | P131: -10 | Q131: On Time | R131: No | S131: Not Cancelled | T131: 186 | U131: 148 | V131: 79.57 | W131: Economy | X131: 7716 | Y131: 1141968 | Z131: 78144 | AA131: 65416 | AB131: 1285528 | AC131: 915466 | AD131: 370062 | AE131: West | AF131: North | AG131: Domestic | AH131: Online | AI131: Low | AJ131: =TEXT(B131,"mmm") -> Oct
A132: FL00131 | B132: 45678 | C132: IndiGo | D132: 6E458 | E132: Jaipur (JAI) | F132: Hyderabad (HYD) | G132: Jaipur | H132: Hyderabad | I132: 1185 | J132: 16:30 | K132: 18:55 | L132: 16:07 | M132: 18:55 | N132: 175 | O132: 7 | P132: -6 | Q132: Delayed <30 min | R132: No | S132: Not Cancelled | T132: 189 | U132: 90 | V132: 47.62 | W132: Mixed | X132: 6635 | Y132: 597150 | Z132: 43830 | AA132: 18270 | AB132: 659250 | AC132: 446804 | AD132: 212446 | AE132: North | AF132: South | AG132: Domestic | AH132: Corporate | AI132: Medium | AJ132: =TEXT(B132,"mmm") -> Jan
A133: FL00132 | B133: 45941 | C133: Akasa Air | D133: QP2760 | E133: Delhi (DEL) | F133: Goa (GOI) | G133: Delhi | H133: Goa | I133: 2259 | J133: 09:00 | K133: 14:23 | N133: 323 | O133: 0 | P133: 0 | Q133: Cancelled | R133: Yes | S133: Operational Issue | T133: 189 | U133: 0 | V133: 0 | W133: Economy | X133: 6011 | Y133: 0 | Z133: 0 | AA133: 0 | AB133: 0 | AC133: 0 | AD133: 0 | AE133: North | AF133: West | AG133: Domestic | AH133: Online | AI133: Low | AJ133: =TEXT(B133,"mmm") -> Oct
A134: FL00133 | B134: 45703 | C134: Akasa Air | D134: QP982 | E134: Chennai (MAA) | F134: Kolkata (CCU) | G134: Chennai | H134: Kolkata | I134: 1015 | J134: 16:15 | K134: 18:12 | L134: 16:18 | M134: 18:48 | N134: 132 | O134: 18 | P134: 36 | Q134: Delayed 30-120 min | R134: No | S134: Not Cancelled | T134: 180 | U134: 120 | V134: 66.67 | W134: Business | X134: 7294 | Y134: 875280 | Z134: 42240 | AA134: 71760 | AB134: 989280 | AC134: 745109 | AD134: 244171 | AE134: South | AF134: East | AG134: Domestic | AH134: Corporate | AI134: High | AJ134: =TEXT(B134,"mmm") -> Feb
A135: FL00134 | B135: 45832 | C135: Air India | D135: AI9194 | E135: Kolkata (CCU) | F135: Pune (PNQ) | G135: Kolkata | H135: Pune | I135: 714 | J135: 19:45 | K135: 20:52 | N135: 112 | O135: 0 | P135: 0 | Q135: Cancelled | R135: Yes | S135: Weather | T135: 150 | U135: 0 | V135: 0 | W135: Economy | X135: 6735 | Y135: 0 | Z135: 0 | AA135: 0 | AB135: 0 | AC135: 0 | AD135: 0 | AE135: East | AF135: West | AG135: Domestic | AH135: Online | AI135: Low | AJ135: =TEXT(B135,"mmm") -> Jun
A136: FL00135 | B136: 45944 | C136: Air India Express | D136: IX4217 | E136: Pune (PNQ) | F136: Ahmedabad (AMD) | G136: Pune | H136: Ahmedabad | I136: 2099 | J136: 20:15 | K136: 00:23 | L136: 20:01 | M136: 00:23 | N136: 263 | O136: 1 | P136: -7 | Q136: Delayed <30 min | R136: No | S136: Not Cancelled | T136: 180 | U136: 126 | V136: 70 | W136: Economy | X136: 6952 | Y136: 875952 | Z136: 46746 | AA136: 50652 | AB136: 973350 | AC136: 853787 | AD136: 119563 | AE136: West | AF136: West | AG136: Domestic | AH136: Online | AI136: High | AJ136: =TEXT(B136,"mmm") -> Oct
...
